Workbook

Sheet LEIA-ME
B1: REORDENAMENTO 2027 — SEDUC-PI / SUPEX / UGERF / GDI
B2: Três versões da aba Reordenamento 2027 no mesmo arquivo, para comparar antes de decidir.
B4: AS TRÊS VERSÕES
B5: Reordenamento 2027 — V1. Retrato exato da aba que existe hoje na Proposta. Nada foi recalculado: é o ponto de partida para comparação.
B6: Reordenamento 2027 V2 — mesma estrutura e mesmas 38 colunas da V1, com o que estava sem funcionar já funcionando.
B7: Reordenamento 2027 V3 — a V2 mais os pedidos novos: anexos, fusão entre escolas, UETEP, UEJA, fundamental e 2ª/3ª série editáveis.
B9: O QUE ESTAVA QUEBRADO NA V1 E FOI CORRIGIDO NA V2
B10: Ainda faltam no município — devolvia "—" em todas as 576 linhas. O município vinha acentuado da Base GDI e o Panorama Municipal guarda o nome sem acento, então o PROCV nunca achava. Agora as duas pontas usam o nome sem acento e a coluna responde ao que for digitado na 1ª série.
B11: Panorama Municipal — as colunas Turmas decididas / Saldo / Cobertura estavam com #ERROR!. Usavam coluna inteira ($C:$C e $M:$M), o que fecha um ciclo de dependência no Google Sheets. Agora o intervalo é limitado às linhas que existem.
B12: Salas necessárias 2027 — estava preenchida em 1 das 576 linhas. Como Situação da sala e Resumo 2027 dependem dela, as duas saíam vazias ("Necessidade: salas |"). Agora todas vêm calculadas pelo motor e continuam editáveis.
B13: Possíveis fusões de turmas — devolvia "—" em toda a coluna. Voltou a ser calculada, e a coluna ao lado conta quantas turmas saem e quantas chegam segundo a aba Fusão Turmas.
B14: IDEB, ANEXOS e CURSOS — colunas existiam no cabeçalho e nunca foram preenchidas. Agora saem das abas IDEB Municípios, Base Anexos e Base UETEP.
... B41: Atualizar tudo — refaz Base Tratada, Base Anexos, Base UETEP, Base UEJA, Fusão Entre Escolas e Panorama, e reescreve as colunas calculadas das três versões sem tocar nas colunas ★.

Sheet Reordenamento 2027
A1: INEP | B1: GRE | C1: Município | D1: Escola | E1: Turmas hoje (2026) | F1: Turmas 2027 (projeção) | G1: Oferta Fundamental | H1: 9º Ano do município | I1: Ainda faltam no município | J1: ★ FUNDAMENTAL 2027 — DECIDA AQUI | K1: IDEB | L1: 1ª Série 2026 | M1: ★ 1ª SÉRIE 2027 DECIDA AQUI | N1: Cursos EM 2026 (sem EJA) | O1: ★ CURSOS 1ª SÉRIE 2027 — DECIDA AQUI | P1: ALTERAÇÃO DE CURSOS EMI | Q1: 2ª Série 2027 | R1: 3ª Série 2027 | S1: Parciais 2026 | T1: Parciais 2026 justificativa | U1: Possíveis Fusões de Turmas | V1: Validações Fusões Turmas | W1: Salas existentes | X1: ★ SALAS NECESSÁRIAS 2027 — DECIDA AQUI | Y1: Situação da sala | Z1: Oferta EJA 2026 | AA1: Matrículas / Turmas EJA | AB1: ★ EJA Turmas 2027 | AC1: ★ EJA Cursos 2027 | AD1: ANEXOS | AE1: CURSOS | AG1: Resumo 2027 | AH1: Escola Próxima | AI1: Reordenamento 2027 | AJ1: Justificativa | AK1: Observação | AL1: ✓ Pronto
A2: 22129723 | B2: 01ª - PARNAÍBA | C2: BOM PRINCIPIO DO PIAUI | D2: CETI DARCY RIBEIRO | E2: POSSUI 06 SLS E NECESSITA 09 SLS 08 TURMA(S) MÉDIO INTEGRAL 03 turma(s) - 1ª série 03 turma(s) - 2ª série 02 turma(s) - 3ª série MANHÃ - 01 TURMA(S) MÉDIO PARCIAL 01 turma(s) - 3ª série NOITE - 06 TURMA(S) EJA | F2: POSSUI 09 SLS E NECESSITA 09 SLS (03 salas foram construídas por pactue/ata) 09 TURMA(S) MÉDIO INTEGRAL 03 turma(s) - 1ª série 03 turma(s) - 2ª série 03 turma(s) - 3ª série NOITE - 06 TURMA(S) EJA | G2: — | H2: 84 alunos · 3 turmas | I2: — | L2: 3 | N2: • EM - 3ª Série - PARCIAL DIURNO - 30 matrículas M - 1 turma • EPT EMI - 1ª Série - CURSO TECNICO EM ADMINISTRACAO COM ENFASE EM EMPREENDEDORISMO - 76 matrículas I - 2 turmas • EPT EMI - 1ª Série - CURSO TECNICO EM LOGISTICA - 39 matrículas I - 1 turma • EPT EMI - 2ª Série - CURSO TECNICO EM DESENVOLVIMENTO DE SISTEMAS - 36 matrículas I - 1 turma • EPT EMI - 2ª Série - CURSO TECNICO EM MARKETING DIGITAL - 62 matrículas I - 2 turmas • EPT EMI - 3ª Série - CURSO TECNICO EM DESENVOLVIMENTO DE SISTEMAS - 53 matrículas I - 2 turmas Turmas: 8 Integral | 1 Manhã | Q2: 3 | R2: 3 | S2: EM - 3ª Série | MANHÃ | 1T (30 al.) | U2: — | W2: 9 | X2: 11 | Y2: Construir 2 SALAS | Z2: • EJA EF I 1/6 - ANOS INICIAIS - 203 matrículas N - 13 turmas • EJA EM 2/2 - ALTERNATIVO - 9 matrículas N - 1 turma • EPT EJA EMI 2/5 - CURSO TECNICO EM ADMINISTRACAO - 19 matrículas N - 1 turma • EPT EJA EMI 4/5 - CURSO TECNICO EM INFORMATICA - 28 matrículas N - 1 turma Turmas EJA: 16 Noite | AA2: 259 matrículas | 16 turmas | AG2: 3 de 1ª | 3 de 2ª | 3 de 3ª | Necessidade: 11 salas | Construir 2 SALAS | AH2: Única no município
A3: 22012419 | B3: 01ª - PARNAÍBA | C3: BURITI DOS LOPES | D3: CETI ZEZITA SAMPAIO | E3: POSSUI 05 SLS E NECESSITA 05 SLS 04 TURMA(S) MÉDIO INTEGRAL 02 turma(s) - 1ª série 02 turma(s) - 2ª série MANHÃ - 01 TURMA(S) PARCIAL 01 turma(s) MÉDIO - 3ª série TARDE - 01 TURMA(S) PARCIAIS 01 turma(s) MÉDIO - 3ª série | F3: POSSUI 05 SLS E NECESSITA 05 SLS 06 TURMA(S) MÉDIO INTEGRAL 01 turma(s) - 1ª série 02 turma(s) - 2ª série 02 turma(s) - 3ª série | G3: — | H3: 318 alunos · 8 turmas | I3: — | L3: 2 | N3: • EM - 3ª Série - PARCIAL DIURNO - 63 matrículas T - 1 turma • EM - 3ª Série - PARCIAL DIURNO - 65 matrículas M - 1 turma • EPT EMI - 1ª Série - CURSO TECNICO EM MARKETING DIGITAL - 79 matrículas I - 2 turmas • EPT EMI - 2ª Série - CURSO TECNICO EM AGENTE COMUNITARIO DE SAUDE - 72 matrículas I - 2 turmas Turmas: 4 Integral | 1 Manhã | 1 Tarde | Q3: 2 | R3: 2 | S3: EM - 3ª Série | MANHÃ | 1T (65 al.) EM - 3ª Série | TARDE | 1T (63 al.) | U3: — | W3: 5 | Z3: • EJA EF I 1/6 - ANOS INICIAIS - 92 matrículas N - 7 turmas Turmas EJA: 7 Noite | AA3: 92 matrículas | 7 turmas | AG3: 2 de 1ª | 2 de 2ª | 2 de 3ª | Necessidade: salas | | AH3: CEJA LEÔNIDAS MELO CEJA | EJA (7.86 km)
A4: 22012508 | B4: 01ª - PARNAÍBA | C4: BURITI DOS LOPES | D4: CEJA LEÔNIDAS MELO | E4: POSSUI 07 SLS E NECESSITA 07 SLS TARDE - 03 TURMA(S) DE EJA 01 turma(s) - EJA EF II 1/2 01 turma(s) - EPT EJA EMI 1/5 01 turma(s) - EPT EJA EMI 3/5 NOITE - 07 TURMA(S) DE EJA 01 turma(s) - EJA EF I 1/6 01 turma(s) - EJA EM 1/2 01 turma(s) - EPT EJA EMI 1/5 01 turma(s) - EPT EJA EMI 3/5 01 turma(s) - EPT EJA EMI 3/5 01 turma(s) - EPT EJA EMI 5/5 01 turma(s) - EPT EJA EMI 5/5 | F4: POSSUI 07 SLS E NECESSITA 07 SLS TARDE - 03 TURMA(S) DE EJA 01 turma(s) - EJA EF II 1/2 01 turma(s) - EPT EJA EMI 1/5 01 turma(s) - EPT EJA EMI 3/5 NOITE - 07 TURMA(S) DE EJA 01 turma(s) - EJA EF I 1/6 01 turma(s) - EJA EM 1/2 01 turma(s) - EPT EJA EMI 1/5 01 turma(s) - EPT EJA EMI 3/5 01 turma(s) - EPT EJA EMI 3/5 01 turma(s) - EPT EJA EMI 5/5 01 turma(s) - EPT EJA EMI 5/5 | G4: — | H4: 318 alunos · 8 turmas | I4: — | L4: 0 | N4: — | Q4: 0 | R4: 0 | S4: — | U4: — | W4: 7 | Z4: • EJA EF I 1/6 - ANOS INICIAIS - 84 matrículas N - 4 turmas • EJA EF I 5/6 - ANOS INICIAIS - 0 matrículas N - 1 turma • EJA EF II 2/2 - ALTERNATIVA - 17 matrículas T - 1 turma • EJA EM 2/2 - ALTERNATIVO - 12 matrículas N - 1 turma • EPT EJA EMI 1/5 - CURSO TECNICO EM SEGURANCA DO TRABALHO - 22 matrículas T - 1 turma • EPT EJA EMI 2/5 - CURSO TECNICO EM AGENTE COMUNITARIO DE SAUDE - 15 matrículas N - 1 turma • EPT EJA EMI 2/5 - CURSO TECNICO EM SEGURANCA DO TRABALHO - 16 matrículas T - 1 turma • EPT EJA EMI 4/5 - CURSO TECNICO EM ADMINISTRACAO - 17 matrículas T - 1 turma • EPT EJA EMI 4/5 - CURSO TECNICO EM ADMINISTRACAO - 18 matrículas N - 1 turma • EPT EJA EMI 4/5 - CURSO TECNICO EM CONTROLE AMBIENTAL - 4 matrículas N - 1 turma Turmas EJA: 4 Tarde | 9 Noite | AA4: 205 matrículas | 13 turmas | AG4: 0 de 1ª | 0 de 2ª | 0 de 3ª | Necessidade: salas | | AH4: CETI ZEZITA SAMPAIO CETI (0.44 km)
A5: 22137947 | B5: 01ª - PARNAÍBA | C5: BURITI DOS LOPES | D5: CETI DEPUTADA FRANCISCA TRINDADE | E5: POSSUI 08 SLS E NECESSITA 14 SLS 14 TURMA(S) MÉDIO INTEGRAL 06 turma(s) - 1ª série 04 turma(s) - 2ª série 04 turma(s) - 3ª série | F5: POSSUI 14 SLS E NECESSITA 14 SLS 14 TURMA(S) MÉDIO INTEGRAL 04 turma(s) - 1ª série 06 turma(s) - 2ª série 04 turma(s) - 3ª série | G5: — | H5: 318 alunos · 8 turmas | I5: — | L5: 6 | N5: • EM - 3ª Série - INTEGRAL - 64 matrículas I - 2 turmas • EM - 3ª Série - PARCIAL DIURNO - 25 matrículas T - 1 turma • EPT EMI - 1ª Série - CURSO TECNICO EM DESENVOLVIMENTO DE SISTEMAS - 69 matrículas I - 2 turmas • EPT EMI - 1ª Série - CURSO TECNICO EM FARMACIA - 36 matrículas I - 1 turma • EPT EMI - 1ª Série - CURSO TECNICO EM SISTEMAS DE ENERGIA RENOVAVEL - 65 matrículas I - 2 turmas • EPT EMI - 2ª Série - CURSO TECNICO EM ADMINISTRACAO COM ENFASE EM EMPREENDEDORISMO - 30 matrículas I - 1 turma • EPT EMI - 2ª Série - CURSO TECNICO EM DESENVOLVIMENTO DE SISTEMAS - 39 matrículas I - 1 turma • EPT EMI - 2ª Série - CURSO TECNICO EM MARKETING DIGITAL - 70 matrículas I - 2 turmas • EPT EMI - 3ª Série - CURSO TECNICO EM DESENVOLVIMENTO DE SISTEMAS - 31 matrículas I - 1 turma Turmas: 12 Integral | 1 Tarde | Q5: 6 | R5: 4 | S5: EM - 3ª Série | TARDE | 1T (25 al.) | U5: — | W5: 14 | Z5: • EJA EF I 1/6 - ANOS INICIAIS - 89 matrículas N - 6 turmas • EPT EMI - 1ª Série - CURSO TECNICO EM PLANEJAMENTO E CONTROLE DA PRODUCAO - 38 matrículas I - 1 turma Turmas EJA: 1 Integral | 6 Noite | AA5: 127 matrículas | 7 turmas | AG5: 6 de 1ª | 6 de 2ª | 4 de 3ª | Necessidade: salas | | AH5: CETI ZEZITA SAMPAIO CETI (0.69 km)
A6: 22162607 | B6: 01ª - PARNAÍBA | C6: BURITI DOS LOPES | D6: CETI PEDRO MARIANO DE FREITAS | E6: POSSUI 04 SLS E NECESSITA 06 SLS 06 TURMA(S) MÉDIO INTEGRAL 02 turma(s) - 1ª série 02 turma(s) - 2ª série 02 turma(s) - 3ª série NOITE - 04 TURMA(S) DE EJA 02 turma(s) - EJA EF I 1/6 01 turma(s) - EPT EJA EMI 1/5 01 turma(s) - EPT EJA EMI 3/5 | F6: POSSUI 06 SLS E NECESSITA 06 SLS (01 sala foi construída por pactue; 01 sala está sendo construída por ata) 06 TURMA(S) MÉDIO INTEGRAL 02 turma(s) - 1ª série 02 turma(s) - 2ª série 02 turma(s) - 3ª série NOITE - 04 TURMA(S) DE EJA 02 turma(s) - EJA EF I 1/6 01 turma(s) - EPT EJA EMI 1/5 01 turma(s) - EPT EJA EMI 3/5 | G6: — | H6: 318 alunos · 8 turmas | I6: — | L6: 2 | N6: • EM - 3ª Série - INTEGRAL - 33 matrículas I - 1 turma • EPT EMI - 1ª Série - CURSO TECNICO EM AGROPECUARIA - 33 matrículas I - 1 turma • EPT EMI - 1ª Série - CURSO TECNICO EM SEGURANCA DO TRABALHO - 36 matrículas I - 1 turma • EPT EMI - 2ª Série - CURSO TECNICO EM AGROPECUARIA - 55 matrículas I - 2 turmas • EPT EMI - 3ª Série - CURSO TECNICO EM GUIA DE TURISMO - 22 matrículas I - 1 turma • EPT EMS 1/2 - CURSO TECNICO EM AGROPECUARIA - 40 matrículas N - 1 turma Turmas: 6 Integral | 1 Noite | Q6: 2 | R6: 2 | S6: — | U6: — | W6: 6 | Z6: • EJA EF I 1/6 - ANOS INICIAIS - 75 matrículas N - 4 turmas • EPT EJA EMI 2/5 - CURSO TECNICO EM AGENTE COMUNITARIO DE SAUDE - 11 matrículas N - 1 turma • EPT EJA EMI 4/5 - CURSO TECNICO EM CONTROLE AMBIENTAL - 0 matrículas N - 1 turma Turmas EJA: 6 Noite | AA6: 86 matrículas | 6 turmas | AG6: 2 de 1ª | 2 de 2ª | 2 de 3ª | Necessidade: salas | | AH6: CETI DEPUTADA FRANCISCA TRINDADE CETI (10.45 km)
A7: 22014306 | B7: 01ª - PARNAÍBA | C7: CAJUEIRO DA PRAIA | D7: CETI MANOEL RICARDO | E7: POSSUI 09 SLS E NECESSITA DE 08 SLS 08 TURMA(S) MÉDIO INTEGRAL 03 turma(s) - 1ª série 03 turma(s) - 2ª série 02 turma(s) - 3ª série NOITE - 01 TURMA(S) DE EJA 01 turma(s) - EPT EJA EMI 1/5 | F7: POSSUI 09 SLS E NECESSITA DE 09 SLS 09 TURMA(S) MÉDIO INTEGRAL 03 turma(s) - 1ª série 03 turma(s) - 2ª série 03 turma(s) - 3ª série NOITE - 01 TURMA(S) DE EJA 01 turma(s) - EPT EJA EMI 1/5 | G7: — | H7: 114 alunos · 3 turmas | I7: — | L7: 3 | N7: • EPT EMI - 1ª Série - CURSO TECNICO EM CONTROLE AMBIENTAL - 42 matrículas I - 1 turma • EPT EMI - 1ª Série - CURSO TECNICO EM GUIA DE TURISMO - 42 matrículas I - 1 turma • EPT EMI - 1ª Série - CURSO TECNICO EM HOSPEDAGEM - 42 matrículas I - 1 turma • EPT EMI - 2ª Série - CURSO TECNICO EM AGENTE COMUNITARIO DE SAUDE - 39 matrículas I - 1 turma • EPT EMI - 2ª Série - CURSO TECNICO EM GUIA DE TURISMO - 38 matrículas I - 1 turma • EPT EMI - 2ª Série - CURSO TECNICO EM SERVICOS DE RESTAURANTE E BAR - 28 matrículas I - 1 turma • EPT EMI - 3ª Série - CURSO TECNICO EM DESENVOLVIMENTO DE SISTEMAS - 43 matrículas I - 2 turmas • EPT EMI - 3ª Série - CURSO TECNICO EM GUIA DE TURISMO - 30 matrículas I - 1 turma Turmas: 9 Integral | Q7: 3 | R7: 3 | S7: — | U7: — | W7: 9 | Z7: • EJA EF I 1/6 - ANOS INICIAIS - 15 matrículas N - 1 turma • EPT EJA EMI 1/5 - CURSO TECNICO EM GUIA DE TURISMO - PORT 11/2025 - 25 matrículas N - 1 turma Turmas EJA: 2 Noite | AA7: 40 matrículas | 2 turmas | AG7: 3 de 1ª | 3 de 2ª | 3 de 3ª | Necessidade: salas | | AH7: CEJA LEÔNIDAS MELO CEJA | EJA (0.44 km)
A8: 22135863 | B8: 01ª - PARNAÍBA | C8: CARAUBAS DO PIAUI | D8: CETI AMARO ALVES PORTELA | E8: POSSUI 06 SLS E NECESSITA 06 SLS 06 TURMA(S) MÉDIO INTEGRAL 02 turma(s) - 1ª série 02 turma(s) - 2ª série 02 turma(s) - 3ª série NOITE - 03 TURMA(S) DE EJA | F8: POSSUI 06 SLS E NECESSITA 06 SLS 06 TURMA(S) MÉDIO INTEGRAL 02 turma(s) - 1ª série 02 turma(s) - 2ª série 02 turma(s) - 3ª série NOITE - 03 TURMA(S) DE EJA | G8: — | H8: 87 alunos · 3 turmas | I8: — | L8: 2 | N8: • EPT EMI - 1ª Série - CURSO TECNICO EM ADMINISTRACAO COM ENFASE EM EMPREENDEDORISMO - 34 matrículas I - 1 turma • EPT EMI - 1ª Série - CURSO TECNICO EM DESENVOLVIMENTO DE SISTEMAS - 36 matrículas I - 1 turma • EPT EMI - 2ª Série - CURSO TECNICO EM ADMINISTRACAO COM ENFASE EM EMPREENDEDORISMO - 69 matrículas I - 2 turmas • EPT EMI - 3ª Série - CURSO TECNICO EM MARKETING DIGITAL - 55 matrículas I - 2 turmas Turmas: 6 Integral | Q8: 2 | R8: 2 | S8: — | U8: — | W8: 6 | Z8: • EJA EF I 1/6 - ANOS INICIAIS - 102 matrículas N - 6 turmas • EJA EF I 4/6 - ANOS INICIAIS - 15 matrículas N - 1 turma • EPT EJA EMI 2/5 - CURSO TECNICO EM INFORMATICA - 15 matrículas N - 1 turma • EPT EJA EMI 4/5 - CURSO TECNICO EM INFORMATICA - 9 matrículas N - 1 turma Turmas EJA: 9 Noite | AA8: 141 matrículas | 9 turmas | AG8: 2 de 1ª | 2 de 2ª | 2 de 3ª | Necessidade: salas | | AH8: Única no município
A9: 22135782 | B9: 01ª - PARNAÍBA | C9: CAXINGO | D9: CETI PROFª MARIA DO SOCORRO SAMPAIO MARTINS | E9: POSSUI 07 SLS E NECESSITA DE 06 SLS 08 TURMA(S) MÉDIO INTEGRAL 02 turma(s) - 1ª série 02 turma(s) - 2ª série 02 turma(s) - 3ª série NOITE - 01 TURMA(S) DE EJA | F9: POSSUI 06 SLS E NECESSITA DE 06 SLS 06 TURMA(S) MÉDIO INTEGRAL 02 turma(s) - 1ª série 02 turma(s) - 2ª série 02 turma(s) - 3ª série NOITE - 01 TURMA(S) DE EJA | G9: — | H9: 84 alunos · 3 turmas | I9: — | L9: 2 | N9: • EPT EMI - 1ª Série - CURSO TECNICO EM ADMINISTRACAO COM ENFASE EM EMPREENDEDORISMO - 43 matrículas I - 1 turma • EPT EMI - 1ª Série - CURSO TECNICO EM DESENVOLVIMENTO DE SISTEMAS - 39 matrículas I - 1 turma • EPT EMI - 2ª Série - CURSO TECNICO EM DESENVOLVIMENTO DE SISTEMAS - 76 matrículas I - 2 turmas • EPT EMI - 3ª Série - CURSO TECNICO EM MARKETING DIGITAL - 72 matrículas I - 2 turmas Turmas: 6 Integral | Q9: 2 | R9: 2 | S9: — | U9: — | W9: 6 | Z9: • EJA EF I 1/6 - ANOS INICIAIS - 107 matrículas N - 7 turmas • EJA EF I 2/6 - ANOS INICIAIS - 11 matrículas N - 1 turma • EPT EJA EMI 4/5 - CURSO TECNICO EM INFORMATICA - 10 matrículas N - 1 turma Turmas EJA: 9 Noite | AA9: 128 matrículas | 9 turmas | AG9: 2 de 1ª | 2 de 2ª | 2 de 3ª | Necessidade: salas | | AH9: Única no município
A10: 22013555 | B10: 01ª - PARNAÍBA | C10: COCAL | D10: CETI JOSÉ BASSON | E10: POSSUI 06 SLS E NECESSITA 06 SLS 04 TURMA(S) MÉDIO INTEGRAL 01 turma(s) - 1ª série 03 turma(s) - 2ª série MANHÃ - 02 TURMA(S) MÉDIO PARCIAL 02 turma(s) - 3ª série TARDE - 02 TURMA(S) MÉDIO PARCIAL 02 turma(s) - 3ª série | F10: POSSUI 06 SLS E NECESSITA 06 SLS 06 TURMA(S) MÉDIO INTEGRAL 02 turma(s) - 1ª série 01 turma(s) - 2ª série 03 turma(s) - 3ª série | G10: — | H10: 487 alunos · 13 turmas | I10: — | L10: 1 | N10: • EM - 3ª Série - PARCIAL DIURNO - 61 matrículas T - 2 turmas • EM - 3ª Série - PARCIAL DIURNO - 81 matrículas M - 2 turmas • EPT EMI - 1ª Série - CURSO TECNICO EM DESENVOLVIMENTO DE SISTEMAS - 45 matrículas I - 1 turma • EPT EMI - 2ª Série - CURSO TECNICO EM ADMINISTRACAO - 41 matrículas I - 1 turma • EPT EMI - 2ª Série - CURSO TECNICO EM DESENVOLVIMENTO DE SISTEMAS - 33 matrículas I - 1 turma • EPT EMI - 2ª Série - CURSO TECNICO EM MARKETING DIGITAL - 34 matrículas I - 1 turma Turmas: 4 Integral | 2 Manhã | 2 Tarde | Q10: 1 | R10: 3 | S10: EM - 3ª Série | MANHÃ | 2T (81 al.) EM - 3ª Série | TARDE | 2T (61 al.) | U10: — | W10: 6 | Z10: • EJA EF I 1/6 - ANOS INICIAIS - 16 matrículas N - 1 turma Turmas EJA: 1 Noite | AA10: 16 matrículas | 1 turmas | AG10: 1 de 1ª | 1 de 2ª | 3 de 3ª | Necessidade: salas | | AH10: CETI PINHEIRO MACHADO CETI (3.64 km)
A11: 22013601 | B11: 01ª - PARNAÍBA | C11: COCAL | D11: U E EMILIA SOARES ARAUJO | E11: POSSUI 06 SLS E NECESSITA 04 SLS MANHÃ - 01 TURMA(S) FUNDAMENTAL PARCIAL 01 turma(s) FUND - 9º ano NOITE - 04 TURMA(S) DE EJA FUNDAMENTAL | F11: POSSUI 06 SLS E NECESSITA 04 SLS MANHÃ - 01 TURMA(S) FUNDAMENTAL PARCIAL 01 turma(s) FUND - 9º ano NOITE - 04 TURMA(S) DE EJA FUNDAMENTAL | G11: • EF - 9º Ano - PARCIAL - ANOS FINAIS - 22 matrículas M - 1 turma | H11: 487 alunos · 13 turmas | I11: — | L11: 0 | N11: — | Q11: 0 | R11: 0 | S11: — | U11: — | W11: 6 | Z11: • EJA EF I 1/6 - ANOS INICIAIS - 553 matrículas N - 27 turmas • EJA EF I 3/6 - ANOS INICIAIS - 14 matrículas N - 1 turma • EJA EF I 4/6 - ANOS INICIAIS - 0 matrículas N - 1 turma • EJA EF II 2/2 - ALTERNATIVA - 0 matrículas N - 1 turma • EPT EJA EMI 2/5 - CURSO TECNICO EM ADMINISTRACAO - 20 matrículas N - 1 turma • EPT EJA EMI 4/5 - CURSO TECNICO EM ADMINISTRACAO - 37 matrículas N - 2 turmas Turmas EJA: 33 Noite | AA11: 624 matrículas | 33 turmas | AG11: 0 de 1ª | 0 de 2ª | 0 de 3ª | Necessidade: salas | | AH11: CETI JOSÉ BASSON CETI (0.34 km)
A12: 22136037 | B12: 01ª - PARNAÍBA | C12: COCAL | D12: CETI PINHEIRO MACHADO | E12: POSSUI 09 SLS E NECESSITA 9 SLS 9 TURMA(S) MÉDIO INTEGRAL 04 turma(s) - 1ª série 03 turma(s) - 2ª série 02 turma(s) - 3ª série ANEXO CAMPESTRE 01 turma(s) - 1ª série 01 turma(s) - 2ª série 01 turma(s) - 3ª série | F12: POSSUI 10 SLS E NECESSITA 10 SLS 10 TURMA(S) MÉDIO INTEGRAL 03 turma(s) - 1ª série 04 turma(s) - 2ª série 03 turma(s) - 3ª série ANEXO CAMPESTRE 01 turma(s) - 1ª série 01 turma(s) - 2ª série 01 turma(s) - 3ª série | G12: — | H12: 487 alunos · 13 turmas | I12: — | L12: 4 | N12: • EM - 3ª Série - INTEGRAL - 92 matrículas I - 2 turmas • EPT EMI - 1ª Série - CURSO TECNICO EM ADMINISTRACAO COM ENFASE EM EMPREENDEDORISMO - 50 matrículas I - 1 turma • EPT EMI - 1ª Série - CURSO TECNICO EM LOGISTICA - 49 matrículas I - 1 turma • EPT EMI - 1ª Série - CURSO TECNICO EM PROGRAMACAO DE JOGOS DIGITAIS - 53 matrículas I - 1 turma • EPT EMI - 1ª Série - CURSO TECNICO EM SISTEMAS DE ENERGIA RENOVAVEL - 50 matrículas I - 1 turma • EPT EMI - 2ª Série - CURSO TECNICO EM ADMINISTRACAO COM ENFASE EM EMPREENDEDORISMO - 34 matrículas I - 1 turma • EPT EMI - 2ª Série - CURSO TECNICO EM DESENVOLVIMENTO DE SISTEMAS - 33 matrículas I - 1 turma • EPT EMI - 2ª Série - CURSO TECNICO EM GUIA DE TURISMO - 64 matrículas I - 1 turma Turmas: 9 Integral | Q12: 4 | R12: 3 | S12: — | U12: — | W12: 10 | Z12: — | AA12: — | AG12: 4 de 1ª | 4 de 2ª | 3 de 3ª | Necessidade: salas | | AH12: CETI PINHEIRO MACHADO CETI (0.34 km)
A13: 22140115 | B13: 01ª - PARNAÍBA | C13: COCAL | D13: CETI DEPUTADO RIBEIRO MAGALHÃES | E13: POSSUI 04 SLS E NECESSITA 04 SLS 04 TURMA(S) MÉDIO INTEGRAL 02 turma(s) - 1ª série 01 turma(s) - 2ª série 01 turma(s) - 3ª série NOITE - 05 TURMA(S) EJA | F13: POSSUI 04 SLS E NECESSITA 05 SLS 05 TURMA(S) MÉDIO INTEGRAL 02 turma(s) - 1ª série 02 turma(s) - 2ª série 01 turma(s) - 3ª série NOITE - 05 TURMA(S) EJA | G13: — | H13: 487 alunos · 13 turmas | I13: — | L13: 2 | N13: • EPT EMI - 1ª Série - CURSO TECNICO EM AGROPECUARIA - 28 matrículas I - 1 turma • EPT EMI - 1ª Série - CURSO TECNICO EM SISTEMAS DE ENERGIA RENOVAVEL - 28 matrículas I - 1 turma • EPT EMI - 2ª Série - CURSO TECNICO EM AGROPECUARIA - 14 matrículas I - 1 turma • EPT EMI - 3ª Série - CURSO TECNICO EM AGROPECUARIA - 16 matrículas I - 1 turma Turmas: 4 Integral | Q13: 2 | R13: 1 | S13: — | U13: — | W13: 5 | Z13: • EPT EJA EMI 2/5 - CURSO TECNICO EM FARMACIA - 30 matrículas N - 2 turmas • EPT EJA EMI 4/5 - CURSO TECNICO EM ADMINISTRACAO - 16 matrículas N - 1 turma • EPT EJA EMI 4/5 - CURSO TECNICO EM EM RECURSOS HUMANOS - 7 matrículas N - 1 turma Turmas EJA: 4 Noite | AA13: 53 matrículas | 4 turmas | AG13: 2 de 1ª | 2 de 2ª | 1 de 3ª | Necessidade: salas | | AH13: Única no município
A14: 22136002 | B14: 01ª - PARNAÍBA | C14: COCAL DOS ALVES | D14: CETI AUGUSTINHO BRANDÃO | E14: POSSUI 09 SLS E NECESSITA 09 SLS 09 TURMA(S) MÉDIO INTEGRAL 03 turma(s) MÉDIO - 1ª série 03 turma(s) MÉDIO - 2ª série 02 turma(s) MÉDIO - 3ª série 01 turma(s) FUND - 9º ano NOITE - 05 TURMA(S) DE EJA 03 turma(s) EJA | F14: POSSUI 09 SLS E NECESSITA 09 SLS 09 TURMA(S) MÉDIO INTEGRAL 03 turma(s) MÉDIO - 1ª série 03 turma(s) MÉDIO - 2ª série 03 turma(s) MÉDIO - 3ª série NOITE - 05 TURMA(S) DE EJA 03 turma(s) EJA | G14: • EF - 9º Ano - INTEGRAL - ANOS FINAIS - 35 matrículas I - 1 turma | H14: 88 alunos · 3 turmas | I14: — | L14: 3 | N14: • EM - 3ª Série - INTEGRAL - 32 matrículas I - 1 turma • EPT EMI - 1ª Série - CURSO TECNICO EM ADMINISTRACAO COM ENFASE EM EMPREENDEDORISMO - 57 matrículas I - 2 turmas • EPT EMI - 1ª Série - CURSO TECNICO EM DESENVOLVIMENTO DE SISTEMAS - 29 matrículas I - 1 turma • EPT EMI - 2ª Série - CURSO TECNICO EM DESENVOLVIMENTO DE SISTEMAS - 72 matrículas I - 2 turmas • EPT EMI - 2ª Série - CURSO TECNICO EM LOGISTICA - 41 matrículas I - 1 turma • EPT EMI - 3ª Série - CURSO TECNICO EM DESENVOLVIMENTO DE SISTEMAS - 22 matrículas I - 1 turma Turmas: 8 Integral | Q14: 3 | R14: 3 | S14: — | U14: — | W14: 9 | Z14: • EJA EF I 1/6 - ANOS INICIAIS - 48 matrículas N - 3 turmas • EJA Médio FIC/QP 2/4 - ASSISTENTE ADMINISTRATIVO - 6 matrículas N - 1 turma • EPT EJA EMI 4/5 - CURSO TECNICO EM INFORMATICA - 12 matrículas N - 1 turma Turmas EJA: 5 Noite | AA14: 66 matrículas | 5 turmas | AG14: 3 de 1ª | 3 de 2ª | 3 de 3ª | Necessidade: salas | | AH14: CETI PINHEIRO MACHADO CETI (0.74 km)
... A39: 22135456 | B39: 01ª - PARNAÍBA | C39: PARNAIBA | D39: CETI LICEU PARNAIBANO | E39: POSSUI 12 SLS E NECESSITA 12 SLS 12 TURMA(S) MÉDIO INTEGRAL 03 turma(s) - 1ª série 04 turma(s) - 2ª série 05 turma(s) - 3ª série | F39: POSSUI 12 SLS E NECESSITA 10 SLS 10 TURMA(S) MÉDIO INTEGRAL 03 turma(s) - 1ª série 03 turma(s) - 2ª série 04 turma(s) - 3ª série | G39: — | H39: 1789 alunos · 45 turmas | I39: — | L39: 3 | N39: • EPT EMI - 1ª Série - CURSO TECNICO EM ADMINISTRACAO COM ENFASE EM EMPREENDEDORISMO - 48 matrículas I - 1 turma • EPT EMI - 1ª Série - CURSO TECNICO EM DESENVOLVIMENTO DE SISTEMAS - 48 matrículas I - 1 turma • EPT EMI - 1ª Série - CURSO TECNICO EM PROGRAMACAO DE JOGOS DIGITAIS - 40 matrículas I - 1 turma • EPT EMI - 2ª Série - CURSO TECNICO EM DESENVOLVIMENTO DE SISTEMAS - 43 matrículas I - 1 turma • EPT EMI - 2ª Série - CURSO TECNICO EM MARKETING DIGITAL - 44 matrículas I - 1 turma • EPT EMI - 2ª Série - CURSO TECNICO EM PRODUCAO DE AUDIO E VIDEO - 41 matrículas I - 1 turma • EPT EMI - 2ª Série - CURSO TECNICO EM PROGRAMACAO DE JOGOS DIGITAIS - 35 matrículas I - 1 turma • EPT EMI - 3ª Série - CURSO TECNICO EM ADMINISTRACAO COM ENFASE EM EMPREENDEDORISMO - 35 matrículas I - 1 turma • EPT EMI - 3ª Série - CURSO TECNICO EM CONTROLE AMBIENTAL - 26 matrículas I - 1 turma • EPT EMI - 3ª Série - CURSO TECNICO EM DESENVOLVIMENTO DE SISTEMAS - 38 matrículas I - 1 turma • EPT EMI - 3ª Série - CURSO TECNICO EM MARKETING DIGITAL - 45 matrículas I - 1 turma • EPT EMI - 3ª Série - CURSO TECNICO EM PROGRAMACAO DE JOGOS DIGITAIS - 34 matrículas I - 1 turma Turmas: 12 Integral | Q39: 3 | R39: 4 | S39: — | U39: — | W39: 12 | Z39: • EJA EF I 1/6 - ANOS INICIAIS - 96 matrículas N - 7 turmas Turmas EJA: 7 Noite | AA39: 96 matrículas | 7 turmas | AG39: 3 de 1ª | 3 de 2ª | 4 de 3ª | Necessidade: salas | | AH39: CETI POLIVALENTE LIMA REBELO CETI (0.62 km)
A40: 22146504 | B40: 01ª - PARNAÍBA | C40: PARNAIBA | D40: CENTRO CULTURAL DE LÍNGUAS MONSENHOR ANTÔNIO SAMPAIO | F40: CENTRO ESPECIALIZADO | G40: — | H40: 1789 alunos · 45 turmas | I40: — | L40: 0 | N40: — | Q40: 0 | R40: 0 | S40: — | U40: — | W40: 5 | Z40: — | AA40: — | AG40: 0 de 1ª | 0 de 2ª | 0 de 3ª | Necessidade: salas | | AH40: CETI MINISTRO PETRONIO PORTELLA CETI (0.42 km)
A41: 22162615 | B41: 01ª - PARNAÍBA | C41: PARNAIBA | D41: CETI DEPUTADA FRANCISCA TRINDADE II | E41: POSSUI 04 SLS E NECESSITA 03 SLS 02 TURMA(S) DE MÉDIO INTEGRAL 01 turma - 1ª série 01 turma - 2ª série MANHÃ - 01 TURMA DE MÉDIO PARCIAL 01 turma - 3ª série NOITE - 03 TURMA(S) DE EJA | F41: POSSUI 04 SLS E NECESSITA 03 SLS 03 TURMA(S) DE MÉDIO INTEGRAL 01 turma - 1ª série 01 turma - 2ª série 01 turma - 3ª série NOITE - 03 TURMA(S) DE EJA | G41: — | H41: 1789 alunos · 45 turmas | I41: — | L41: 1 | N41: • EM - 3ª Série - PARCIAL DIURNO - 24 matrículas T - 1 turma • EPT EMI - 1ª Série - CURSO TECNICO EM AGROPECUARIA - 19 matrículas I - 1 turma • EPT EMI - 2ª Série - CURSO TECNICO EM MARKETING DIGITAL - 18 matrículas I - 1 turma Turmas: 2 Integral | 1 Tarde | Q41: 1 | R41: 1 | S41: EM - 3ª Série | TARDE | 1T (24 al.) | U41: — | W41: 4 | Z41: • EJA EF I 1/6 - ANOS INICIAIS - 35 matrículas N - 2 turmas • EJA EM 2/2 - ALTERNATIVO - 9 matrículas N - 1 turma • EPT EJA EMI 2/5 - CURSO TECNICO EM ADMINISTRACAO - 19 matrículas N - 1 turma • EPT EJA EMI 4/5 - CURSO TECNICO EM ADMINISTRACAO - 11 matrículas N - 1 turma Turmas EJA: 5 Noite | AA41: 74 matrículas | 5 turmas | AG41: 1 de 1ª | 1 de 2ª | 1 de 3ª | Necessidade: salas | | AH41: CETI EPAMINONDAS CASTELO BRANCO CETI (1.34 km)
A42: 22000054 | B42: 02ª - BARRAS | C42: BARRAS | D42: CEJA PROFESSOR CONRADO AMORIM DE SOUSA | E42: POSSUI 11 SLS E NECESSITA 10 SLS 15 TURMA(S) DE EJA 10 turma(s) de EJA (sede) 05 turma(s) de EJA (externas) | F42: POSSUI 11 SLS E NECESSITA 10 SLS 15 TURMA(S) DE EJA 10 turma(s) de EJA (sede) 05 turma(s) de EJA (externas) | G42: — | H42: 715 alunos · 18 turmas | I42: — | L42: 0 | N42: • EPT EMC 5/4 - AUXILIAR ADMINISTRATIVO - 10 matrículas N - 1 turma • EPT EMC 5/4 - INFORMATICA BASICA - 16 matrículas N - 1 turma Turmas: 2 Noite | Q42: 0 | R42: 0 | S42: — | U42: — | W42: 11 | Z42: • EJA EF I 1/6 - ANOS INICIAIS - 480 matrículas N - 27 turmas • EJA EF I 3/6 - ANOS INICIAIS - 76 matrículas N - 4 turmas • EJA EF I 4/6 - ANOS INICIAIS - 0 matrículas N - 1 turma • EJA EM 2/2 - ALTERNATIVO - 13 matrículas N - 1 turma • EPT EJA EMI 2/5 - CURSO TECNICO EM ADMINISTRACAO - 12 matrículas N - 1 turma • EPT EJA EMI 2/5 - CURSO TECNICO EM AGENTE COMUNITARIO DE SAUDE - 100 matrículas N - 3 turmas • EPT EJA EMI 2/5 - CURSO TECNICO EM INFORMATICA - 11 matrículas N - 1 turma • EPT EJA EMI 4/5 - CURSO TECNICO EM ADMINISTRACAO - 51 matrículas N - 2 turmas • EPT EJA EMI 4/5 - CURSO TECNICO EM INFORMATICA - 21 matrículas N - 2 turmas Turmas EJA: 42 Noite | AA42: 764 matrículas | 42 turmas | AG42: 0 de 1ª | 0 de 2ª | 0 de 3ª | Necessidade: salas | | AH42: CETI EDSON DA PAZ CUNHA CETI (0.16 km)
A43: 22001530 | B43: 02ª - BARRAS | C43: BARRAS | D43: CETI GERVASIO COSTA | E43: POSSUI 06 SLS E NECESSITA 09 SLS (usam 03 salas da UESPI, contabilizando 09) 07 TURMA(S) MÉDIO INTEGRAL 04 turma(s) - 1ª série 03 turma(s) - 2ª série MANHÃ - 03 TURMA(S) MÉDIO PARCIAL 03 turma(s) - 3ª série TARDE - 02 TURMA(S) MÉDIO PARCIAL 02 turma(s) de 3 série ANEXO LAGOA DE LAGES 03 TURMA(S) MÉDIO PARCIAL 01 turma(s) - 1ª série 01 turma(s) - 2ª série 01 turma(s) - 3ª série | F43: POSSUI 06 SLS E NECESSITA 08 SLS 08 TURMA(S) MÉDIO INTEGRAL 01 turma(s) - 1ª série 04 turma(s) - 2ª série 03 turma(s) - 3ª série ANEXO LAGOA DE LAGES 03 TURMA(S) MÉDIO PARCIAL 01 turma(s) - 1ª série 01 turma(s) - 2ª série 01 turma(s) - 3ª série | G43: — | H43: 715 alunos · 18 turmas | I43: — | L43: 4 | N43: • EM - 3ª Série - PARCIAL DIURNO - 139 matrículas M - 3 turmas • EM - 3ª Série - PARCIAL DIURNO - 61 matrículas T - 2 turmas • EPT EMC 4/3 - CURSO TECNICO EM SISTEMAS DE ENERGIAS RENOVAVEIS - 6 matrículas N - 1 turma • EPT EMI - 1ª Série - CURSO TECNICO EM ADMINISTRACAO COM ENFASE EM EMPREENDEDORISMO - 38 matrículas I - 1 turma • EPT EMI - 1ª Série - CURSO TECNICO EM DESENVOLVIMENTO DE SISTEMAS - 42 matrículas I - 1 turma • EPT EMI - 1ª Série - CURSO TECNICO EM MARKETING DIGITAL - 42 matrículas I - 1 turma • EPT EMI - 1ª Série - CURSO TECNICO EM PROGRAMACAO DE JOGOS DIGITAIS - 35 matrículas I - 1 turma • EPT EMI - 2ª Série - CURSO TECNICO EM ADMINISTRACAO - 45 matrículas I - 1 turma • EPT EMI - 2ª Série - CURSO TECNICO EM ADMINISTRACAO COM ENFASE EM EMPREENDEDORISMO - 44 matrículas I - 1 turma • EPT EMI - 2ª Série - CURSO TECNICO EM MARKETING DIGITAL - 45 matrículas I - 1 turma • EPT EMS 1/2 - CURSO TECNICO EM DESENVOLVIMENTO DE SISTEMAS - 34 matrículas N - 1 turma Turmas: 7 Integral | 3 Manhã | 2 Tarde | 2 Noite | Q43: 4 | R43: 3 | S43: EM - 3ª Série | MANHÃ | 3T (139 al.) EM - 3ª Série | TARDE | 2T (61 al.) | U43: — | W43: 6 | Z43: • EJA EF I 1/6 - ANOS INICIAIS - 237 matrículas N - 22 turmas Turmas EJA: 22 Noite | AA43: 237 matrículas | 22 turmas | AG43: 4 de 1ª | 4 de 2ª | 3 de 3ª | Necessidade: salas | | AH43: CETI PROFESSORA MARIA DE JESUS CARVALHO ROCHA CETI (1.29 km)
A44: 22001573 | B44: 02ª - BARRAS | C44: BARRAS | D44: CETI MATIAS OLIMPIO | E44: POSSUI 13 SLS E NECESSITA 12 SLS 10 TURMA(S) MÉDIO INTEGRAL 05 turma(s) - 1ª série 05 turma(s) - 2ª série MANHÃ - 02 TURMA(S) PARCIAL 02 turma(s) MÉDIO - 3ª série TARDE - 02 TURMA(S) PARCIAIS 01 turma(s) MÉDIO - 3ª série 01 turma(s) de EJA NOITE - 05 TURMA(S) DE EJA | F44: POSSUI 13 SLS E NECESSITA 13 SLS 13 TURMA(S) MÉDIO INTEGRAL 02 turma(s) - 1ª série 05 turma(s) - 2ª série 05 turma(s) - 3ª série TARDE - 01 TURMA(S) PARCIAIS 01 turma(s) de EJA NOITE - 05 TURMA(S) DE EJA | G44: — | H44: 715 alunos · 18 turmas | I44: — | L44: 5 | N44: • EM - 3ª Série - PARCIAL DIURNO - 73 matrículas M - 2 turmas • EPT EMC 4/2 - CURSO TECNICO EM MARKETING DIGITAL - 0 matrículas N - 1 turma • EPT EMC 4/4 - CURSO TECNICO EM DESENVOLVIMENTO DE SISTEMAS - 0 matrículas N - 1 turma • EPT EMI - 1ª Série - CURSO TECNICO EM ADMINISTRACAO COM ENFASE EM EMPREENDEDORISMO - 102 matrículas I - 2 turmas • EPT EMI - 1ª Série - CURSO TECNICO EM ALIMENTOS - 37 matrículas I - 1 turma • EPT EMI - 1ª Série - CURSO TECNICO EM DESENVOLVIMENTO DE SISTEMAS - 89 matrículas I - 2 turmas • EPT EMI - 2ª Série - CURSO TECNICO EM DESENVOLVIMENTO DE SISTEMAS - 78 matrículas I - 2 turmas • EPT EMI - 2ª Série - CURSO TECNICO EM MARKETING DIGITAL - 131 matrículas I - 3 turmas Turmas: 10 Integral | 2 Manhã | 2 Noite | Q44: 5 | R44: 5 | S44: EM - 3ª Série | MANHÃ | 2T (73 al.) | U44: — | W44: 13 | Z44: • EJA EF I 1/6 - ANOS INICIAIS - 413 matrículas N - 27 turmas • EJA EM 2/2 - ALTERNATIVO - 12 matrículas N - 1 turma • EJA FIQ/QP 2/# - AUXILIAR ADMINISTRATIVO - 9 matrículas N - 1 turma • EJA Médio FIC/QP 1/2 - ASSIST ADM / INFO BASICA - 16 matrículas T - 1 turma • EJA Médio FIC/QP 1/2 - ASSIST ADM / INFO BASICA - 16 matrículas T - 1 turma • EPT EJA EMI 2/5 - CURSO TECNICO EM ADMINISTRACAO - 0 matrículas N - 1 turma • EPT EJA EMI 2/5 - CURSO TECNICO EM MARKETING DIGITAL - 11 matrículas N - 1 turma • EPT EJA EMI 4/5 - CURSO TECNICO EM ADMINISTRACAO - 17 matrículas N - 1 turma Turmas EJA: 2 Tarde | 32 Noite | AA44: 494 matrículas | 34 turmas | AG44: 5 de 1ª | 5 de 2ª | 5 de 3ª | Necessidade: salas | | AH44: CETI NOSSA SENHORA DA CONCEIÇÃO CETI (0.55 km)
A45: 22001603 | B45: 02ª - BARRAS | C45: BARRAS | D45: CETI NOSSA SENHORA DA CONCEIÇÃO | E45: POSSUI 07 SLS E NECESSITA 07 SLS 07 TURMA(S) MÉDIO INTEGRAL 02 turma(s) - 1ª série 02 turma(s) - 2ª série 03 turma(s) - 3ª série | F45: POSSUI 07 SLS E NECESSITA 07 SLS 07 TURMA(S) MÉDIO INTEGRAL 03 turma(s) - 1ª série 02 turma(s) - 2ª série 02 turma(s) - 3ª série | G45: — | H45: 715 alunos · 18 turmas | I45: — | L45: 2 | N45: • EM - 3ª Série - INTEGRAL - 78 matrículas I - 2 turmas • EPT EMI - 1ª Série - CURSO TECNICO EM ADMINISTRACAO COM ENFASE EM EMPREENDEDORISMO - 40 matrículas I - 1 turma • EPT EMI - 1ª Série - CURSO TECNICO EM DESENVOLVIMENTO DE SISTEMAS - 27 matrículas I - 1 turma • EPT EMI - 2ª Série - CURSO TECNICO EM MARKETING DIGITAL - 39 matrículas I - 1 turma • EPT EMI - 2ª Série - CURSO TECNICO EM PROGRAMACAO DE JOGOS DIGITAIS - 45 matrículas I - 1 turma • EPT EMI - 3ª Série - CURSO TECNICO EM MARKETING DIGITAL - 39 matrículas I - 1 turma Turmas: 7 Integral | Q45: 2 | R45: 2 | S45: — | U45: — | W45: 7 | Z45: • EJA EF I 1/6 - ANOS INICIAIS - 155 matrículas N - 11 turmas Turmas EJA: 11 Noite | AA45: 155 matrículas | 11 turmas | AG45: 2 de 1ª | 2 de 2ª | 2 de 3ª | Necessidade: salas | | AH45: CETI NOSSA SENHORA DA CONCEIÇÃO CETI (0.65 km)
A46: 22136703 | B46: 02ª - BARRAS | C46: BARRAS | D46: CETI FRANCISCA TRINDADE | E46: POSSUI 11 SLS E NECESSITA 09 SLS 09 TURMA(S) MÉDIO INTEGRAL 03 turma(s) - 1ª série 03 turma(s) - 2ª série 03 turma(s) - 3ª série | F46: POSSUI 09 SLS E NECESSITA 09 SLS 09 TURMA(S) MÉDIO INTEGRAL 03 turma(s) - 1ª série 03 turma(s) - 2ª série 03 turma(s) - 3ª série | G46: — | H46: 715 alunos · 18 turmas | I46: — | L46: 3 | N46: • EM - 3ª Série - INTEGRAL - 39 matrículas I - 1 turma • EPT EMI - 1ª Série - CURSO TECNICO EM ADMINISTRACAO COM ENFASE EM EMPREENDEDORISMO - 42 matrículas I - 1 turma • EPT EMI - 1ª Série - CURSO TECNICO EM DESENVOLVIMENTO DE SISTEMAS - 47 matrículas I - 1 turma • EPT EMI - 1ª Série - CURSO TECNICO EM PROGRAMACAO DE JOGOS DIGITAIS - 44 matrículas I - 1 turma • EPT EMI - 2ª Série - CURSO TECNICO EM DESENVOLVIMENTO DE SISTEMAS - 39 matrículas I - 1 turma • EPT EMI - 2ª Série - CURSO TECNICO EM MARKETING DIGITAL - 81 matrículas I - 2 turmas • EPT EMI - 3ª Série - CURSO TECNICO EM DESENVOLVIMENTO DE SISTEMAS - 34 matrículas I - 1 turma • EPT EMI - 3ª Série - CURSO TECNICO EM MARKETING DIGITAL - 38 matrículas I - 1 turma Turmas: 9 Integral | Q46: 3 | R46: 3 | S46: — | U46: — | W46: 9 | Z46: • EJA EF I 1/6 - ANOS INICIAIS - 291 matrículas N - 18 turmas Turmas EJA: 18 Noite | AA46: 291 matrículas | 18 turmas | AG46: 3 de 1ª | 3 de 2ª | 3 de 3ª | Necessidade: salas | | AH46: CETI MATIAS OLIMPIO CETI (0.95 km)
A47: 22136711 | B47: 02ª - BARRAS | C47: BARRAS | D47: CETI PROFESSORA MARIA DE JESUS CARVALHO ROCHA | E47: POSSUI 09 SLS E NECESSITA 11 SLS 08 TURMA(S) MÉDIO INTEGRAL 04 turma(s) - 1ª série 04 turma(s) - 2ª série MANHÃ - 02 TURMA(S) MÉDIO PARCIAL 02 turma(s) - 3ª série TARDE - 03 TURMA(S) MÉDIO PARCIAL 03 turma(s) - 3ª série NOITE - 08 TURMA(S) DE EJA ANEXO HAYDEE LAGES MONTES - 32km 01 turma(s) - 1ª série 01 turma(s) - 2ª série 01 turma(s) - 3ª série 01 turma(s) - Alfabetiza ANEXO JOÃO ODORICO - 37km 01 turma(s) - 1ª série 01 turma(s)de 2ª série 01 turma(s)de 3ª série ANEXOS DESCONTINUADOS: ANEXO FORMOSA - 17km ANEXO SOSSEGO - 42km ANEXO CARA TORTA - 30km 01 turma(s) - 1ª série 01 turma(s)de 2ª série 01 turma(s)de 3ª série | F47: POSSUI 12 SLS E NECESSITA 12 SLS 12 TURMA(S) MÉDIO INTEGRAL 04 turma(s) - 1ª série 04 turma(s) - 2ª série 04 turma(s) - 3ª série NOITE - 08 TURMA(S) DE EJA ANEXO HAYDEE LAGES MONTES - 32km 01 turma(s) - 1ª série 01 turma(s) - 2ª série 01 turma(s) - 3ª série 01 turma(s) - Alfabetiza ANEXO JOÃO ODORICO - 37km 01 turma(s) - 1ª série 01 turma(s)de 2ª série 01 turma(s)de 3ª série ANEXOS DESCONTINUADOS: ANEXO FORMOSA - 17km ANEXO SOSSEGO - 42km ANEXO CARA TORTA - 30km 01 turma(s) - 1ª série 01 turma(s)de 2ª série 01 turma(s)de 3ª série | G47: — | H47: 715 alunos · 18 turmas | I47: — | L47: 4 | N47: • EPT EMI - 1ª Série - CURSO TECNICO EM AGROPECUARIA - 43 matrículas I - 1 turma • EPT EMI - 1ª Série - CURSO TECNICO EM ANALISES CLINICAS - 43 matrículas I - 1 turma • EPT EMI - 1ª Série - CURSO TECNICO EM ENFERMAGEM - 26 matrículas I - 1 turma • EPT EMI - 2ª Série - CURSO TECNICO EM AGROPECUARIA - 41 matrículas I - 1 turma • EPT EMI - 2ª Série - CURSO TECNICO EM FARMACIA - 35 matrículas I - 1 turma • EPT EMI - 2ª Série - CURSO TECNICO EM SAUDE BUCAL - 61 matrículas I - 2 turmas • EPT EMI - 3ª Série - CURSO TECNICO EM ADMINISTRACAO COM ENFASE EM EMPREENDEDORISMO - 29 matrículas T - 1 turma • EPT EMI - 3ª Série - CURSO TECNICO EM ADMINISTRACAO COM ENFASE EM EMPREENDEDORISMO - 37 matrículas M - 1 turma • EPT EMI - 3ª Série - CURSO TECNICO EM AGROPECUARIA - 35 matrículas M - 1 turma • EPT EMI - 3ª Série - CURSO TECNICO EM CONTROLE AMBIENTAL - 23 matrículas T - 1 turma • EPT EMI - 3ª Série - CURSO TECNICO EM INFORMATICA PARA INTERNET - 41 matrículas T - 1 turma Turmas: 7 Integral | 2 Manhã | 3 Tarde | Q47: 4 | R47: 4 | S47: — | U47: — | W47: 12 | Z47: • EJA EF I 1/6 - ANOS INICIAIS - 315 matrículas N - 22 turmas • EPT EJA EMI #/5 - CURSO TECNICO EM ENFERMAGEM - 18 matrículas N - 1 turma • EPT EJA EMI 2/5 - CURSO TECNICO EM FARMACIA - 14 matrículas N - 1 turma • EPT EJA EMI 4/5 - CURSO TECNICO EM ENFERMAGEM - 25 matrículas N - 1 turma • EPT EJA EMI 4/5 - CURSO TECNICO EM FARMACIA - 6 matrículas N - 1 turma • EPT EJA EMI 4/5 - CURSO TECNICO EM INFORMATICA - 7 matrículas N - 1 turma • EPT EMI - 1ª Série - CURSO TECNICO EM PLANEJAMENTO E CONTROLE DA PRODUCAO - 40 matrículas I - 1 turma Turmas EJA: 1 Integral | 27 Noite | AA47: 425 matrículas | 28 turmas | AG47: 4 de 1ª | 4 de 2ª | 4 de 3ª | Necessidade: salas | | AH47: CETI GERVASIO COSTA CETI (0.55 km)
A48: 22002049 | B48: 02ª - BARRAS | C48: BATALHA | D48: CETI CONSELHEIRO SARAIVA | E48: POSSUI 11 SLS E NECESSITA 11 SLS 09 TURMA(S) MÉDIO INTEGRAL 03 turma(s) - 1ª série 03 turma(s) - 2ª série 03 turma(s) - 3ª série MANHÃ - 02 TURMA(S) FUNDAMENTAL PARCIAL 02 turma(s) FUND - 9º ano | F48: POSSUI 11 SLS E NECESSITA 08 SLS 08 TURMA(S) MÉDIO INTEGRAL 02 turma(s) - 1ª série 03 turma(s) - 2ª série 03 turma(s) - 3ª série | G48: • EF - 9º Ano - PARCIAL - ANOS FINAIS - 52 matrículas M - 2 turmas | H48: 371 alunos · 10 turmas | I48: — | L48: 3 | N48: • EM - 3ª Série - INTEGRAL - 54 matrículas I - 2 turmas • EPT EMI - 1ª Série - CURSO TECNICO EM DESENVOLVIMENTO DE SISTEMAS - 60 matrículas I - 2 turmas • EPT EMI - 1ª Série - CURSO TECNICO EM PROGRAMACAO DE JOGOS DIGITAIS - 23 matrículas I - 1 turma • EPT EMI - 2ª Série - CURSO TECNICO EM ADMINISTRACAO - 25 matrículas I - 1 turma • EPT EMI - 2ª Série - CURSO TECNICO EM DESENVOLVIMENTO DE SISTEMAS - 31 matrículas I - 1 turma • EPT EMI - 2ª Série - CURSO TECNICO EM MARKETING DIGITAL - 30 matrículas I - 1 turma • EPT EMI - 3ª Série - CURSO TECNICO EM DESENVOLVIMENTO DE SISTEMAS - 22 matrículas I - 1 turma Turmas: 9 Integral | Q48: 3 | R48: 3 | S48: — | U48: — | W48: 11 | X48: 13 | Y48: Construir 2 SALAS | Z48: • EJA EF I 1/6 - ANOS INICIAIS - 124 matrículas N - 7 turmas Turmas EJA: 7 Noite | AA48: 124 matrículas | 7 turmas | AG48: 3 de 1ª | 3 de 2ª | 3 de 3ª | Necessidade: 13 salas | Construir 2 SALAS | AH48: CETI FRANCISCA TRINDADE CETI (1.29 km)
A49: 22002391 | B49: 02ª - BARRAS | C49: BATALHA | D49: CETI DIRCEU ARCOVERDE | E49: POSSUI 07 SLS E NECESSITA DE 07 SLS 06 TURMA(S) MÉDIO INTEGRAL 02 turma(s) - 1ª série 02 turma(s) - 2ª série 02 turma(s) - 3ª série NOITE - 07 TURMA(S) PARCIAIS 03 turma(s) de EJA 01 turma(s) - 1ª série 01 turma(s) - 2ª série 02 turma(s) - 3ª série ANEXO CARAIBAS - 19KM - NOITE 01 turma(s) de EJA 01 turma(s) - 1ª série 01 turma(s) - 2ª série 01 turma(s) - 3ª série ANEXO IMBIRIBAS - 30km - NOITE 02 turma(s) de EJA 01 turma(s) - 1ª série 01 turma(s) - 2ª série 02 turma(s) - 3ª série ANEXO VITORIA DE BAIXO - 70km - NOITE 01 turma(s) - 1ª série 01 turma(s) - 2ª série 01 turma(s) - 3ª série | F49: POSSUI 07 SLS E NECESSITA DE 07 SLS 07 TURMA(S) MÉDIO INTEGRAL 01 turma(s) - 1ª série 03 turma(s) - 2ª série 03 turma(s) - 3ª série NOITE - 03 TURMA(S) PARCIAIS 03 turma(s) de EJA ANEXO CARAIBAS - 19KM - NOITE 01 turma(s) de EJA 01 turma(s) - 1ª série 01 turma(s) - 2ª série 01 turma(s) - 3ª série ANEXO IMBIRIBAS - 30km - NOITE 02 turma(s) de EJA 01 turma(s) - 1ª série 01 turma(s) - 2ª série 02 turma(s) - 3ª série ANEXO VITORIA DE BAIXO - 70km - NOITE 01 turma(s) - 1ª série 01 turma(s) - 2ª série 01 turma(s) - 3ª série | G49: — | H49: 371 alunos · 10 turmas | I49: — | L49: 3 | N49: • EM - 3ª Série - INTEGRAL - 28 matrículas I - 1 turma • EM - 3ª Série - PARCIAL NOTURNO - 50 matrículas N - 2 turmas • EPT EMI - 1ª Série - CURSO TECNICO EM ADMINISTRACAO COM ENFASE EM EMPREENDEDORISMO - 18 matrículas N - 1 turma • EPT EMI - 1ª Série - CURSO TECNICO EM ADMINISTRACAO COM ENFASE EM EMPREENDEDORISMO - 76 matrículas I - 2 turmas • EPT EMI - 2ª Série - CURSO TECNICO EM ADMINISTRACAO COM ENFASE EM EMPREENDEDORISMO - 29 matrículas N - 1 turma • EPT EMI - 2ª Série - CURSO TECNICO EM ADMINISTRACAO COM ENFASE EM EMPREENDEDORISMO - 44 matrículas I - 2 turmas • EPT EMI - 3ª Série - CURSO TECNICO EM MARKETING DIGITAL - 17 matrículas I - 1 turma Turmas: 6 Integral | 4 Noite | Q49: 3 | R49: 3 | S49: EM - 3ª Série | NOITE | 2T (50 al.) | U49: — | W49: 7 | Z49: • EJA EF I 1/6 - ANOS INICIAIS - 211 matrículas N - 12 turmas • EJA EF I 4/6 - ANOS INICIAIS - 6 matrículas N - 1 turma • EPT EJA EMI 2/5 - CURSO TECNICO EM INFORMATICA - 22 matrículas N - 1 turma Turmas EJA: 14 Noite | AA49: 239 matrículas | 14 turmas | AG49: 3 de 1ª | 3 de 2ª | 3 de 3ª | Necessidade: salas | | AH49: CETI DIRCEU ARCOVERDE CETI (0.25 km)
A50: 22002588 | B50: 02ª - BARRAS | C50: BATALHA | D50: CETI GAYOSO E ALMENDRA | E50: POSSUI 08 SLS E NECESSITA 08 SLS 06 TURMA(S) MÉDIO INTEGRAL 02 turma(s) - 1ª série 02 turma(s) - 2ª série 02 turma(s) - 3ª série MANHÃ - 02 TURMA(S) FUNDAMENTAL PARCIAL 02 turma(s) FUND - 9º ano TARDE - 02 TURMA(S) FUNDAMENTAL PARCIAL 02 turma(s) FUND - 8º ano NOITE - 07 TURMA(S) PARCIAIS 05 turma(s) de EJA | F50: POSSUI 08 SLS E NECESSITA 08 SLS 06 TURMA(S) MÉDIO INTEGRAL 02 turma(s) - 1ª série 02 turma(s) - 2ª série 02 turma(s) - 3ª série TARDE - 02 TURMA(S) FUNDAMENTAL PARCIAL 02 turma(s) FUND - 9º ano NOITE - 07 TURMA(S) PARCIAIS 05 turma(s) de EJA | G50: • EF - 8º Ano - PARCIAL - ANOS FINAIS - 49 matrículas T - 2 turmas • EF - 9º Ano - PARCIAL - ANOS FINAIS - 58 matrículas M - 2 turmas | H50: 371 alunos · 10 turmas | I50: — | L50: 3 | N50: • EM - 3ª Série - INTEGRAL - 32 matrículas I - 1 turma • EPT EMC 5/4 - CUIDADOS DE IDOSOS - 18 matrículas N - 1 turma • EPT EMI - 1ª Série - CURSO TECNICO EM ADMINISTRACAO COM ENFASE EM EMPREENDEDORISMO - 94 matrículas I - 2 turmas • EPT EMI - 1ª Série - CURSO TECNICO EM DESENVOLVIMENTO DE SISTEMAS - 44 matrículas I - 1 turma • EPT EMI - 2ª Série - CURSO TECNICO EM MARKETING DIGITAL - 22 matrículas I - 1 turma • EPT EMI - 2ª Série - CURSO TECNICO EM PROGRAMACAO DE JOGOS DIGITAIS - 51 matrículas I - 2 turmas • EPT EMI - 3ª Série - CURSO TECNICO EM PROGRAMACAO DE JOGOS DIGITAIS - 30 matrículas I - 1 turma Turmas: 8 Integral | 1 Noite | Q50: 3 | R50: 3 | S50: — | U50: — | W50: 8 | Z50: • EJA EF I 1/6 - ANOS INICIAIS - 141 matrículas N - 11 turmas • EJA EF I 3/6 - ANOS INICIAIS - 49 matrículas N - 2 turmas • EPT EJA EMI 2/5 - CURSO TECNICO EM AGENTE COMUNITARIO DE SAUDE - 19 matrículas N - 1 turma • EPT EJA EMI 4/5 - CURSO TECNICO EM AGENTE COMUNITARIO DE SAUDE - 26 matrículas N - 1 turma Turmas EJA: 15 Noite | AA50: 235 matrículas | 15 turmas | AG50: 3 de 1ª | 3 de 2ª | 3 de 3ª | Necessidade: salas | | AH50: CETI CONSELHEIRO SARAIVA CETI (0.25 km)
A51: 22002677 | B51: 02ª - BARRAS | C51: BATALHA | D51: CETI MARIA MELO | E51: POSSUI 05 SLS E NECESSITA 05 SLS (Possuia 04, mas dividiu 01 Sala em 02 de tamanho menor) 03 TURMA(S) MÉDIO INTEGRAL 01 turma(s) - 1ª série 02 turma(s) - 2ª série MANHÃ - 02 TURMA(S) DE PARCIAIS 01 turma(s) MÉDIO - 3ª série 01 turma(s) FUND - 9º ano TARDE - 02 TURMA(S) PARCIAL 01 turma(s) MÉDIO - 3ª série 01 turma(s) FUND - 8º ano | F51: POSSUI 06 SLS E NECESSITA 05 SLS (6ª Sala - Pactue Em Execução) 04 TURMA(S) MÉDIO INTEGRAL 01 turma(s) - 1ª série 01 turma(s) - 2ª série 02 turma(s) - 3ª série TARDE - 01 TURMA(S) PARCIAL 01 turma(s) FUND - 9º ano | G51: • EF - 8º Ano - PARCIAL - ANOS FINAIS - 34 matrículas T - 1 turma • EF - 9º Ano - PARCIAL - ANOS FINAIS - 33 matrículas M - 1 turma | H51: 371 alunos · 10 turmas | I51: — | L51: 1 | N51: • EPT EMI - 1ª Série - CURSO TECNICO EM ADMINISTRACAO COM ENFASE EM EMPREENDEDORISMO - 33 matrículas I - 1 turma • EPT EMI - 2ª Série - CURSO TECNICO EM DESENVOLVIMENTO DE SISTEMAS - 36 matrículas I - 2 turmas • EPT EMI - 3ª Série - CURSO TECNICO EM DESENVOLVIMENTO DE SISTEMAS - 19 matrículas T - 1 turma • EPT EMI - 3ª Série - CURSO TECNICO EM DESENVOLVIMENTO DE SISTEMAS - 23 matrículas M - 1 turma Turmas: 3 Integral | 1 Manhã | 1 Tarde | Q51: 1 | R51: 2 | S51: — | U51: EPT EMI - 2ª Série - CURSO TECNICO EM DESENVOLVIMENTO DE SISTEMAS | INTEGRAL: 2T / 36 alunos → 1T (possível liberar 1 turma) | W51: 6 | Z51: • EJA EF I 1/6 - ANOS INICIAIS - 92 matrículas N - 6 turmas Turmas EJA: 6 Noite | AA51: 92 matrículas | 6 turmas | AG51: 1 de 1ª | 1 de 2ª | 2 de 3ª | Necessidade: salas | | AH51: CETI MARIA MELO CETI (0.83 km)
A52: 22003452 | B52: 02ª - BARRAS | C52: CABECEIRAS DO PIAUI | D52: CETI VENANCIA LAGES VELOSO | E52: POSSUI 09 SLS E NECESSITA 09 SLS 09 TURMA(S) MÉDIO INTEGRAL 03 turma(s) - 1ª série 03 turma(s) - 2ª série 03 turma(s) - 3ª série NOITE - 07 TURMA(S) EJA ANEXO SÃO BENTO - 32km 01 turma(s) - 1ª série 01 turma(s) - 2ª série 01 turma(s) - 3ª série 01 turma(s) de EJA ANEXO BOM FUTURO - 15km 01 turma(s) - Alfabetiza 01 turma(s) - 2ª série 01 turma(s) - 3ª série ANEXO PEDRAS - 18km 01 turma(s) - Alfabetiza 01 turma(s) - 2ª série 01 turma(s) - 3ª série | F52: POSSUI 09 SLS E NECESSITA 09 SLS 09 TURMA(S) MÉDIO INTEGRAL 03 turma(s) - 1ª série 03 turma(s) - 2ª série 03 turma(s) - 3ª série NOITE - 07 TURMA(S) EJA ANEXO SÃO BENTO - 32km 01 turma(s) - 1ª série 01 turma(s) - 2ª série 01 turma(s) - 3ª série 01 turma(s) de EJA ANEXO BOM FUTURO - 15km 01 turma(s) - Alfabetiza 01 turma(s) - 2ª série 01 turma(s) - 3ª série ANEXO PEDRAS - 18km 01 turma(s) - Alfabetiza 01 turma(s) - 2ª série 01 turma(s) - 3ª série | G52: — | H52: 131 alunos · 4 turmas | I52: — | L52: 3 | N52: • EM - 3ª Série - INTEGRAL - 16 matrículas I - 1 turma • EPT EMI - 1ª Série - CURSO TECNICO EM DESENVOLVIMENTO DE SISTEMAS - 30 matrículas I - 1 turma • EPT EMI - 1ª Série - CURSO TECNICO EM MARKETING DIGITAL - 35 matrículas I - 1 turma • EPT EMI - 2ª Série - CURSO TECNICO EM ADMINISTRACAO COM ENFASE EM EMPREENDEDORISMO - 63 matrículas I - 2 turmas • EPT EMI - 2ª Série - CURSO TECNICO EM DESENVOLVIMENTO DE SISTEMAS - 34 matrículas I - 1 turma • EPT EMI - 3ª Série - CURSO TECNICO EM DESENVOLVIMENTO DE SISTEMAS - 55 matrículas I - 2 turmas Turmas: 8 Integral | Q52: 3 | R52: 3 | S52: — | U52: — | W52: 9 | Z52: • EJA EF I 1/6 - ANOS INICIAIS - 319 matrículas N - 18 turmas • EJA EF I 3/6 - ANOS INICIAIS - 12 matrículas N - 1 turma • EJA EF I 3/6 - ANOS INICIAIS - 16 matrículas N - 1 turma • EJA EF I 4/6 - ANOS INICIAIS - 8 matrículas N - 1 turma • EPT EJA EMI 2/5 - CURSO TECNICO EM ADMINISTRACAO - 23 matrículas N - 1 turma • EPT EJA EMI 4/5 - CURSO TECNICO EM INFORMATICA - 9 matrículas N - 1 turma • EPT EMI - 1ª Série - CURSO TECNICO EM PLANEJAMENTO E CONTROLE DA PRODUCAO - 29 matrículas I - 1 turma Turmas EJA: 1 Integral | 23 Noite | AA52: 416 matrículas | 24 turmas | AG52: 3 de 1ª | 3 de 2ª | 3 de 3ª | Necessidade: salas | | AH52: CETI GAYOSO E ALMENDRA CETI (0.83 km)
A53: 22011170 | B53: 02ª - BARRAS | C53: CAMPO LARGO DO PIAUI | D53: CETI SÃO JOSÉ | E53: POSSUI 05 SLS E NECESSITA 05 SLS 05 TURMA(S) MÉDIO INTEGRAL 03 turma(s) - 1ª série 02 turma(s) - 2ª série MANHÃ - 02 TURMA(S) PARCIAL (ANEXO SALÃO PAROQUIAL) 02 turma(s) - 3ª série TARDE - 01 TURMA(S) PARCIAL (ANEXO SALÃO PAROQUIAL) 01 turma(s) - 3ª série NOITE - 03 TURMA(S) DE EJA ANEXO RURAL POVOADO COSTA 01 turma(s) - 1ª série 01 turma(s) - 2ª série 01 turma(s) - 3ª série 01 turma(s) de EJA ZONA RURAL - SALAS EXTERNAS 04 turma(s) - Alfabetiza | F53: POSSUI 05 SLS E NECESSITA 08 SLS 08 TURMA(S) MÉDIO INTEGRAL 03 turma(s) - 1ª série 03 turma(s) - 2ª série 02 turma(s) - 3ª série NOITE - 03 TURMA(S) DE EJA ANEXO RURAL POVOADO COSTA 01 turma(s) - 1ª série 01 turma(s) - 2ª série 01 turma(s) - 3ª série 01 turma(s) de EJA ZONA RURAL - SALAS EXTERNAS 04 turma(s) - Alfabetiza | G53: — | H53: 119 alunos · 3 turmas | I53: — | L53: 3 | N53: • EM - 3ª Série - PARCIAL DIURNO - 80 matrículas M - 3 turmas • EPT EMI - 1ª Série - CURSO TECNICO EM ADMINISTRACAO COM ENFASE EM EMPREENDEDORISMO - 28 matrículas I - 1 turma • EPT EMI - 1ª Série - CURSO TECNICO EM DESENVOLVIMENTO DE SISTEMAS - 35 matrículas I - 1 turma • EPT EMI - 1ª Série - CURSO TECNICO EM PROGRAMACAO DE JOGOS DIGITAIS - 35 matrículas I - 1 turma • EPT EMI - 2ª Série - CURSO TECNICO EM DESENVOLVIMENTO DE SISTEMAS - 40 matrículas I - 1 turma • EPT EMI - 2ª Série - CURSO TECNICO EM MARKETING DIGITAL - 37 matrículas I - 1 turma Turmas: 5 Integral | 3 Manhã | Q53: 3 | R53: 2 | S53: EM - 3ª Série | MANHÃ | 3T (80 al.) | U53: EM - 3ª Série - PARCIAL DIURNO | MANHÃ: 3T / 80 alunos → 2T (possível liberar 1 turma) | W53: 5 | Z53: • EJA EF I 1/6 - ANOS INICIAIS - 207 matrículas N - 12 turmas • EJA EF I 3/6 - ANOS INICIAIS - 29 matrículas N - 2 turmas • EPT EJA EMI 2/5 - CURSO TECNICO EM AGENTE COMUNITARIO DE SAUDE - 17 matrículas N - 1 turma • EPT EJA EMI 4/5 - CURSO TECNICO EM INFORMATICA - 8 matrículas N - 1 turma Turmas EJA: 16 Noite | AA53: 261 matrículas | 16 turmas | AG53: 3 de 1ª | 3 de 2ª | 2 de 3ª | Necessidade: salas | | AH53: Única no município
A54: 22004777 | B54: 02ª - BARRAS | C54: ESPERANTINA | D54: CETI PETRONIO PORTELA | E54: POSSUI 07 SLS E NECESSITA 07 SLS 05 TURMA(S) MÉDIO INTEGRAL 02 turma(s) - 1ª série 03 turma(s) - 2ª série MANHÃ - 02 TURMA(S) PARCIAIS 02 turma(s) MÉDIO - 3ª série TARDE - 02 TURMA(S) PARCIAIS 01 turma(s) MÉDIO - 3ª série 01 TURMA(S) EJA NOITE - 03 TURMA(S) DE EJA | F54: POSSUI 07 SLS E NECESSITA 07 SLS 06 TURMA(S) MÉDIO INTEGRAL 01 turma(s) - 1ª série 02 turma(s) - 2ª série 03 turma(s) - 3ª série TARDE - 01 TURMA(S) PARCIAIS 01 TURMA(S) EJA NOITE - 03 TURMA(S) DE EJA | G54: — | H54: 552 alunos · 14 turmas | I54: — | L54: 2 | N54: • EM - 3ª Série - PARCIAL DIURNO - 20 matrículas T - 1 turma • EM - 3ª Série - PARCIAL DIURNO - 53 matrículas M - 2 turmas • EPT EMI - 1ª Série - CURSO TECNICO EM CONTROLE AMBIENTAL - 37 matrículas I - 1 turma • EPT EMI - 1ª Série - CURSO TECNICO EM LOGISTICA - 41 matrículas I - 1 turma • EPT EMI - 2ª Série - CURSO TECNICO EM ADMINISTRACAO COM ENFASE EM EMPREENDEDORISMO - 26 matrículas I - 1 turma • EPT EMI - 2ª Série - CURSO TECNICO EM DESENVOLVIMENTO DE SISTEMAS - 60 matrículas I - 2 turmas Turmas: 5 Integral | 2 Manhã | 1 Tarde | Q54: 2 | R54: 3 | S54: EM - 3ª Série | MANHÃ | 2T (53 al.) EM - 3ª Série | TARDE | 1T (20 al.) | U54: — | W54: 7 | Z54: • EJA EF I 1/6 - ANOS INICIAIS - 74 matrículas N - 3 turmas • EJA EF I 2/6 - ANOS INICIAIS - 20 matrículas M - 1 turma • EJA EF I 4/6 - ANOS INICIAIS - 21 matrículas N - 1 turma • EPT EJA EMI 2/5 - CURSO TECNICO EM CONTABILIDADE - 22 matrículas N - 1 turma • EPT EJA EMI 4/5 - CURSO TECNICO EM INFORMATICA - 19 matrículas N - 1 turma Turmas EJA: 1 Manhã | 6 Noite | AA54: 156 matrículas | 7 turmas | AG54: 2 de 1ª | 2 de 2ª | 3 de 3ª | Necessidade: salas | | AH54: CETI ESTADO DA PARAIBA CETI (17.66 km)
A55: 22004793 | B55: 02ª - BARRAS | C55: ESPERANTINA | D55: CETI ESTADO DA PARAIBA | E55: POSSUI 05 SLS E NECESSITA 06 SLS (USA SALA DE AULA DA UAB) 04 TURMA(S) MÉDIO INTEGRAL 02 turma(s) - 1ª série 02 turma(s) - 2ª série MANHÃ - 02 TURMA(S) FUNDAMENTAL PARCIAL 02 turma(s) FUND - 9º ano TARDE - 02 TURMA(S) PARCIAL 01 turma(s) MÉDIO - 3ª série 01 turma(s) de EJA NOITE - 03 TURMA(S) DE EJA | F55: POSSUI 05 SLS E NECESSITA 07 SLS 06 TURMA(S) MÉDIO INTEGRAL 02 turma(s) - 1ª série 02 turma(s) - 2ª série 02 turma(s) - 3ª série TARDE - 01 TURMA(S) PARCIAL 01 turma(s) de EJA NOITE - 03 TURMA(S) DE EJA | G55: • EF - 9º Ano - PARCIAL - ANOS FINAIS - 73 matrículas M - 2 turmas | H55: 552 alunos · 14 turmas | I55: — | L55: 2 | N55: • EM - 3ª Série - PARCIAL DIURNO - 21 matrículas T - 1 turma • EPT EMI - 1ª Série - CURSO TECNICO EM LOGISTICA - 83 matrículas I - 2 turmas • EPT EMI - 2ª Série - CURSO TECNICO EM ADMINISTRACAO COM ENFASE EM EMPREENDEDORISMO - 30 matrículas I - 1 turma • EPT EMI - 2ª Série - CURSO TECNICO EM DESENVOLVIMENTO DE SISTEMAS - 16 matrículas I - 1 turma Turmas: 4 Integral | 1 Tarde | Q55: 2 | R55: 2 | S55: EM - 3ª Série | TARDE | 1T (21 al.) | U55: — | W55: 5 | Z55: • EJA EF I 1/6 - ANOS INICIAIS - 33 matrículas N - 2 turmas • EPT EJA EMI 2/5 - CURSO TECNICO EM AGENTE COMUNITARIO DE SAUDE - 29 matrículas N - 1 turma • EPT EJA EMI 4/5 - CURSO TECNICO EM AGENTE COMUNITARIO DE SAUDE - 31 matrículas N - 2 turmas Turmas EJA: 5 Noite | AA55: 93 matrículas | 5 turmas | AG55: 2 de 1ª | 2 de 2ª | 2 de 3ª | Necessidade: salas | | AH55: Única no município
A56: 22004815 | B56: 02ª - BARRAS | C56: ESPERANTINA | D56: CETI JOSÉ NOGUEIRA DE AGUIAR | E56: POSSUI 14 SLS E NECESSITA 14 SLS (eram 13 salas, foi construída uma via PACTUE em 2026) 14 TURMA(S) MÉDIO INTEGRAL 04 turma(s) - 1ª série 06 turma(s) - 2ª série 04 turma(s) - 3ª série | F56: POSSUI 15 SLS E NECESSITA 14 SLS 14 TURMA(S) MÉDIO INTEGRAL 04 turma(s) - 1ª série 04 turma(s) - 2ª série 06 turma(s) - 3ª série | G56: — | H56: 552 alunos · 14 turmas | I56: — | L56: 4 | N56: • EM - 3ª Série - INTEGRAL - 40 matrículas I - 1 turma • EPT EMI - 1ª Série - CURSO TECNICO EM ADMINISTRACAO COM ENFASE EM EMPREENDEDORISMO - 42 matrículas I - 1 turma • EPT EMI - 1ª Série - CURSO TECNICO EM DESENVOLVIMENTO DE SISTEMAS - 119 matrículas I - 2 turmas • EPT EMI - 1ª Série - CURSO TECNICO EM SEGURANCA DO TRABALHO - 41 matrículas I - 1 turma • EPT EMI - 2ª Série - CURSO TECNICO EM ADMINISTRACAO - 42 matrículas I - 1 turma • EPT EMI - 2ª Série - CURSO TECNICO EM ADMINISTRACAO COM ENFASE EM EMPREENDEDORISMO - 80 matrículas I - 2 turmas • EPT EMI - 2ª Série - CURSO TECNICO EM DESENVOLVIMENTO DE SISTEMAS - 42 matrículas I - 1 turma • EPT EMI - 2ª Série - CURSO TECNICO EM MARKETING DIGITAL - 80 matrículas I - 2 turmas • EPT EMI - 3ª Série - CURSO TECNICO EM ADMINISTRACAO COM ENFASE EM EMPREENDEDORISMO - 34 matrículas I - 1 turma • EPT EMI - 3ª Série - CURSO TECNICO EM DESENVOLVIMENTO DE SISTEMAS - 26 matrículas I - 1 turma • EPT EMI - 3ª Série - CURSO TECNICO EM INFORMATICA PARA INTERNET - 28 matrículas I - 1 turma Turmas: 14 Integral | Q56: 4 | R56: 6 | S56: — | U56: — | W56: 14 | Z56: • EJA EF I 1/6 - ANOS INICIAIS - 41 matrículas N - 2 turmas Turmas EJA: 2 Noite | AA56: 41 matrículas | 2 turmas | AG56: 4 de 1ª | 4 de 2ª | 6 de 3ª | Necessidade: salas | | AH56: CETI JOSÉ NOGUEIRA DE AGUIAR CETI (0.84 km)
A57: 22004823 | B57: 02ª - BARRAS | C57: ESPERANTINA | D57: CETI LEONARDO DAS DORES | E57: POSSUI 12 SLS E NECESSITA 14 SLS (Utilizam Lab de Matemática e Biblioteca como Sala de Aula) 10 TURMA(S) MÉDIO INTEGRAL 06 turma(s) - 1ª série 04 turma(s) - 2ª série MANHÃ - 04 TURMA(S) MÉDIO PARCIAL 04 turma(s) - 3ª série TARDE - 04 TURMA(S) MÉDIO PARCIAL 04 turma(s) - 3ª série NOITE - 09 TURMA(S) DE EJA | F57: POSSUI 13 SLS E NECESSITA 13 SLS 13 TURMA(S) MÉDIO INTEGRAL 03 turma(s) - 1ª série 06 turma(s) - 2ª série 04 turma(s) - 3ª série NOITE - 09 TURMA(S) DE EJA | G57: — | H57: 552 alunos · 14 turmas | I57: — | L57: 6 | N57: • EPT EMI - 1ª Série - CURSO TECNICO EM ANALISES CLINICAS - 117 matrículas I - 2 turmas • EPT EMI - 1ª Série - CURSO TECNICO EM ENFERMAGEM - 40 matrículas I - 1 turma • EPT EMI - 1ª Série - CURSO TECNICO EM FARMACIA - 143 matrículas I - 3 turmas • EPT EMI - 2ª Série - CURSO TECNICO EM ANALISES CLINICAS - 36 matrículas I - 1 turma • EPT EMI - 2ª Série - CURSO TECNICO EM ENFERMAGEM - 33 matrículas I - 1 turma • EPT EMI - 2ª Série - CURSO TECNICO EM FARMACIA - 41 matrículas I - 1 turma • EPT EMI - 2ª Série - CURSO TECNICO EM SAUDE BUCAL - 35 matrículas I - 1 turma • EPT EMI - 3ª Série - CURSO TECNICO EM ADMINISTRACAO COM ENFASE EM EMPREENDEDORISMO - 33 matrículas T - 1 turma • EPT EMI - 3ª Série - CURSO TECNICO EM ADMINISTRACAO COM ENFASE EM EMPREENDEDORISMO - 38 matrículas M - 1 turma • EPT EMI - 3ª Série - CURSO TECNICO EM ANALISES CLINICAS - 35 matrículas T - 1 turma • EPT EMI - 3ª Série - CURSO TECNICO EM DESENVOLVIMENTO DE SISTEMAS - 37 matrículas M - 1 turma • EPT EMI - 3ª Série - CURSO TECNICO EM ENFERMAGEM - 33 matrículas T - 1 turma • EPT EMI - 3ª Série - CURSO TECNICO EM GUIA DE TURISMO - 24 matrículas T - 1 turma • EPT EMI - 3ª Série - CURSO TECNICO EM MARKETING DIGITAL - 31 matrículas M - 1 turma • EPT EMI - 3ª Série - CURSO TECNICO EM PROGRAMACAO DE JOGOS DIGITAIS - 30 matrículas M - 1 turma Turmas: 10 Integral | 4 Manhã | 4 Tarde | Q57: 6 | R57: 4 | S57: — | U57: — | W57: 13 | Z57: • EJA EF I 1/6 - ANOS INICIAIS - 141 matrículas N - 8 turmas • EJA EF I 3/6 - ANOS INICIAIS - 39 matrículas N - 3 turmas • EJA EF I 4/6 - ANOS INICIAIS - 0 matrículas N - 1 turma • EPT EJA EMI #/5 - CURSO TECNICO EM ENFERMAGEM - 22 matrículas N - 1 turma • EPT EJA EMI 2/5 - CURSO TECNICO EM ANALISES CLINICAS - 13 matrículas N - 1 turma • EPT EJA EMI 4/5 - CURSO TECNICO EM ENFERMAGEM - 43 matrículas N - 2 turmas Turmas EJA: 16 Noite | AA57: 258 matrículas | 16 turmas | AG57: 6 de 1ª | 6 de 2ª | 4 de 3ª | Necessidade: salas | | AH57: CETI PETRONIO PORTELA CETI (0.33 km)
A58: 22253734 | B58: 02ª - BARRAS | C58: ESPERANTINA | D58: CETI MARIA DO AMPARO OLIVEIRA | E58: POSSUI 05 SLS E NECESSITA 05 SLS 04 TURMA(S) MÉDIO INTEGRAL 02 turma(s) - 1ª série 02 turma(s) - 2ª série NOITE - 03 TURMA(S) MÉDIO PARCIAL 01 turma(s) - 2ª série 02 turma(s) - 3ª série ANEXO SÃO RAIMUNDO - Escola Municipal Manoel Amorim Neto 02 turma(s) - 1ª série 01 turma(s) - 2ª série 01 turma(s) - 3ª série ANEXO MUNDO NOVO (DESATIVADO) - Escola Municipal João Batista de Amorim Alunos remanejados para Sede - NOITE. | F58: POSSUI 05 SLS E NECESSITA 07 SLS 07 TURMA(S) MÉDIO INTEGRAL 02 turma(s) - 1ª série 02 turma(s) - 2ª série 03 turma(s) - 3ª série NOITE - 01 TURMA(S) MÉDIO PARCIAL 01 turma(s) - 3ª série ANEXO SÃO RAIMUNDO - Escola Municipal Manoel Amorim Neto 02 turma(s) - 1ª série 01 turma(s) - 2ª série 01 turma(s) - 3ª série ANEXO MUNDO NOVO (DESATIVADO) - Escola Municipal João Batista de Amorim Alunos remanejados para Sede - NOITE. | G58: — | H58: 552 alunos · 14 turmas | I58: — | L58: 2 | N58: • EM - 3ª Série - PARCIAL NOTURNO - 74 matrículas N - 2 turmas • EPT EMC 2/4 - CURSO TECNICO EM DESENVOLVIMENTO DE SISTEMAS - 13 matrículas M - 1 turma • EPT EMI - 1ª Série - CURSO TECNICO EM ADMINISTRACAO COM ENFASE EM EMPREENDEDORISMO - 66 matrículas I - 2 turmas • EPT EMI - 2ª Série - CURSO TECNICO EM ADMINISTRACAO COM ENFASE EM EMPREENDEDORISMO - 20 matrículas N - 1 turma • EPT EMI - 2ª Série - CURSO TECNICO EM ADMINISTRACAO COM ENFASE EM EMPREENDEDORISMO - 46 matrículas I - 2 turmas Turmas: 4 Integral | 1 Manhã | 3 Noite | Q58: 2 | R58: 3 | S58: EM - 3ª Série | NOITE | 2T (74 al.) | U58: — | W58: 5 | Z58: • EJA EF I 1/6 - ANOS INICIAIS - 123 matrículas N - 6 turmas Turmas EJA: 6 Noite | AA58: 123 matrículas | 6 turmas | AG58: 2 de 1ª | 2 de 2ª | 3 de 3ª | Necessidade: salas | | AH58: CETI ESTADO DA PARAIBA CETI (2.04 km)
A59: 22005242 | B59: 02ª - BARRAS | C59: JOAQUIM PIRES | D59: CETI DOROTEU SERTAO | E59: POSSUI 13 SLS E NECESSITA 13 SLS (12 salas de tam. padrão e 01 sala menor) 12 TURMA(S) MÉDIO INTEGRAL 04 turma(s) - 1ª série 04 turma(s) - 2ª série 04 turma(s) - 3ª série NOITE - 04 TURMA(S) DE EJA 3 turma(s) - Alfabetiza | F59: POSSUI 12 SLS E NECESSITA 12 SLS 12 TURMA(S) MÉDIO INTEGRAL 04 turma(s) - 1ª série 04 turma(s) - 2ª série 04 turma(s) - 3ª série NOITE - 04 TURMA(S) DE EJA 3 turma(s) - Alfabetiza | G59: — | H59: 214 alunos · 6 turmas | I59: — | L59: 4 | N59: • EM - 3ª Série - INTEGRAL - 54 matrículas I - 2 turmas • EPT EMI - 1ª Série - CURSO TECNICO EM ADMINISTRACAO COM ENFASE EM EMPREENDEDORISMO - 37 matrículas I - 1 turma • EPT EMI - 1ª Série - CURSO TECNICO EM DESENVOLVIMENTO DE SISTEMAS - 118 matrículas I - 3 turmas • EPT EMI - 2ª Série - CURSO TECNICO EM ADMINISTRACAO COM ENFASE EM EMPREENDEDORISMO - 56 matrículas I - 2 turmas • EPT EMI - 2ª Série - CURSO TECNICO EM DESENVOLVIMENTO DE SISTEMAS - 26 matrículas I - 1 turma • EPT EMI - 2ª Série - CURSO TECNICO EM MARKETING DIGITAL - 29 matrículas I - 1 turma • EPT EMI - 3ª Série - CURSO TECNICO EM CONTROLE AMBIENTAL - 32 matrículas I - 1 turma • EPT EMI - 3ª Série - CURSO TECNICO EM MARKETING DIGITAL - 38 matrículas I - 1 turma Turmas: 12 Integral | Q59: 4 | R59: 4 | S59: — | U59: — | W59: 12 | Z59: • EJA EF I 1/6 - ANOS INICIAIS - 230 matrículas N - 13 turmas • EJA EF I 3/6 - ANOS INICIAIS - 27 matrículas N - 2 turmas • EJA EF II 4/4 - ANOS FINAIS - 30 matrículas N - 1 turma • EJA EF II 4/4 - ANOS FINAIS - 30 matrículas N - 1 turma • EJA FIQ/QP 2/# - CUIDADOS DE IDOSOS - 10 matrículas N - 1 turma • EJA Médio FIC/QP 1/2 - ASSIST ADM / INFO BASICA - 21 matrículas N - 1 turma • EJA Médio FIC/QP 1/2 - ASSIST ADM / INFO BASICA - 21 matrículas N - 1 turma • EPT EJA EMI 2/5 - CURSO TECNICO EM CONTABILIDADE - 14 matrículas N - 1 turma Turmas EJA: 21 Noite | AA59: 383 matrículas | 21 turmas | AG59: 4 de 1ª | 4 de 2ª | 4 de 3ª | Necessidade: salas | | AH59: CETI JOSÉ NOGUEIRA DE AGUIAR CETI (0.33 km)
A60: 22005315 | B60: 02ª - BARRAS | C60: JOAQUIM PIRES | D60: CETI JOSÉ MENDES VASCONCELOS | E60: POSSUI 05 SLS E NECESSITA 06 SLS 06 TURMA(S) MÉDIO INTEGRAL 02 turma(s) - 1ª série 02 turma(s) - 2ª série 02 turma(s) - 3ª série NOITE - 02 TURMA(S) DE EJA | F60: POSSUI 06 SLS E NECESSITA 06 SLS 06 TURMA(S) MÉDIO INTEGRAL 02 turma(s) - 1ª série 02 turma(s) - 2ª série 02 turma(s) - 3ª série NOITE - 02 TURMA(S) DE EJA | G60: — | H60: 214 alunos · 6 turmas | I60: — | L60: 2 | N60: • EPT EMI - 1ª Série - CURSO TECNICO EM MARKETING DIGITAL - 34 matrículas I - 1 turma • EPT EMI - 1ª Série - CURSO TECNICO EM PROGRAMACAO DE JOGOS DIGITAIS - 35 matrículas I - 1 turma • EPT EMI - 2ª Série - CURSO TECNICO EM DESENVOLVIMENTO DE SISTEMAS - 26 matrículas I - 1 turma • EPT EMI - 2ª Série - CURSO TECNICO EM MARKETING DIGITAL - 17 matrículas I - 1 turma • EPT EMI - 3ª Série - CURSO TECNICO EM DESENVOLVIMENTO DE SISTEMAS - 25 matrículas I - 1 turma • EPT EMI - 3ª Série - CURSO TECNICO EM MARKETING DIGITAL - 36 matrículas I - 1 turma Turmas: 6 Integral | Q60: 2 | R60: 2 | S60: — | U60: — | W60: 6 | Z60: • EJA EF I 1/6 - ANOS INICIAIS - 95 matrículas N - 5 turmas • EPT EJA EMI 2/5 - CURSO TECNICO EM INFORMATICA - 16 matrículas N - 1 turma • EPT EJA EMI 4/5 - CURSO TECNICO EM INFORMATICA - 9 matrículas N - 1 turma Turmas EJA: 7 Noite | AA60: 120 matrículas | 7 turmas | AG60: 2 de 1ª | 2 de 2ª | 2 de 3ª | Necessidade: salas | | AH60: CETI JOSÉ MENDES VASCONCELOS CETI (0.81 km)
... A85: 22123458 | B85: 03ª - PIRIPIRI | C85: PEDRO II | D85: CETI FAMILIA AGRICOLA SANTA ANGELA | E85: POSSUI 14 SLS E NECESSITA 12 SLS 12 TURMA(S) MÉDIO INTEGRAL 04 turma(s) - 1ª série 04 turma(s) - 2ª série 04 turma(s) - 3ª série ANEXO LAGEDO 08 TURMA(S) FUNDAMENTAL INTEGRAL 01 turma(s) FUND - 6º ano 02 turma(s) FUND - 7º ano 02 turma(s) FUND - 8º ano 02 turma(s) FUND - 9º ano | F85: POSSUI 14 SLS E NECESSITA 12 SLS 12 TURMA(S) MÉDIO INTEGRAL (ALTERNÂNCIA) 04 turma(s) - 1ª série 04 turma(s) - 2ª série 04 turma(s) - 3ª série ANEXO LAGEDO 06 TURMA(S) FUNDAMENTAL INTEGRAL 01 turma(s) FUND - 6º ano 01 turma(s) FUND - 7º ano 02 turma(s) FUND - 8º ano 02 turma(s) FUND - 9º ano | G85: • EF - 6º Ano - INTEGRAL - ANOS FINAIS - 40 matrículas I - 1 turma • EF - 7º Ano - INTEGRAL - ANOS FINAIS - 53 matrículas I - 2 turmas • EF - 8º Ano - INTEGRAL - ANOS FINAIS - 67 matrículas I - 2 turmas • EF - 9º Ano - INTEGRAL - ANOS FINAIS - 45 matrículas I - 2 turmas | H85: 500 alunos · 13 turmas | I85: — | L85: 4 | N85: • EPT EMI - 1ª Série - CURSO TECNICO EM AGROINDUSTRIA - 27 matrículas I - 1 turma • EPT EMI - 1ª Série - CURSO TECNICO EM AGROPECUARIA - 63 matrículas I - 2 turmas • EPT EMI - 1ª Série - CURSO TECNICO EM ZOOTECNIA - 25 matrículas I - 1 turma • EPT EMI - 2ª Série - CURSO TECNICO EM AGROINDUSTRIA - 28 matrículas I - 1 turma • EPT EMI - 2ª Série - CURSO TECNICO EM AGROPECUARIA - 47 matrículas I - 2 turmas • EPT EMI - 2ª Série - CURSO TECNICO EM ZOOTECNIA - 21 matrículas I - 1 turma • EPT EMI - 3ª Série - CURSO TECNICO EM AGROINDUSTRIA - 32 matrículas I - 1 turma • EPT EMI - 3ª Série - CURSO TECNICO EM AGROPECUARIA - 46 matrículas I - 2 turmas • EPT EMI - 3ª Série - CURSO TECNICO EM ZOOTECNIA - 24 matrículas I - 1 turma Turmas: 12 Integral | Q85: 4 | R85: 4 | S85: — | U85: — | W85: 14 | Z85: — | AA85: — | AG85: 4 de 1ª | 4 de 2ª | 4 de 3ª | Necessidade: salas | | AH85: Única no município
A86: 22130640 | G86: • EF - 6º Ano - INTEGRAL - ANOS FINAIS - 29 matrículas I - 1 turma • EF - 7º Ano - INTEGRAL - ANOS FINAIS - 25 matrículas I - 1 turma • EF - 8º Ano - INTEGRAL - ANOS FINAIS - 27 matrículas I - 1 turma • EF - 9º Ano - INTEGRAL - ANOS FINAIS - 24 matrículas I - 1 turma | I86: — | L86: 1 | N86: • EM - 1ª Série - INTEGRAL - 25 matrículas I - 1 turma • EM - 2ª Série - INTEGRAL - 19 matrículas I - 1 turma • EM - 3ª Série - INTEGRAL - 24 matrículas I - 1 turma Turmas: 3 Integral | Q86: 1 | R86: 1 | S86: — | U86: — | Z86: — | AA86: — | AG86: 1 de 1ª | 1 de 2ª | 1 de 3ª | Necessidade: salas |
A87: 22137211 | B87: 03ª - PIRIPIRI | C87: PEDRO II | D87: CETI PROFESSOR PEDRO SOARES | E87: POSSUI 03 E SLS E NECESSITA 03 SLS 03 TURMA(S) MÉDIO INTEGRAL 01 turma(s) - 1ª série 01 turma(s) - 2ª série 01 turma(s) - 3ª série | F87: POSSUI 03 E SLS E NECESSITA 03 SLS 03 TURMA(S) MÉDIO INTEGRAL 01 turma(s) - 1ª série 01 turma(s) - 2ª série 01 turma(s) - 3ª série | G87: — | H87: 500 alunos · 13 turmas | I87: — | L87: 1 | N87: • EPT EMI - 1ª Série - CURSO TECNICO EM ADMINISTRACAO COM ENFASE EM EMPREENDEDORISMO - 16 matrículas I - 1 turma • EPT EMI - 2ª Série - CURSO TECNICO EM ADMINISTRACAO COM ENFASE EM EMPREENDEDORISMO - 7 matrículas I - 1 turma • EPT EMI - 3ª Série - CURSO TECNICO EM CONTROLE AMBIENTAL - 14 matrículas I - 1 turma Turmas: 3 Integral | Q87: 1 | R87: 1 | S87: — | U87: — | W87: 3 | Z87: • EJA EF I 1/6 - ANOS INICIAIS - 0 matrículas N - 1 turma Turmas EJA: 1 Noite | AA87: 0 matrículas | 1 turmas | AG87: 1 de 1ª | 1 de 2ª | 1 de 3ª | Necessidade: salas | | AH87: Única no município
A88: 22016694 | B88: 03ª - PIRIPIRI | C88: PIRACURUCA | D88: CETI PATRONATO IRMAOS DANTAS | E88: POSSUI 12 SLS E NECESSITA 12 SLS 06 TURMA(S) MÉDIO INTEGRAL 03 turma(s) - 1ª série 03 turma(s) - 2ª série MANHÃ - 06 TURMA(S) FUNDAMENTAL PARCIAL 03 turma(s) FUND - 7º ano 03 turma(s) FUND - 8º ano TARDE - 06 TURMA(S) PARCIAIS 02 turma(s) MÉDIO - 3ª série 03 turma(s) FUND - 9º ano | F88: POSSUI 12 SLS E NECESSITA 15SLS 08 TURMA(S) MÉDIO INTEGRAL 03 turma(s) - 1ª série 03 turma(s) - 2ª série 03 turma(s) - 3ª série MANHÃ - 06 TURMA(S) FUNDAMENTAL PARCIAL 03 turma(s) FUND - 8º ano 03 turma(s) FUND - 9º ano | G88: • EF - 7º Ano - PARCIAL - ANOS FINAIS - 148 matrículas M - 3 turmas • EF - 8º Ano - PARCIAL - ANOS FINAIS - 151 matrículas M - 3 turmas • EF - 9º Ano - PARCIAL - ANOS FINAIS - 155 matrículas T - 3 turmas | H88: 412 alunos · 11 turmas | I88: — | L88: 3 | N88: • EM - 3ª Série - PARCIAL DIURNO - 140 matrículas T - 3 turmas • EPT EMI - 1ª Série - CURSO TECNICO EM ADMINISTRACAO COM ENFASE EM EMPREENDEDORISMO - 36 matrículas I - 1 turma • EPT EMI - 1ª Série - CURSO TECNICO EM ALIMENTOS - 24 matrículas I - 1 turma • EPT EMI - 1ª Série - CURSO TECNICO EM SEGURANCA DO TRABALHO - 35 matrículas I - 1 turma • EPT EMI - 2ª Série - CURSO TECNICO EM DESENVOLVIMENTO DE SISTEMAS - 27 matrículas I - 1 turma • EPT EMI - 2ª Série - CURSO TECNICO EM MARKETING DIGITAL - 33 matrículas I - 1 turma • EPT EMI - 2ª Série - CURSO TECNICO EM PROGRAMACAO DE JOGOS DIGITAIS - 29 matrículas I - 1 turma Turmas: 6 Integral | 3 Tarde | Q88: 3 | R88: 3 | S88: EM - 3ª Série | TARDE | 3T (140 al.) | U88: — | W88: 12 | Z88: — | AA88: — | AG88: 3 de 1ª | 3 de 2ª | 3 de 3ª | Necessidade: salas | | AH88: CETI FAMILIA AGRICOLA SANTA ANGELA CETI (1.61 km)
A89: 22016724 | B89: 03ª - PIRIPIRI | C89: PIRACURUCA | D89: CETI HESICHIA DE SOUSA BRITO | E89: POSSUI 13 SLS E NECESSITA 12 SLS 10 TURMA(S) MÉDIO INTEGRAL 04 turma(s) - 1ª série 04 turma(s) - 2ª série 03 turma(s) - 3ª série TARDE - 02 TURMA(S) PARCIAIS 02 turma(s) - 3ª série NOITE - 07 TURMA(S) DE EJA ANEXOS (Angical e Jacareí) - 06 turma(s) 02 turma(s) - 1ª série 02 turma(s) - 2ª série 02 turma(s) - 3ª série | F89: POSSUI 13 SLS E NECESSITA 12 SLS 12 TURMA(S) MÉDIO INTEGRAL 04 turma(s) - 1ª série 04 turma(s) - 2ª série 04 turma(s) - 3ª série NOITE - 07 TURMA(S) DE EJA ANEXOS (Angical e Jacareí) - 06 turma(s) 02 turma(s) - 1ª série 02 turma(s) - 2ª série 02 turma(s) - 3ª série | G89: — | H89: 412 alunos · 11 turmas | I89: — | L89: 4 | N89: • EM - 3ª Série - INTEGRAL - 26 matrículas I - 1 turma • EM - 3ª Série - PARCIAL DIURNO - 74 matrículas T - 2 turmas • EPT EMI - 1ª Série - CURSO TECNICO EM DESENVOLVIMENTO DE SISTEMAS - 84 matrículas I - 2 turmas • EPT EMI - 1ª Série - CURSO TECNICO EM SEGURANCA DO TRABALHO - 43 matrículas I - 1 turma • EPT EMI - 1ª Série - CURSO TECNICO EM SERVICOS DE RESTAURANTE E BAR - 42 matrículas I - 1 turma • EPT EMI - 2ª Série - CURSO TECNICO EM ADMINISTRACAO - 87 matrículas I - 2 turmas • EPT EMI - 2ª Série - CURSO TECNICO EM DESENVOLVIMENTO DE SISTEMAS - 34 matrículas I - 1 turma • EPT EMI - 2ª Série - CURSO TECNICO EM MARKETING DIGITAL - 34 matrículas I - 1 turma • EPT EMI - 3ª Série - CURSO TECNICO EM DESENVOLVIMENTO DE SISTEMAS - 42 matrículas I - 2 turmas Turmas: 11 Integral | 2 Tarde | Q89: 4 | R89: 4 | S89: EM - 3ª Série | TARDE | 2T (74 al.) | U89: — | W89: 13 | Z89: • EJA EF I 1/6 - ANOS INICIAIS - 253 matrículas N - 15 turmas • EJA EF I 4/6 - ANOS INICIAIS - 71 matrículas N - 4 turmas • EJA EM 2/2 - ALTERNATIVO - 23 matrículas N - 1 turma Turmas EJA: 20 Noite | AA89: 347 matrículas | 20 turmas | AG89: 4 de 1ª | 4 de 2ª | 4 de 3ª | Necessidade: salas | | AH89: CETI TERTULIANO BRANDÃO FILHO CETI (0.08 km)
A90: 22016937 | B90: 03ª - PIRIPIRI | C90: PIRACURUCA | D90: CETI ANISIO BRITO | E90: POSSUI 08 SLS E NECESSITA 07 SLS 04 TURMA(S) MÉDIO INTEGRAL 01 turma(s) - 1ª série 02 turma(s) - 2ª série 01 turma(s) - 3ª série MANHÃ - 03 TURMA(S) FUNDAMENTAL PARCIAL 01 turma(s) FUND - 8º ano 02 turma(s) FUND - 9º ano NOITE - 11 TURMA(S) DE EJA | F90: POSSUI 08 SLS E NECESSITA 06 SLS 04 TURMA(S) MÉDIO INTEGRAL 01 turma(s) - 1ª série 01 turma(s) - 2ª série 02 turma(s) - 3ª série MANHÃ - 02 TURMA(S) FUNDAMENTAL PARCIAL 01 turma(s) FUND - 8º ano 01 turma(s) FUND - 9º ano NOITE - 11 TURMA(S) DE EJA | G90: • EF - 8º Ano - PARCIAL - ANOS FINAIS - 20 matrículas M - 1 turma • EF - 9º Ano - PARCIAL - ANOS FINAIS - 62 matrículas M - 2 turmas | H90: 412 alunos · 11 turmas | I90: — | L90: 1 | N90: • EPT EMI - 1ª Série - CURSO TECNICO EM ADMINISTRACAO COM ENFASE EM EMPREENDEDORISMO - 32 matrículas I - 1 turma • EPT EMI - 2ª Série - CURSO TECNICO EM AGENTE COMUNITARIO DE SAUDE - 16 matrículas I - 1 turma • EPT EMI - 2ª Série - CURSO TECNICO EM DESENVOLVIMENTO DE SISTEMAS - 18 matrículas I - 1 turma • EPT EMI - 3ª Série - CURSO TECNICO EM DESENVOLVIMENTO DE SISTEMAS - 18 matrículas I - 1 turma • EPT EMS #/2 - CURSO TECNICO EM SEGURANCA DO TRABALHO - 22 matrículas N - 1 turma Turmas: 4 Integral | 1 Noite | Q90: 1 | R90: 2 | S90: — | U90: — | W90: 8 | Z90: • EJA EF I 1/6 - ANOS INICIAIS - 184 matrículas N - 6 turmas • EJA EF I 3/6 - ANOS INICIAIS - 20 matrículas N - 1 turma • EJA EF II 2/2 - ALTERNATIVA - 15 matrículas N - 1 turma • EJA EM 2/2 - ALTERNATIVO - 19 matrículas N - 1 turma • EJA FIQ/QP 2/# - CUIDADOS DE IDOSOS - 8 matrículas N - 1 turma • EPT EJA EMI 2/5 - CURSO TECNICO EM AGENTE COMUNITARIO DE SAUDE - 42 matrículas N - 2 turmas • EPT EJA EMI 4/5 - CURSO TECNICO EM INFORMATICA - 26 matrículas N - 1 turma Turmas EJA: 13 Noite | AA90: 314 matrículas | 13 turmas | AG90: 1 de 1ª | 1 de 2ª | 2 de 3ª | Necessidade: salas | | AH90: CETI MARIA MENDES MOURÃO CETI (17.24 km)
A91: 22017011 | B91: 03ª - PIRIPIRI | C91: PIRACURUCA | D91: CETI INES DE MARIA SOUSA ROCHA | E91: POSSUI 11 SLS E NECESSITA 10 SLS 10 TURMA(S) MÉDIO INTEGRAL 04 turma(s) - 1ª série 03 turma(s) - 2ª série 03 turma(s) - 3ª série NOITE - 04 TURMA(S) DE EJA | F91: POSSUI 11 SLS E NECESSITA 11 SLS 11 TURMA(S) MÉDIO INTEGRAL 04 turma(s) - 1ª série 04 turma(s) - 2ª série 03 turma(s) - 3ª série NOITE - 04 TURMA(S) DE EJA | G91: — | H91: 412 alunos · 11 turmas | I91: — | L91: 4 | N91: • EM - 3ª Série - INTEGRAL - 38 matrículas I - 1 turma • EPT EMI - 1ª Série - CURSO TECNICO EM ANALISES CLINICAS - 30 matrículas I - 1 turma • EPT EMI - 1ª Série - CURSO TECNICO EM ENFERMAGEM - 67 matrículas I - 2 turmas • EPT EMI - 1ª Série - CURSO TECNICO EM GUIA DE TURISMO - 30 matrículas I - 1 turma • EPT EMI - 2ª Série - CURSO TECNICO EM ADMINISTRACAO - 37 matrículas I - 1 turma • EPT EMI - 2ª Série - CURSO TECNICO EM GUIA DE TURISMO - 33 matrículas I - 1 turma • EPT EMI - 2ª Série - CURSO TECNICO EM SEGURANCA DO TRABALHO - 29 matrículas I - 1 turma • EPT EMI - 3ª Série - CURSO TECNICO EM DESENVOLVIMENTO DE SISTEMAS - 35 matrículas I - 1 turma • EPT EMI - 3ª Série - CURSO TECNICO EM MARKETING DIGITAL - 22 matrículas I - 1 turma • EPT EMS 1/2 - CURSO TECNICO EM AGROPECUARIA - 39 matrículas N - 1 turma • EPT EMS 1/2 - CURSO TECNICO EM DESENVOLVIMENTO DE SISTEMAS - 40 matrículas N - 1 turma Turmas: 10 Integral | 2 Noite | Q91: 4 | R91: 3 | S91: — | U91: — | W91: 11 | Z91: • EJA EF I 1/6 - ANOS INICIAIS - 86 matrículas N - 5 turmas • EPT EJA EMI #/5 - CURSO TECNICO EM ENFERMAGEM - 37 matrículas N - 2 turmas • EPT EJA EMI 2/5 - CURSO TECNICO EM ANALISES CLINICAS - 32 matrículas N - 2 turmas Turmas EJA: 9 Noite | AA91: 155 matrículas | 9 turmas | AG91: 4 de 1ª | 4 de 2ª | 3 de 3ª | Necessidade: salas | | AH91: CETI PROFESSORA ANGELINA MENDES BRAGA CETI (0.08 km)
A92: 22147403 | B92: 03ª - PIRIPIRI | C92: PIRACURUCA | D92: CETI PROFESSOR ANTÔNIO DE BRITO FORTES | E92: POSSUI 05 SLS E NECESSITA 03 SLS 03 TURMA(S) MÉDIO INTEGRAL (03 turma(s) de altenância) 01 turma(s) - 1ª série 01 turma(s) - 2ª série 01 turma(s) - 3ª série | F92: POSSUI 05 SLS E NECESSITA 03 SLS 03 TURMA(S) MÉDIO INTEGRAL (03 turma(s) de altenância) 01 turma(s) - 1ª série 01 turma(s) - 2ª série 01 turma(s) - 3ª série | G92: — | H92: 412 alunos · 11 turmas | I92: — | L92: 1 | N92: • EPT EMI - 1ª Série - CURSO TECNICO EM AGROPECUARIA - 20 matrículas I - 1 turma • EPT EMI - 2ª Série - CURSO TECNICO EM AGROPECUARIA - 20 matrículas I - 1 turma • EPT EMI - 3ª Série - CURSO TECNICO EM AGROPECUARIA - 7 matrículas I - 1 turma Turmas: 3 Integral | Q92: 1 | R92: 1 | S92: — | U92: — | W92: 5 | Z92: — | AA92: — | AG92: 1 de 1ª | 1 de 2ª | 1 de 3ª | Necessidade: salas | | AH92: CETI INES DE MARIA SOUSA ROCHA CETI (0.31 km)
A93: 22010254 | B93: 03ª - PIRIPIRI | C93: PIRIPIRI | D93: CETI JUDITH ALVES SANTANA | E93: POSSUI 08 SLS E NECESSITA 08 SLS 08 TURMA(S) MÉDIO INTEGRAL 03 turma(s) - 1ª série 03 turma(s) - 2ª série 02 turma(s) - 3ª série | F93: POSSUI 08 SLS E NECESSITA 08 SLS 08 TURMA(S) MÉDIO INTEGRAL 02 turma(s) - 1ª série 03 turma(s) - 2ª série 03 turma(s) - 3ª série | G93: — | H93: 959 alunos · 24 turmas | I93: — | L93: 3 | N93: • EM - 3ª Série - INTEGRAL - 32 matrículas I - 1 turma • EPT EMI - 1ª Série - CURSO TECNICO EM ADMINISTRACAO COM ENFASE EM EMPREENDEDORISMO - 36 matrículas I - 1 turma • EPT EMI - 1ª Série - CURSO TECNICO EM GUIA DE TURISMO - 38 matrículas I - 1 turma • EPT EMI - 1ª Série - CURSO TECNICO EM SEGURANCA DO TRABALHO - 36 matrículas I - 1 turma • EPT EMI - 2ª Série - CURSO TECNICO EM ADMINISTRACAO - 34 matrículas I - 1 turma • EPT EMI - 2ª Série - CURSO TECNICO EM ADMINISTRACAO COM ENFASE EM EMPREENDEDORISMO - 30 matrículas I - 1 turma • EPT EMI - 2ª Série - CURSO TECNICO EM DESENVOLVIMENTO DE SISTEMAS - 30 matrículas I - 1 turma • EPT EMI - 3ª Série - CURSO TECNICO EM PROGRAMACAO DE JOGOS DIGITAIS - 28 matrículas I - 1 turma Turmas: 8 Integral | Q93: 3 | R93: 3 | S93: — | U93: — | W93: 8 | Z93: — | AA93: — | AG93: 3 de 1ª | 3 de 2ª | 3 de 3ª | Necessidade: salas | | AH93: CETI BAURELIO MANGABEIRA CETI (0.12 km)
A94: 22010467 | B94: 03ª - PIRIPIRI | C94: PIRIPIRI | D94: CETI JOSÉ NARCISO DA ROCHA FILHO | E94: POSSUI 09 SLS E NECESSITA 09 SLS 09 TURMA(S) MÉDIO INTEGRAL 03 turma(s) - 1ª série 03 turma(s) - 2ª série 03 turma(s) - 3ª série | F94: POSSUI 09 SLS E NECESSITA 09 SLS 09 TURMA(S) MÉDIO INTEGRAL 03 turma(s) - 1ª série 03 turma(s) - 2ª série 03 turma(s) - 3ª série | G94: — | H94: 959 alunos · 24 turmas | I94: — | L94: 3 | N94: • EM - 3ª Série - INTEGRAL - 79 matrículas I - 2 turmas • EPT EMI - 1ª Série - CURSO TECNICO EM CONTROLE AMBIENTAL - 38 matrículas I - 1 turma • EPT EMI - 1ª Série - CURSO TECNICO EM PROGRAMACAO DE JOGOS DIGITAIS - 38 matrículas I - 1 turma • EPT EMI - 2ª Série - CURSO TECNICO EM ADMINISTRACAO - 41 matrículas I - 1 turma • EPT EMI - 2ª Série - CURSO TECNICO EM AGENTE COMUNITARIO DE SAUDE - 37 matrículas I - 1 turma • EPT EMI - 2ª Série - CURSO TECNICO EM MARKETING DIGITAL - 36 matrículas I - 1 turma • EPT EMI - 3ª Série - CURSO TECNICO EM DESENVOLVIMENTO DE SISTEMAS - 36 matrículas I - 1 turma Turmas: 8 Integral | Q94: 3 | R94: 3 | S94: — | U94: — | W94: 9 | Z94: • EJA EF I 1/6 - ANOS INICIAIS - 17 matrículas N - 2 turmas • EPT EMI - 1ª Série - CURSO TECNICO EM PLANEJAMENTO E CONTROLE DA PRODUCAO - 39 matrículas I - 1 turma Turmas EJA: 1 Integral | 2 Noite | AA94: 56 matrículas | 3 turmas | AG94: 3 de 1ª | 3 de 2ª | 3 de 3ª | Necessidade: salas | | AH94: CETI JOSÉ NARCISO DA ROCHA FILHO CETI (0.12 km)
A95: 22010483 | B95: 03ª - PIRIPIRI | C95: PIRIPIRI | D95: CETI BAURELIO MANGABEIRA | E95: POSSUI 08 SLS E NECESSITA 08 SLS 08 TURMA(S) MÉDIO INTEGRAL 03 turma(s) - 1ª série 03 turma(s) - 2ª série 02 turma(s) - 3ª série | F95: POSSUI 08 SLS E NECESSITA 08 SLS 08 TURMA(S) MÉDIO INTEGRAL 02 turma(s) - 1ª série 03 turma(s) - 2ª série 03 turma(s) - 3ª série | G95: — | H95: 959 alunos · 24 turmas | I95: — | L95: 3 | N95: • EPT EMI - 1ª Série - CURSO TECNICO EM DESENVOLVIMENTO DE SISTEMAS - 36 matrículas I - 1 turma • EPT EMI - 1ª Série - CURSO TECNICO EM SEGURANCA DO TRABALHO - 82 matrículas I - 2 turmas • EPT EMI - 2ª Série - CURSO TECNICO EM DESENVOLVIMENTO DE SISTEMAS - 39 matrículas I - 1 turma • EPT EMI - 2ª Série - CURSO TECNICO EM SISTEMAS DE ENERGIA RENOVAVEL - 83 matrículas I - 2 turmas • EPT EMI - 3ª Série - CURSO TECNICO EM DESENVOLVIMENTO DE SISTEMAS - 91 matrículas I - 2 turmas Turmas: 8 Integral | Q95: 3 | R95: 3 | S95: — | U95: — | W95: 8 | Z95: • EJA EF I 1/6 - ANOS INICIAIS - 149 matrículas N - 9 turmas Turmas EJA: 9 Noite | AA95: 149 matrículas | 9 turmas | AG95: 3 de 1ª | 3 de 2ª | 3 de 3ª | Necessidade: salas | | AH95: CETI ANISIO BRITO CETI (0.31 km)
A96: 22010505 | B96: 03ª - PIRIPIRI | C96: PIRIPIRI | D96: CETI DES JOSÉ DE ARIMATHEA TITO | E96: POSSUI 08 E SLS E NECESSITA 08 SLS 06 TURMA(S) MÉDIO INTEGRAL 02 turma(s) - 1ª série 02 turma(s) - 2ª série 02 turma(s) - 3ª série 02 TURMA(S) FUNDAMENTAL INTEGRAL 02 turma(s) - 9º ano | F96: POSSUI 08 E SLS E NECESSITA 08 SLS 06 TURMA(S) MÉDIO INTEGRAL 02 turma(s) - 1ª série 02 turma(s) - 2ª série 02 turma(s) - 3ª série 02 TURMA(S) FUNDAMENTAL INTEGRAL 02 turma(s) - 9º ano | G96: • EF - 9º Ano - INTEGRAL - ANOS FINAIS - 78 matrículas I - 2 turmas | H96: 959 alunos · 24 turmas | I96: — | L96: 2 | N96: • EPT EMI - 1ª Série - CURSO TECNICO EM ADMINISTRACAO COM ENFASE EM EMPREENDEDORISMO - 36 matrículas I - 1 turma • EPT EMI - 1ª Série - CURSO TECNICO EM DESENVOLVIMENTO DE SISTEMAS - 37 matrículas I - 1 turma • EPT EMI - 2ª Série - CURSO TECNICO EM DESENVOLVIMENTO DE SISTEMAS - 42 matrículas I - 1 turma • EPT EMI - 2ª Série - CURSO TECNICO EM PROGRAMACAO DE JOGOS DIGITAIS - 41 matrículas I - 1 turma • EPT EMI - 3ª Série - CURSO TECNICO EM INFORMATICA PARA INTERNET - 56 matrículas I - 2 turmas Turmas: 6 Integral | Q96: 2 | R96: 2 | S96: — | U96: — | W96: 8 | Z96: • EJA EF I 1/6 - ANOS INICIAIS - 18 matrículas N - 1 turma Turmas EJA: 1 Noite | AA96: 18 matrículas | 1 turmas | AG96: 2 de 1ª | 2 de 2ª | 2 de 3ª | Necessidade: salas | | AH96: CETI PATRONATO IRMAOS DANTAS CETI (4.18 km)
A97: 22010513 | B97: 03ª - PIRIPIRI | C97: PIRIPIRI | D97: CEJA PROFESSORA COTA SAMPAIO | E97: POSSUI 05 SALAS E NECESSITA 05 TARDE - 04 TURMA(S) DE EJA NOITE - 05 TURMA(S) DE EJA Anexo São Luís - 15km NOITE - 03 turma(s) de EJA Anexo Vertentes - 18km NOITE - 02 turma(s) de EJA | F97: POSSUI 05 SALAS E NECESSITA 05 TARDE - 04 TURMA(S) DE EJA NOITE - 05 TURMA(S) DE EJA Anexo São Luís - 15km NOITE - 03 turma(s) de EJA Anexo Vertentes - 18km NOITE - 02 turma(s) de EJA | G97: — | H97: 959 alunos · 24 turmas | I97: — | L97: 0 | N97: • EPT EMC 5/4 - AUXILIAR ADMINISTRATIVO - 9 matrículas N - 1 turma Turmas: 1 Noite | Q97: 0 | R97: 0 | S97: — | U97: — | W97: 4 | Z97: • EJA EF I 1/6 - ANOS INICIAIS - 189 matrículas N - 10 turmas • EJA EF I 3/6 - ANOS INICIAIS - 17 matrículas N - 1 turma • EJA EF I 4/6 - ANOS INICIAIS - 9 matrículas N - 1 turma • EJA EF II 2/2 - ALTERNATIVA - 16 matrículas T - 1 turma • EJA Médio FIC/QP 1/2 - ASSIST ADM / INFO BASICA - 38 matrículas N - 2 turmas • EJA Médio FIC/QP 1/2 - ASSIST ADM / INFO BASICA - 38 matrículas N - 2 turmas • EJA Médio FIC/QP 2/4 - ASSISTENTE ADMINISTRATIVO - 39 matrículas N - 2 turmas • EPT EJA EMI 2/5 - CURSO TECNICO EM ADMINISTRACAO - 20 matrículas N - 1 turma • EPT EJA EMI 2/5 - CURSO TECNICO EM INFORMATICA - 7 matrículas T - 1 turma • EPT EJA EMI 4/5 - CURSO TECNICO EM ADMINISTRACAO - 12 matrículas N - 1 turma • EPT EJA EMI 4/5 - CURSO TECNICO EM INFORMATICA - 20 matrículas T - 1 turma Turmas EJA: 3 Tarde | 20 Noite | AA97: 405 matrículas | 23 turmas | AG97: 0 de 1ª | 0 de 2ª | 0 de 3ª | Necessidade: salas | | AH97: CETI ANISIO BRITO CETI (0.58 km)
A98: 22010521 | B98: 03ª - PIRIPIRI | C98: PIRIPIRI | D98: CETI PROF NENEM CAVALCANTE | E98: POSSUI 06 SLS E NECESSITA 06 SLS 05 TURMA(S) MÉDIO INTEGRAL 02 turma(s) - 1ª série 02 turma(s) - 2ª série 01 turma(s) - 3ª série MANHÃ - 01 TURMA(S) FUNDAMENTAL PARCIAL 01 turma(s) FUND - 9º ano TARDE - 01 TURMA(S) FUNDAMENTAL PARCIAL 01 turma(s) FUND - 9º ano | F98: POSSUI 06 SLS E NECESSITA 06 SLS 06 TURMA(S) MÉDIO INTEGRAL 02 turma(s) - 1ª série 02 turma(s) - 2ª série 02 turma(s) - 3ª série | G98: • EF - 9º Ano - PARCIAL - ANOS FINAIS - 33 matrículas M - 1 turma • EF - 9º Ano - PARCIAL - ANOS FINAIS - 35 matrículas T - 1 turma | H98: 959 alunos · 24 turmas | I98: — | L98: 2 | N98: • EPT EMI - 1ª Série - CURSO TECNICO EM DESENVOLVIMENTO DE SISTEMAS - 38 matrículas I - 1 turma • EPT EMI - 1ª Série - CURSO TECNICO EM SEGURANCA DO TRABALHO - 40 matrículas I - 1 turma • EPT EMI - 2ª Série - CURSO TECNICO EM ADMINISTRACAO COM ENFASE EM EMPREENDEDORISMO - 23 matrículas I - 1 turma • EPT EMI - 2ª Série - CURSO TECNICO EM DESENVOLVIMENTO DE SISTEMAS - 28 matrículas I - 1 turma • EPT EMI - 3ª Série - CURSO TECNICO EM INFORMATICA PARA INTERNET - 20 matrículas I - 1 turma Turmas: 5 Integral | Q98: 2 | R98: 2 | S98: — | U98: — | W98: 6 | Z98: • EJA EF I 1/6 - ANOS INICIAIS - 62 matrículas N - 3 turmas Turmas EJA: 3 Noite | AA98: 62 matrículas | 3 turmas | AG98: 2 de 1ª | 2 de 2ª | 2 de 3ª | Necessidade: salas | | AH98: CETI BAURELIO MANGABEIRA CETI (9.24 km)
... A577: 22143017 | B577: 21ª - TERESINA SUDESTE | C577: TERESINA | D577: CETI PROFESSOR JOSÉ PACIFICO DE MOURA NETO | E577: POSSUI 13 SLS E NECESSITA 13 SLS 09 TURMA(S) MÉDIO INTEGRAL 06 turma(s) - 1ª série 03 turma(s) - 2ª série MANHÃ - 03 TURMA(S) PARCIAIS 03 turma(s) - 3ª série TARDE - 04 TURMA(S) PARCIAIS 04 turma(s) - 3ª série NOITE - 12 TURMA(S) EJA | F577: POSSUI 13 SLS E NECESSITA 12 SLS 12 TURMA(S) MÉDIO INTEGRAL 03 turma(s) - 1ª série 06 turma(s) - 2ª série 03 turma(s) - 3ª série NOITE - 12 TURMA(S) EJA | G577: — | H577: 11425 alunos · 286 turmas | I577: — | L577: 6 | N577: • EPT EMI - 1ª Série - CURSO TECNICO EM ANALISES CLINICAS - 42 matrículas I - 1 turma • EPT EMI - 1ª Série - CURSO TECNICO EM MANUTENCAO AUTOMOTIVA - 158 matrículas I - 2 turmas • EPT EMI - 1ª Série - CURSO TECNICO EM MODELAGEM DO VESTUARIO - 49 matrículas I - 1 turma • EPT EMI - 1ª Série - CURSO TECNICO EM SISTEMAS DE ENERGIA RENOVAVEL - 175 matrículas I - 2 turmas • EPT EMI - 2ª Série - CURSO TECNICO EM ANALISES CLINICAS - 41 matrículas I - 1 turma • EPT EMI - 2ª Série - CURSO TECNICO EM DESENVOLVIMENTO DE SISTEMAS - 31 matrículas I - 1 turma • EPT EMI - 2ª Série - CURSO TECNICO EM ENFERMAGEM - 78 matrículas I - 1 turma • EPT EMI - 3ª Série - CURSO TECNICO EM ANALISES CLINICAS - 37 matrículas T - 1 turma • EPT EMI - 3ª Série - CURSO TECNICO EM DESENVOLVIMENTO DE SISTEMAS - 34 matrículas M - 1 turma • EPT EMI - 3ª Série - CURSO TECNICO EM ENFERMAGEM - 47 matrículas T - 1 turma • EPT EMI - 3ª Série - CURSO TECNICO EM FARMACIA - 43 matrículas M - 1 turma • EPT EMI - 3ª Série - CURSO TECNICO EM MODELAGEM DO VESTUARIO - 36 matrículas M - 1 turma • EPT EMI - 3ª Série - CURSO TECNICO EM SEGURANCA DO TRABALHO - 41 matrículas T - 1 turma • EPT EMI - 3ª Série - CURSO TECNICO EM SISTEMAS DE ENERGIA RENOVAVEL - 41 matrículas T - 1 turma • EPT EMS 1/2 - CURSO TECNICO EM EDIFICACOES - 27 matrículas N - 1 turma • EPT EMS 1/2 - CURSO TECNICO EM MANUTENCAO AUTOMOTIVA - 17 matrículas N - 1 turma Turmas: 9 Integral | 3 Manhã | 4 Tarde | 2 Noite | Q577: 6 | R577: 3 | S577: — | U577: — | W577: 13 | Z577: • EJA EF I 1/6 - ANOS INICIAIS - 21 matrículas N - 1 turma • EPT EJA EMI #/5 - CURSO TECNICO EM ENFERMAGEM - 25 matrículas N - 1 turma • EPT EJA EMI 1/5 - CURSO TECNICO EM ANALISES CLINICAS - 17 matrículas N - 1 turma • EPT EJA EMI 1/5 - CURSO TECNICO EM ENFERMAGEM - 30 matrículas N - 1 turma • EPT EJA EMI 1/5 - CURSO TECNICO EM FARMACIA - 24 matrículas N - 1 turma • EPT EJA EMI 4/5 - CURSO TECNICO EM ANALISES CLINICAS - 12 matrículas N - 1 turma • EPT EJA EMI 4/5 - CURSO TECNICO EM ENFERMAGEM - 44 matrículas N - 2 turmas • EPT EJA EMI 4/5 - CURSO TECNICO EM FARMACIA - 23 matrículas N - 1 turma • EPT EJA EMI 4/5 - CURSO TECNICO EM INFORMATICA - 7 matrículas N - 1 turma • EPT EJA EMI 4/5 - CURSO TECNICO EM MANUTENCAO AUTOMOTIVA - 8 matrículas N - 1 turma Turmas EJA: 11 Noite | AA577: 211 matrículas | 11 turmas | AG577: 6 de 1ª | 6 de 2ª | 3 de 3ª | Necessidade: salas | | AH577: CETI GOVERNADOR FREITAS NETO CETI (0.80 km)

Sheet Reordenamento 2027 V2
A1: INEP | B1: GRE | C1: Município | D1: Escola | E1: Turmas hoje (2026) | F1: Turmas 2027 (projeção) | G1: Oferta Fundamental | H1: 9º Ano do município | I1: Ainda faltam no município | J1: ★ FUNDAMENTAL 2027 — DECIDA AQUI | K1: IDEB | L1: 1ª Série 2026 | M1: ★ 1ª SÉRIE 2027 DECIDA AQUI | N1: Cursos EM 2026 (sem EJA) | O1: ★ CURSOS 1ª SÉRIE 2027 — DECIDA AQUI | P1: ALTERAÇÃO DE CURSOS EMI | Q1: 2ª Série 2027 | R1: 3ª Série 2027 | S1: Parciais 2026 | T1: Parciais 2026 justificativa | U1: Possíveis Fusões de Turmas | V1: Validações Fusões Turmas | W1: Salas existentes | X1: ★ SALAS NECESSÁRIAS 2027 — DECIDA AQUI | Y1: Situação da sala | Z1: Oferta EJA 2026 | AA1: Matrículas / Turmas EJA | AB1: ★ EJA Turmas 2027 | AC1: ★ EJA Cursos 2027 | AD1: ANEXOS | AE1: CURSOS | AF1: (reservado) | AG1: Resumo 2027 | AH1: Escola Próxima | AI1: Reordenamento 2027 | AJ1: Justificativa | AK1: Observação | AL1: ✓ Pronto
A2: 22129723 | B2: =IFERROR(VLOOKUP($A2,'Base GDI'!$A$2:$AL$1501,3,FALSE),"") | C2: BOM PRINCIPIO DO PIAUI | D2: =IFERROR(VLOOKUP($A2,'Base GDI'!$A$2:$AL$1501,5,FALSE),"") | E2: =IFERROR(VLOOKUP($A2,'Base GDI'!$A$2:$AL$1501,14,FALSE),"") | F2: =IFERROR(VLOOKUP($A2,'Base GDI'!$A$2:$AL$1501,15,FALSE),"") | G2: =IFERROR(VLOOKUP($A2,'Base Tratada'!$A$2:$AD$577,9,FALSE),"—") | H2: =IF($C2="","",IFERROR(VLOOKUP($C2,'Panorama Municipal'!$A$2:$N$228,7,FALSE),"—")&" alunos · "&IFERROR(VLOOKUP($C2,'Panorama Municipal'!$A$2:$N$228,8,FALSE),"—")&" turmas (estadual nesta escola: "&IFERROR(VLOOKUP($A2,'Base Tratada'!$A$2:$AD$577,18,FALSE),0)&")") | I2: =IF($C2="","",IF(IFERROR(VLOOKUP($C2,'Panorama Municipal'!$A$2:$N$228,11,FALSE),"")="","—",IF(IFERROR(VLOOKUP($C2,'Panorama Municipal'!$A$2:$N$228,11,FALSE),"")>0,"FALTAM DISTRIBUIR "&IFERROR(VLOOKUP($C2,'Panorama Municipal'!$A$2:$N$228,11,FALSE),"")&" TURMA(S)",IF(IFERROR(VLOOKUP($C2,'Panorama Municipal'!$A$2:$N$228,11,FALSE),"")=0,"DEMANDA MUNICIPAL ATENDIDA","EXCEDE A DEMANDA EM "&ABS(IFERROR(VLOOKUP($C2,'Panorama Municipal'!$A$2:$N$228,11,FALSE),""))&" TURMA(S)")))) | K2: =IFERROR(IF(N(VLOOKUP($C2,'IDEB Municípios'!$A$2:$F$228,2,FALSE))=0,"— sem IDEB cadastrado",VLOOKUP($C2,'IDEB Municípios'!$A$2:$F$228,2,FALSE)),"— sem IDEB cadastrado") | L2: 3 | M2: 3 | N2: =IFERROR(VLOOKUP($A2,'Base Tratada'!$A$2:$AD$577,3,FALSE),"—") | Q2: 3 | R2: 3 | S2: =IFERROR(VLOOKUP($A2,'Base Tratada'!$A$2:$AD$577,10,FALSE),"—") | U2: =IFERROR(VLOOKUP($A2,'Base Tratada'!$A$2:$AD$577,11,FALSE),"—") | V2: =IFERROR(IF(COUNTIF('Fusão Turmas'!$J$2:$J$63,$A2)+COUNTIF('Fusão Turmas'!$N$2:$N$63,$A2)=0,"Sem fusão turma a turma",COUNTIF('Fusão Turmas'!$J$2:$J$63,$A2)&" turma(s) saem · "&COUNTIF('Fusão Turmas'!$N$2:$N$63,$A2)&" turma(s) recebem"),"—") | W2: =IFERROR(VLOOKUP($A2,'Base GDI'!$A$2:$AL$1501,6,FALSE),"") | X2: 9 | Y2: =IF($X2="","",IF($W2>$X2,($W2-$X2)&" SALA(S) OCIOSA(S)",IF($W2<$X2,"CONSTRUIR "&($X2-$W2)&" SALA(S)","QUANTIDADE ADEQUADA"))) | Z2: =IFERROR(VLOOKUP($A2,'Base Tratada'!$A$2:$AD$577,7,FALSE),"—") | AA2: =IFERROR(VLOOKUP($A2,'Base Tratada'!$A$2:$AD$577,16,FALSE),"—") | AD2: =IFERROR(VLOOKUP($A2,'Base Tratada'!$A$2:$AD$577,26,FALSE),"—") | AE2: =IFERROR(VLOOKUP($A2,'Base Tratada'!$A$2:$AD$577,21,FALSE),"—") | AG2: =IF($A2="","",$M2&" de 1ª | "&$Q2&" de 2ª | "&$R2&" de 3ª | Necessidade: "&$X2&" salas | "&$Y2) | AH2: =IFERROR(VLOOKUP($A2,'Base GDI'!$A$2:$AL$1501,18,FALSE),"—")
A3: 22012419 | B3: =IFERROR(VLOOKUP($A3,'Base GDI'!$A$2:$AL$1501,3,FALSE),"") | C3: BURITI DOS LOPES | D3: =IFERROR(VLOOKUP($A3,'Base GDI'!$A$2:$AL$1501,5,FALSE),"") | E3: =IFERROR(VLOOKUP($A3,'Base GDI'!$A$2:$AL$1501,14,FALSE),"") | F3: =IFERROR(VLOOKUP($A3,'Base GDI'!$A$2:$AL$1501,15,FALSE),"") | G3: =IFERROR(VLOOKUP($A3,'Base Tratada'!$A$2:$AD$577,9,FALSE),"—") | H3: =IF($C3="","",IFERROR(VLOOKUP($C3,'Panorama Municipal'!$A$2:$N$228,7,FALSE),"—")&" alunos · "&IFERROR(VLOOKUP($C3,'Panorama Municipal'!$A$2:$N$228,8,FALSE),"—")&" turmas (estadual nesta escola: "&IFERROR(VLOOKUP($A3,'Base Tratada'!$A$2:$AD$577,18,FALSE),0)&")") | I3: =IF($C3="","",IF(IFERROR(VLOOKUP($C3,'Panorama Municipal'!$A$2:$N$228,11,FALSE),"")="","—",IF(IFERROR(VLOOKUP($C3,'Panorama Municipal'!$A$2:$N$228,11,FALSE),"")>0,"FALTAM DISTRIBUIR "&IFERROR(VLOOKUP($C3,'Panorama Municipal'!$A$2:$N$228,11,FALSE),"")&" TURMA(S)",IF(IFERROR(VLOOKUP($C3,'Panorama Municipal'!$A$2:$N$228,11,FALSE),"")=0,"DEMANDA MUNICIPAL ATENDIDA","EXCEDE A DEMANDA EM "&ABS(IFERROR(VLOOKUP($C3,'Panorama Municipal'!$A$2:$N$228,11,FALSE),""))&" TURMA(S)")))) | K3: =IFERROR(IF(N(VLOOKUP($C3,'IDEB Municípios'!$A$2:$F$228,2,FALSE))=0,"— sem IDEB cadastrado",VLOOKUP($C3,'IDEB Municípios'!$A$2:$F$228,2,FALSE)),"— sem IDEB cadastrado") | L3: 2 | M3: 2 | N3: =IFERROR(VLOOKUP($A3,'Base Tratada'!$A$2:$AD$577,3,FALSE),"—") | Q3: 2 | R3: 2 | S3: =IFERROR(VLOOKUP($A3,'Base Tratada'!$A$2:$AD$577,10,FALSE),"—") | U3: =IFERROR(VLOOKUP($A3,'Base Tratada'!$A$2:$AD$577,11,FALSE),"—") | V3: =IFERROR(IF(COUNTIF('Fusão Turmas'!$J$2:$J$63,$A3)+COUNTIF('Fusão Turmas'!$N$2:$N$63,$A3)=0,"Sem fusão turma a turma",COUNTIF('Fusão Turmas'!$J$2:$J$63,$A3)&" turma(s) saem · "&COUNTIF('Fusão Turmas'!$N$2:$N$63,$A3)&" turma(s) recebem"),"—") | W3: =IFERROR(VLOOKUP($A3,'Base GDI'!$A$2:$AL$1501,6,FALSE),"") | X3: 6 | Y3: =IF($X3="","",IF($W3>$X3,($W3-$X3)&" SALA(S) OCIOSA(S)",IF($W3<$X3,"CONSTRUIR "&($X3-$W3)&" SALA(S)","QUANTIDADE ADEQUADA"))) | Z3: =IFERROR(VLOOKUP($A3,'Base Tratada'!$A$2:$AD$577,7,FALSE),"—") | AA3: =IFERROR(VLOOKUP($A3,'Base Tratada'!$A$2:$AD$577,16,FALSE),"—") | AD3: =IFERROR(VLOOKUP($A3,'Base Tratada'!$A$2:$AD$577,26,FALSE),"—") | AE3: =IFERROR(VLOOKUP($A3,'Base Tratada'!$A$2:$AD$577,21,FALSE),"—") | AG3: =IF($A3="","",$M3&" de 1ª | "&$Q3&" de 2ª | "&$R3&" de 3ª | Necessidade: "&$X3&" salas | "&$Y3) | AH3: =IFERROR(VLOOKUP($A3,'Base GDI'!$A$2:$AL$1501,18,FALSE),"—")
A4: 22012508 | B4: =IFERROR(VLOOKUP($A4,'Base GDI'!$A$2:$AL$1501,3,FALSE),"") | C4: BURITI DOS LOPES | D4: =IFERROR(VLOOKUP($A4,'Base GDI'!$A$2:$AL$1501,5,FALSE),"") | E4: =IFERROR(VLOOKUP($A4,'Base GDI'!$A$2:$AL$1501,14,FALSE),"") | F4: =IFERROR(VLOOKUP($A4,'Base GDI'!$A$2:$AL$1501,15,FALSE),"") | G4: =IFERROR(VLOOKUP($A4,'Base Tratada'!$A$2:$AD$577,9,FALSE),"—") | H4: =IF($C4="","",IFERROR(VLOOKUP($C4,'Panorama Municipal'!$A$2:$N$228,7,FALSE),"—")&" alunos · "&IFERROR(VLOOKUP($C4,'Panorama Municipal'!$A$2:$N$228,8,FALSE),"—")&" turmas (estadual nesta escola: "&IFERROR(VLOOKUP($A4,'Base Tratada'!$A$2:$AD$577,18,FALSE),0)&")") | I4: =IF($C4="","",IF(IFERROR(VLOOKUP($C4,'Panorama Municipal'!$A$2:$N$228,11,FALSE),"")="","—",IF(IFERROR(VLOOKUP($C4,'Panorama Municipal'!$A$2:$N$228,11,FALSE),"")>0,"FALTAM DISTRIBUIR "&IFERROR(VLOOKUP($C4,'Panorama Municipal'!$A$2:$N$228,11,FALSE),"")&" TURMA(S)",IF(IFERROR(VLOOKUP($C4,'Panorama Municipal'!$A$2:$N$228,11,FALSE),"")=0,"DEMANDA MUNICIPAL ATENDIDA","EXCEDE A DEMANDA EM "&ABS(IFERROR(VLOOKUP($C4,'Panorama Municipal'!$A$2:$N$228,11,FALSE),""))&" TURMA(S)")))) | K4: =IFERROR(IF(N(VLOOKUP($C4,'IDEB Municípios'!$A$2:$F$228,2,FALSE))=0,"— sem IDEB cadastrado",VLOOKUP($C4,'IDEB Municípios'!$A$2:$F$228,2,FALSE)),"— sem IDEB cadastrado") | L4: 0 | M4: 0 | N4: =IFERROR(VLOOKUP($A4,'Base Tratada'!$A$2:$AD$577,3,FALSE),"—") | Q4: 0 | R4: 0 | S4: =IFERROR(VLOOKUP($A4,'Base Tratada'!$A$2:$AD$577,10,FALSE),"—") | U4: =IFERROR(VLOOKUP($A4,'Base Tratada'!$A$2:$AD$577,11,FALSE),"—") | V4: =IFERROR(IF(COUNTIF('Fusão Turmas'!$J$2:$J$63,$A4)+COUNTIF('Fusão Turmas'!$N$2:$N$63,$A4)=0,"Sem fusão turma a turma",COUNTIF('Fusão Turmas'!$J$2:$J$63,$A4)&" turma(s) saem · "&COUNTIF('Fusão Turmas'!$N$2:$N$63,$A4)&" turma(s) recebem"),"—") | W4: =IFERROR(VLOOKUP($A4,'Base GDI'!$A$2:$AL$1501,6,FALSE),"") | X4: 0 | Y4: =IF($X4="","",IF($W4>$X4,($W4-$X4)&" SALA(S) OCIOSA(S)",IF($W4<$X4,"CONSTRUIR "&($X4-$W4)&" SALA(S)","QUANTIDADE ADEQUADA"))) | Z4: =IFERROR(VLOOKUP($A4,'Base Tratada'!$A$2:$AD$577,7,FALSE),"—") | AA4: =IFERROR(VLOOKUP($A4,'Base Tratada'!$A$2:$AD$577,16,FALSE),"—") | AD4: =IFERROR(VLOOKUP($A4,'Base Tratada'!$A$2:$AD$577,26,FALSE),"—") | AE4: =IFERROR(VLOOKUP($A4,'Base Tratada'!$A$2:$AD$577,21,FALSE),"—") | AG4: =IF($A4="","",$M4&" de 1ª | "&$Q4&" de 2ª | "&$R4&" de 3ª | Necessidade: "&$X4&" salas | "&$Y4) | AH4: =IFERROR(VLOOKUP($A4,'Base GDI'!$A$2:$AL$1501,18,FALSE),"—")
A5: 22137947 | B5: =IFERROR(VLOOKUP($A5,'Base GDI'!$A$2:$AL$1501,3,FALSE),"") | C5: BURITI DOS LOPES | D5: =IFERROR(VLOOKUP($A5,'Base GDI'!$A$2:$AL$1501,5,FALSE),"") | E5: =IFERROR(VLOOKUP($A5,'Base GDI'!$A$2:$AL$1501,14,FALSE),"") | F5: =IFERROR(VLOOKUP($A5,'Base GDI'!$A$2:$AL$1501,15,FALSE),"") | G5: =IFERROR(VLOOKUP($A5,'Base Tratada'!$A$2:$AD$577,9,FALSE),"—") | H5: =IF($C5="","",IFERROR(VLOOKUP($C5,'Panorama Municipal'!$A$2:$N$228,7,FALSE),"—")&" alunos · "&IFERROR(VLOOKUP($C5,'Panorama Municipal'!$A$2:$N$228,8,FALSE),"—")&" turmas (estadual nesta escola: "&IFERROR(VLOOKUP($A5,'Base Tratada'!$A$2:$AD$577,18,FALSE),0)&")") | I5: =IF($C5="","",IF(IFERROR(VLOOKUP($C5,'Panorama Municipal'!$A$2:$N$228,11,FALSE),"")="","—",IF(IFERROR(VLOOKUP($C5,'Panorama Municipal'!$A$2:$N$228,11,FALSE),"")>0,"FALTAM DISTRIBUIR "&IFERROR(VLOOKUP($C5,'Panorama Municipal'!$A$2:$N$228,11,FALSE),"")&" TURMA(S)",IF(IFERROR(VLOOKUP($C5,'Panorama Municipal'!$A$2:$N$228,11,FALSE),"")=0,"DEMANDA MUNICIPAL ATENDIDA","EXCEDE A DEMANDA EM "&ABS(IFERROR(VLOOKUP($C5,'Panorama Municipal'!$A$2:$N$228,11,FALSE),""))&" TURMA(S)")))) | K5: =IFERROR(IF(N(VLOOKUP($C5,'IDEB Municípios'!$A$2:$F$228,2,FALSE))=0,"— sem IDEB cadastrado",VLOOKUP($C5,'IDEB Municípios'!$A$2:$F$228,2,FALSE)),"— sem IDEB cadastrado") | L5: 5 | M5: 5 | N5: =IFERROR(VLOOKUP($A5,'Base Tratada'!$A$2:$AD$577,3,FALSE),"—") | Q5: 5 | R5: 4 | S5: =IFERROR(VLOOKUP($A5,'Base Tratada'!$A$2:$AD$577,10,FALSE),"—") | U5: =IFERROR(VLOOKUP($A5,'Base Tratada'!$A$2:$AD$577,11,FALSE),"—") | V5: =IFERROR(IF(COUNTIF('Fusão Turmas'!$J$2:$J$63,$A5)+COUNTIF('Fusão Turmas'!$N$2:$N$63,$A5)=0,"Sem fusão turma a turma",COUNTIF('Fusão Turmas'!$J$2:$J$63,$A5)&" turma(s) saem · "&COUNTIF('Fusão Turmas'!$N$2:$N$63,$A5)&" turma(s) recebem"),"—") | W5: =IFERROR(VLOOKUP($A5,'Base GDI'!$A$2:$AL$1501,6,FALSE),"") | X5: 14 | Y5: =IF($X5="","",IF($W5>$X5,($W5-$X5)&" SALA(S) OCIOSA(S)",IF($W5<$X5,"CONSTRUIR "&($X5-$W5)&" SALA(S)","QUANTIDADE ADEQUADA"))) | Z5: =IFERROR(VLOOKUP($A5,'Base Tratada'!$A$2:$AD$577,7,FALSE),"—") | AA5: =IFERROR(VLOOKUP($A5,'Base Tratada'!$A$2:$AD$577,16,FALSE),"—") | AD5: =IFERROR(VLOOKUP($A5,'Base Tratada'!$A$2:$AD$577,26,FALSE),"—") | AE5: =IFERROR(VLOOKUP($A5,'Base Tratada'!$A$2:$AD$577,21,FALSE),"—") | AG5: =IF($A5="","",$M5&" de 1ª | "&$Q5&" de 2ª | "&$R5&" de 3ª | Necessidade: "&$X5&" salas | "&$Y5) | AH5: =IFERROR(VLOOKUP($A5,'Base GDI'!$A$2:$AL$1501,18,FALSE),"—")
A6: 22162607 | B6: =IFERROR(VLOOKUP($A6,'Base GDI'!$A$2:$AL$1501,3,FALSE),"") | C6: BURITI DOS LOPES | D6: =IFERROR(VLOOKUP($A6,'Base GDI'!$A$2:$AL$1501,5,FALSE),"") | E6: =IFERROR(VLOOKUP($A6,'Base GDI'!$A$2:$AL$1501,14,FALSE),"") | F6: =IFERROR(VLOOKUP($A6,'Base GDI'!$A$2:$AL$1501,15,FALSE),"") | G6: =IFERROR(VLOOKUP($A6,'Base Tratada'!$A$2:$AD$577,9,FALSE),"—") | H6: =IF($C6="","",IFERROR(VLOOKUP($C6,'Panorama Municipal'!$A$2:$N$228,7,FALSE),"—")&" alunos · "&IFERROR(VLOOKUP($C6,'Panorama Municipal'!$A$2:$N$228,8,FALSE),"—")&" turmas (estadual nesta escola: "&IFERROR(VLOOKUP($A6,'Base Tratada'!$A$2:$AD$577,18,FALSE),0)&")") | I6: =IF($C6="","",IF(IFERROR(VLOOKUP($C6,'Panorama Municipal'!$A$2:$N$228,11,FALSE),"")="","—",IF(IFERROR(VLOOKUP($C6,'Panorama Municipal'!$A$2:$N$228,11,FALSE),"")>0,"FALTAM DISTRIBUIR "&IFERROR(VLOOKUP($C6,'Panorama Municipal'!$A$2:$N$228,11,FALSE),"")&" TURMA(S)",IF(IFERROR(VLOOKUP($C6,'Panorama Municipal'!$A$2:$N$228,11,FALSE),"")=0,"DEMANDA MUNICIPAL ATENDIDA","EXCEDE A DEMANDA EM "&ABS(IFERROR(VLOOKUP($C6,'Panorama Municipal'!$A$2:$N$228,11,FALSE),""))&" TURMA(S)")))) | K6: =IFERROR(IF(N(VLOOKUP($C6,'IDEB Municípios'!$A$2:$F$228,2,FALSE))=0,"— sem IDEB cadastrado",VLOOKUP($C6,'IDEB Municípios'!$A$2:$F$228,2,FALSE)),"— sem IDEB cadastrado") | L6: 2 | M6: 2 | N6: =IFERROR(VLOOKUP($A6,'Base Tratada'!$A$2:$AD$577,3,FALSE),"—") | Q6: 2 | R6: 2 | S6: =IFERROR(VLOOKUP($A6,'Base Tratada'!$A$2:$AD$577,10,FALSE),"—") | U6: =IFERROR(VLOOKUP($A6,'Base Tratada'!$A$2:$AD$577,11,FALSE),"—") | V6: =IFERROR(IF(COUNTIF('Fusão Turmas'!$J$2:$J$63,$A6)+COUNTIF('Fusão Turmas'!$N$2:$N$63,$A6)=0,"Sem fusão turma a turma",COUNTIF('Fusão Turmas'!$J$2:$J$63,$A6)&" turma(s) saem · "&COUNTIF('Fusão Turmas'!$N$2:$N$63,$A6)&" turma(s) recebem"),"—") | W6: =IFERROR(VLOOKUP($A6,'Base GDI'!$A$2:$AL$1501,6,FALSE),"") | X6: 7 | Y6: =IF($X6="","",IF($W6>$X6,($W6-$X6)&" SALA(S) OCIOSA(S)",IF($W6<$X6,"CONSTRUIR "&($X6-$W6)&" SALA(S)","QUANTIDADE ADEQUADA"))) | Z6: =IFERROR(VLOOKUP($A6,'Base Tratada'!$A$2:$AD$577,7,FALSE),"—") | AA6: =IFERROR(VLOOKUP($A6,'Base Tratada'!$A$2:$AD$577,16,FALSE),"—") | AD6: =IFERROR(VLOOKUP($A6,'Base Tratada'!$A$2:$AD$577,26,FALSE),"—") | AE6: =IFERROR(VLOOKUP($A6,'Base Tratada'!$A$2:$AD$577,21,FALSE),"—") | AG6: =IF($A6="","",$M6&" de 1ª | "&$Q6&" de 2ª | "&$R6&" de 3ª | Necessidade: "&$X6&" salas | "&$Y6) | AH6: =IFERROR(VLOOKUP($A6,'Base GDI'!$A$2:$AL$1501,18,FALSE),"—")
A7: 22014306 | B7: =IFERROR(VLOOKUP($A7,'Base GDI'!$A$2:$AL$1501,3,FALSE),"") | C7: CAJUEIRO DA PRAIA | D7: =IFERROR(VLOOKUP($A7,'Base GDI'!$A$2:$AL$1501,5,FALSE),"") | E7: =IFERROR(VLOOKUP($A7,'Base GDI'!$A$2:$AL$1501,14,FALSE),"") | F7: =IFERROR(VLOOKUP($A7,'Base GDI'!$A$2:$AL$1501,15,FALSE),"") | G7: =IFERROR(VLOOKUP($A7,'Base Tratada'!$A$2:$AD$577,9,FALSE),"—") | H7: =IF($C7="","",IFERROR(VLOOKUP($C7,'Panorama Municipal'!$A$2:$N$228,7,FALSE),"—")&" alunos · "&IFERROR(VLOOKUP($C7,'Panorama Municipal'!$A$2:$N$228,8,FALSE),"—")&" turmas (estadual nesta escola: "&IFERROR(VLOOKUP($A7,'Base Tratada'!$A$2:$AD$577,18,FALSE),0)&")") | I7: =IF($C7="","",IF(IFERROR(VLOOKUP($C7,'Panorama Municipal'!$A$2:$N$228,11,FALSE),"")="","—",IF(IFERROR(VLOOKUP($C7,'Panorama Municipal'!$A$2:$N$228,11,FALSE),"")>0,"FALTAM DISTRIBUIR "&IFERROR(VLOOKUP($C7,'Panorama Municipal'!$A$2:$N$228,11,FALSE),"")&" TURMA(S)",IF(IFERROR(VLOOKUP($C7,'Panorama Municipal'!$A$2:$N$228,11,FALSE),"")=0,"DEMANDA MUNICIPAL ATENDIDA","EXCEDE A DEMANDA EM "&ABS(IFERROR(VLOOKUP($C7,'Panorama Municipal'!$A$2:$N$228,11,FALSE),""))&" TURMA(S)")))) | K7: =IFERROR(IF(N(VLOOKUP($C7,'IDEB Municípios'!$A$2:$F$228,2,FALSE))=0,"— sem IDEB cadastrado",VLOOKUP($C7,'IDEB Municípios'!$A$2:$F$228,2,FALSE)),"— sem IDEB cadastrado") | L7: 3 | M7: 3 | N7: =IFERROR(VLOOKUP($A7,'Base Tratada'!$A$2:$AD$577,3,FALSE),"—") | Q7: 3 | R7: 3 | S7: =IFERROR(VLOOKUP($A7,'Base Tratada'!$A$2:$AD$577,10,FALSE),"—") | U7: =IFERROR(VLOOKUP($A7,'Base Tratada'!$A$2:$AD$577,11,FALSE),"—") | V7: =IFERROR(IF(COUNTIF('Fusão Turmas'!$J$2:$J$63,$A7)+COUNTIF('Fusão Turmas'!$N$2:$N$63,$A7)=0,"Sem fusão turma a turma",COUNTIF('Fusão Turmas'!$J$2:$J$63,$A7)&" turma(s) saem · "&COUNTIF('Fusão Turmas'!$N$2:$N$63,$A7)&" turma(s) recebem"),"—") | W7: =IFERROR(VLOOKUP($A7,'Base GDI'!$A$2:$AL$1501,6,FALSE),"") | X7: 9 | Y7: =IF($X7="","",IF($W7>$X7,($W7-$X7)&" SALA(S) OCIOSA(S)",IF($W7<$X7,"CONSTRUIR "&($X7-$W7)&" SALA(S)","QUANTIDADE ADEQUADA"))) | Z7: =IFERROR(VLOOKUP($A7,'Base Tratada'!$A$2:$AD$577,7,FALSE),"—") | AA7: =IFERROR(VLOOKUP($A7,'Base Tratada'!$A$2:$AD$577,16,FALSE),"—") | AD7: =IFERROR(VLOOKUP($A7,'Base Tratada'!$A$2:$AD$577,26,FALSE),"—") | AE7: =IFERROR(VLOOKUP($A7,'Base Tratada'!$A$2:$AD$577,21,FALSE),"—") | AG7: =IF($A7="","",$M7&" de 1ª | "&$Q7&" de 2ª | "&$R7&" de 3ª | Necessidade: "&$X7&" salas | "&$Y7) | AH7: =IFERROR(VLOOKUP($A7,'Base GDI'!$A$2:$AL$1501,18,FALSE),"—")
A8: 22135863 | B8: =IFERROR(VLOOKUP($A8,'Base GDI'!$A$2:$AL$1501,3,FALSE),"") | C8: CARAUBAS DO PIAUI | D8: =IFERROR(VLOOKUP($A8,'Base GDI'!$A$2:$AL$1501,5,FALSE),"") | E8: =IFERROR(VLOOKUP($A8,'Base GDI'!$A$2:$AL$1501,14,FALSE),"") | F8: =IFERROR(VLOOKUP($A8,'Base GDI'!$A$2:$AL$1501,15,FALSE),"") | G8: =IFERROR(VLOOKUP($A8,'Base Tratada'!$A$2:$AD$577,9,FALSE),"—") | H8: =IF($C8="","",IFERROR(VLOOKUP($C8,'Panorama Municipal'!$A$2:$N$228,7,FALSE),"—")&" alunos · "&IFERROR(VLOOKUP($C8,'Panorama Municipal'!$A$2:$N$228,8,FALSE),"—")&" turmas (estadual nesta escola: "&IFERROR(VLOOKUP($A8,'Base Tratada'!$A$2:$AD$577,18,FALSE),0)&")") | I8: =IF($C8="","",IF(IFERROR(VLOOKUP($C8,'Panorama Municipal'!$A$2:$N$228,11,FALSE),"")="","—",IF(IFERROR(VLOOKUP($C8,'Panorama Municipal'!$A$2:$N$228,11,FALSE),"")>0,"FALTAM DISTRIBUIR "&IFERROR(VLOOKUP($C8,'Panorama Municipal'!$A$2:$N$228,11,FALSE),"")&" TURMA(S)",IF(IFERROR(VLOOKUP($C8,'Panorama Municipal'!$A$2:$N$228,11,FALSE),"")=0,"DEMANDA MUNICIPAL ATENDIDA","EXCEDE A DEMANDA EM "&ABS(IFERROR(VLOOKUP($C8,'Panorama Municipal'!$A$2:$N$228,11,FALSE),""))&" TURMA(S)")))) | K8: =IFERROR(IF(N(VLOOKUP($C8,'IDEB Municípios'!$A$2:$F$228,2,FALSE))=0,"— sem IDEB cadastrado",VLOOKUP($C8,'IDEB Municípios'!$A$2:$F$228,2,FALSE)),"— sem IDEB cadastrado") | L8: 2 | M8: 2 | N8: =IFERROR(VLOOKUP($A8,'Base Tratada'!$A$2:$AD$577,3,FALSE),"—") | Q8: 2 | R8: 2 | S8: =IFERROR(VLOOKUP($A8,'Base Tratada'!$A$2:$AD$577,10,FALSE),"—") | U8: =IFERROR(VLOOKUP($A8,'Base Tratada'!$A$2:$AD$577,11,FALSE),"—") | V8: =IFERROR(IF(COUNTIF('Fusão Turmas'!$J$2:$J$63,$A8)+COUNTIF('Fusão Turmas'!$N$2:$N$63,$A8)=0,"Sem fusão turma a turma",COUNTIF('Fusão Turmas'!$J$2:$J$63,$A8)&" turma(s) saem · "&COUNTIF('Fusão Turmas'!$N$2:$N$63,$A8)&" turma(s) recebem"),"—") | W8: =IFERROR(VLOOKUP($A8,'Base GDI'!$A$2:$AL$1501,6,FALSE),"") | X8: 6 | Y8: =IF($X8="","",IF($W8>$X8,($W8-$X8)&" SALA(S) OCIOSA(S)",IF($W8<$X8,"CONSTRUIR "&($X8-$W8)&" SALA(S)","QUANTIDADE ADEQUADA"))) | Z8: =IFERROR(VLOOKUP($A8,'Base Tratada'!$A$2:$AD$577,7,FALSE),"—") | AA8: =IFERROR(VLOOKUP($A8,'Base Tratada'!$A$2:$AD$577,16,FALSE),"—") | AD8: =IFERROR(VLOOKUP($A8,'Base Tratada'!$A$2:$AD$577,26,FALSE),"—") | AE8: =IFERROR(VLOOKUP($A8,'Base Tratada'!$A$2:$AD$577,21,FALSE),"—") | AG8: =IF($A8="","",$M8&" de 1ª | "&$Q8&" de 2ª | "&$R8&" de 3ª | Necessidade: "&$X8&" salas | "&$Y8) | AH8: =IFERROR(VLOOKUP($A8,'Base GDI'!$A$2:$AL$1501,18,FALSE),"—")
A9: 22135782 | B9: =IFERROR(VLOOKUP($A9,'Base GDI'!$A$2:$AL$1501,3,FALSE),"") | C9: CAXINGO | D9: =IFERROR(VLOOKUP($A9,'Base GDI'!$A$2:$AL$1501,5,FALSE),"") | E9: =IFERROR(VLOOKUP($A9,'Base GDI'!$A$2:$AL$1501,14,FALSE),"") | F9: =IFERROR(VLOOKUP($A9,'Base GDI'!$A$2:$AL$1501,15,FALSE),"") | G9: =IFERROR(VLOOKUP($A9,'Base Tratada'!$A$2:$AD$577,9,FALSE),"—") | H9: =IF($C9="","",IFERROR(VLOOKUP($C9,'Panorama Municipal'!$A$2:$N$228,7,FALSE),"—")&" alunos · "&IFERROR(VLOOKUP($C9,'Panorama Municipal'!$A$2:$N$228,8,FALSE),"—")&" turmas (estadual nesta escola: "&IFERROR(VLOOKUP($A9,'Base Tratada'!$A$2:$AD$577,18,FALSE),0)&")") | I9: =IF($C9="","",IF(IFERROR(VLOOKUP($C9,'Panorama Municipal'!$A$2:$N$228,11,FALSE),"")="","—",IF(IFERROR(VLOOKUP($C9,'Panorama Municipal'!$A$2:$N$228,11,FALSE),"")>0,"FALTAM DISTRIBUIR "&IFERROR(VLOOKUP($C9,'Panorama Municipal'!$A$2:$N$228,11,FALSE),"")&" TURMA(S)",IF(IFERROR(VLOOKUP($C9,'Panorama Municipal'!$A$2:$N$228,11,FALSE),"")=0,"DEMANDA MUNICIPAL ATENDIDA","EXCEDE A DEMANDA EM "&ABS(IFERROR(VLOOKUP($C9,'Panorama Municipal'!$A$2:$N$228,11,FALSE),""))&" TURMA(S)")))) | K9: =IFERROR(IF(N(VLOOKUP($C9,'IDEB Municípios'!$A$2:$F$228,2,FALSE))=0,"— sem IDEB cadastrado",VLOOKUP($C9,'IDEB Municípios'!$A$2:$F$228,2,FALSE)),"— sem IDEB cadastrado") | L9: 2 | M9: 2 | N9: =IFERROR(VLOOKUP($A9,'Base Tratada'!$A$2:$AD$577,3,FALSE),"—") | Q9: 2 | R9: 2 | S9: =IFERROR(VLOOKUP($A9,'Base Tratada'!$A$2:$AD$577,10,FALSE),"—") | U9: =IFERROR(VLOOKUP($A9,'Base Tratada'!$A$2:$AD$577,11,FALSE),"—") | V9: =IFERROR(IF(COUNTIF('Fusão Turmas'!$J$2:$J$63,$A9)+COUNTIF('Fusão Turmas'!$N$2:$N$63,$A9)=0,"Sem fusão turma a turma",COUNTIF('Fusão Turmas'!$J$2:$J$63,$A9)&" turma(s) saem · "&COUNTIF('Fusão Turmas'!$N$2:$N$63,$A9)&" turma(s) recebem"),"—") | W9: =IFERROR(VLOOKUP($A9,'Base GDI'!$A$2:$AL$1501,6,FALSE),"") | X9: 6 | Y9: =IF($X9="","",IF($W9>$X9,($W9-$X9)&" SALA(S) OCIOSA(S)",IF($W9<$X9,"CONSTRUIR "&($X9-$W9)&" SALA(S)","QUANTIDADE ADEQUADA"))) | Z9: =IFERROR(VLOOKUP($A9,'Base Tratada'!$A$2:$AD$577,7,FALSE),"—") | AA9: =IFERROR(VLOOKUP($A9,'Base Tratada'!$A$2:$AD$577,16,FALSE),"—") | AD9: =IFERROR(VLOOKUP($A9,'Base Tratada'!$A$2:$AD$577,26,FALSE),"—") | AE9: =IFERROR(VLOOKUP($A9,'Base Tratada'!$A$2:$AD$577,21,FALSE),"—") | AG9: =IF($A9="","",$M9&" de 1ª | "&$Q9&" de 2ª | "&$R9&" de 3ª | Necessidade: "&$X9&" salas | "&$Y9) | AH9: =IFERROR(VLOOKUP($A9,'Base GDI'!$A$2:$AL$1501,18,FALSE),"—")
A10: 22013555 | B10: =IFERROR(VLOOKUP($A10,'Base GDI'!$A$2:$AL$1501,3,FALSE),"") | C10: COCAL | D10: =IFERROR(VLOOKUP($A10,'Base GDI'!$A$2:$AL$1501,5,FALSE),"") | E10: =IFERROR(VLOOKUP($A10,'Base GDI'!$A$2:$AL$1501,14,FALSE),"") | F10: =IFERROR(VLOOKUP($A10,'Base GDI'!$A$2:$AL$1501,15,FALSE),"") | G10: =IFERROR(VLOOKUP($A10,'Base Tratada'!$A$2:$AD$577,9,FALSE),"—") | H10: =IF($C10="","",IFERROR(VLOOKUP($C10,'Panorama Municipal'!$A$2:$N$228,7,FALSE),"—")&" alunos · "&IFERROR(VLOOKUP($C10,'Panorama Municipal'!$A$2:$N$228,8,FALSE),"—")&" turmas (estadual nesta escola: "&IFERROR(VLOOKUP($A10,'Base Tratada'!$A$2:$AD$577,18,FALSE),0)&")") | I10: =IF($C10="","",IF(IFERROR(VLOOKUP($C10,'Panorama Municipal'!$A$2:$N$228,11,FALSE),"")="","—",IF(IFERROR(VLOOKUP($C10,'Panorama Municipal'!$A$2:$N$228,11,FALSE),"")>0,"FALTAM DISTRIBUIR "&IFERROR(VLOOKUP($C10,'Panorama Municipal'!$A$2:$N$228,11,FALSE),"")&" TURMA(S)",IF(IFERROR(VLOOKUP($C10,'Panorama Municipal'!$A$2:$N$228,11,FALSE),"")=0,"DEMANDA MUNICIPAL ATENDIDA","EXCEDE A DEMANDA EM "&ABS(IFERROR(VLOOKUP($C10,'Panorama Municipal'!$A$2:$N$228,11,FALSE),""))&" TURMA(S)")))) | K10: =IFERROR(IF(N(VLOOKUP($C10,'IDEB Municípios'!$A$2:$F$228,2,FALSE))=0,"— sem IDEB cadastrado",VLOOKUP($C10,'IDEB Municípios'!$A$2:$F$228,2,FALSE)),"— sem IDEB cadastrado") | L10: 1 | M10: 1 | N10: =IFERROR(VLOOKUP($A10,'Base Tratada'!$A$2:$AD$577,3,FALSE),"—") | Q10: 1 | R10: 3 | S10: =IFERROR(VLOOKUP($A10,'Base Tratada'!$A$2:$AD$577,10,FALSE),"—") | U10: =IFERROR(VLOOKUP($A10,'Base Tratada'!$A$2:$AD$577,11,FALSE),"—") | V10: =IFERROR(IF(COUNTIF('Fusão Turmas'!$J$2:$J$63,$A10)+COUNTIF('Fusão Turmas'!$N$2:$N$63,$A10)=0,"Sem fusão turma a turma",COUNTIF('Fusão Turmas'!$J$2:$J$63,$A10)&" turma(s) saem · "&COUNTIF('Fusão Turmas'!$N$2:$N$63,$A10)&" turma(s) recebem"),"—") | W10: =IFERROR(VLOOKUP($A10,'Base GDI'!$A$2:$AL$1501,6,FALSE),"") | X10: 5 | Y10: =IF($X10="","",IF($W10>$X10,($W10-$X10)&" SALA(S) OCIOSA(S)",IF($W10<$X10,"CONSTRUIR "&($X10-$W10)&" SALA(S)","QUANTIDADE ADEQUADA"))) | Z10: =IFERROR(VLOOKUP($A10,'Base Tratada'!$A$2:$AD$577,7,FALSE),"—") | AA10: =IFERROR(VLOOKUP($A10,'Base Tratada'!$A$2:$AD$577,16,FALSE),"—") | AD10: =IFERROR(VLOOKUP($A10,'Base Tratada'!$A$2:$AD$577,26,FALSE),"—") | AE10: =IFERROR(VLOOKUP($A10,'Base Tratada'!$A$2:$AD$577,21,FALSE),"—") | AG10: =IF($A10="","",$M10&" de 1ª | "&$Q10&" de 2ª | "&$R10&" de 3ª | Necessidade: "&$X10&" salas | "&$Y10) | AH10: =IFERROR(VLOOKUP($A10,'Base GDI'!$A$2:$AL$1501,18,FALSE),"—")
A11: 22013601 | B11: =IFERROR(VLOOKUP($A11,'Base GDI'!$A$2:$AL$1501,3,FALSE),"") | C11: COCAL | D11: =IFERROR(VLOOKUP($A11,'Base GDI'!$A$2:$AL$1501,5,FALSE),"") | E11: =IFERROR(VLOOKUP($A11,'Base GDI'!$A$2:$AL$1501,14,FALSE),"") | F11: =IFERROR(VLOOKUP($A11,'Base GDI'!$A$2:$AL$1501,15,FALSE),"") | G11: =IFERROR(VLOOKUP($A11,'Base Tratada'!$A$2:$AD$577,9,FALSE),"—") | H11: =IF($C11="","",IFERROR(VLOOKUP($C11,'Panorama Municipal'!$A$2:$N$228,7,FALSE),"—")&" alunos · "&IFERROR(VLOOKUP($C11,'Panorama Municipal'!$A$2:$N$228,8,FALSE),"—")&" turmas (estadual nesta escola: "&IFERROR(VLOOKUP($A11,'Base Tratada'!$A$2:$AD$577,18,FALSE),0)&")") | I11: =IF($C11="","",IF(IFERROR(VLOOKUP($C11,'Panorama Municipal'!$A$2:$N$228,11,FALSE),"")="","—",IF(IFERROR(VLOOKUP($C11,'Panorama Municipal'!$A$2:$N$228,11,FALSE),"")>0,"FALTAM DISTRIBUIR "&IFERROR(VLOOKUP($C11,'Panorama Municipal'!$A$2:$N$228,11,FALSE),"")&" TURMA(S)",IF(IFERROR(VLOOKUP($C11,'Panorama Municipal'!$A$2:$N$228,11,FALSE),"")=0,"DEMANDA MUNICIPAL ATENDIDA","EXCEDE A DEMANDA EM "&ABS(IFERROR(VLOOKUP($C11,'Panorama Municipal'!$A$2:$N$228,11,FALSE),""))&" TURMA(S)")))) | K11: =IFERROR(IF(N(VLOOKUP($C11,'IDEB Municípios'!$A$2:$F$228,2,FALSE))=0,"— sem IDEB cadastrado",VLOOKUP($C11,'IDEB Municípios'!$A$2:$F$228,2,FALSE)),"— sem IDEB cadastrado") | L11: 0 | M11: 0 | N11: =IFERROR(VLOOKUP($A11,'Base Tratada'!$A$2:$AD$577,3,FALSE),"—") | Q11: 0 | R11: 0 | S11: =IFERROR(VLOOKUP($A11,'Base Tratada'!$A$2:$AD$577,10,FALSE),"—") | U11: =IFERROR(VLOOKUP($A11,'Base Tratada'!$A$2:$AD$577,11,FALSE),"—") | V11: =IFERROR(IF(COUNTIF('Fusão Turmas'!$J$2:$J$63,$A11)+COUNTIF('Fusão Turmas'!$N$2:$N$63,$A11)=0,"Sem fusão turma a turma",COUNTIF('Fusão Turmas'!$J$2:$J$63,$A11)&" turma(s) saem · "&COUNTIF('Fusão Turmas'!$N$2:$N$63,$A11)&" turma(s) recebem"),"—") | W11: =IFERROR(VLOOKUP($A11,'Base GDI'!$A$2:$AL$1501,6,FALSE),"") | X11: 1 | Y11: =IF($X11="","",IF($W11>$X11,($W11-$X11)&" SALA(S) OCIOSA(S)",IF($W11<$X11,"CONSTRUIR "&($X11-$W11)&" SALA(S)","QUANTIDADE ADEQUADA"))) | Z11: =IFERROR(VLOOKUP($A11,'Base Tratada'!$A$2:$AD$577,7,FALSE),"—") | AA11: =IFERROR(VLOOKUP($A11,'Base Tratada'!$A$2:$AD$577,16,FALSE),"—") | AD11: =IFERROR(VLOOKUP($A11,'Base Tratada'!$A$2:$AD$577,26,FALSE),"—") | AE11: =IFERROR(VLOOKUP($A11,'Base Tratada'!$A$2:$AD$577,21,FALSE),"—") | AG11: =IF($A11="","",$M11&" de 1ª | "&$Q11&" de 2ª | "&$R11&" de 3ª | Necessidade: "&$X11&" salas | "&$Y11) | AH11: =IFERROR(VLOOKUP($A11,'Base GDI'!$A$2:$AL$1501,18,FALSE),"—")
A12: 22136037 | B12: =IFERROR(VLOOKUP($A12,'Base GDI'!$A$2:$AL$1501,3,FALSE),"") | C12: COCAL | D12: =IFERROR(VLOOKUP($A12,'Base GDI'!$A$2:$AL$1501,5,FALSE),"") | E12: =IFERROR(VLOOKUP($A12,'Base GDI'!$A$2:$AL$1501,14,FALSE),"") | F12: =IFERROR(VLOOKUP($A12,'Base GDI'!$A$2:$AL$1501,15,FALSE),"") | G12: =IFERROR(VLOOKUP($A12,'Base Tratada'!$A$2:$AD$577,9,FALSE),"—") | H12: =IF($C12="","",IFERROR(VLOOKUP($C12,'Panorama Municipal'!$A$2:$N$228,7,FALSE),"—")&" alunos · "&IFERROR(VLOOKUP($C12,'Panorama Municipal'!$A$2:$N$228,8,FALSE),"—")&" turmas (estadual nesta escola: "&IFERROR(VLOOKUP($A12,'Base Tratada'!$A$2:$AD$577,18,FALSE),0)&")") | I12: =IF($C12="","",IF(IFERROR(VLOOKUP($C12,'Panorama Municipal'!$A$2:$N$228,11,FALSE),"")="","—",IF(IFERROR(VLOOKUP($C12,'Panorama Municipal'!$A$2:$N$228,11,FALSE),"")>0,"FALTAM DISTRIBUIR "&IFERROR(VLOOKUP($C12,'Panorama Municipal'!$A$2:$N$228,11,FALSE),"")&" TURMA(S)",IF(IFERROR(VLOOKUP($C12,'Panorama Municipal'!$A$2:$N$228,11,FALSE),"")=0,"DEMANDA MUNICIPAL ATENDIDA","EXCEDE A DEMANDA EM "&ABS(IFERROR(VLOOKUP($C12,'Panorama Municipal'!$A$2:$N$228,11,FALSE),""))&" TURMA(S)")))) | K12: =IFERROR(IF(N(VLOOKUP($C12,'IDEB Municípios'!$A$2:$F$228,2,FALSE))=0,"— sem IDEB cadastrado",VLOOKUP($C12,'IDEB Municípios'!$A$2:$F$228,2,FALSE)),"— sem IDEB cadastrado") | L12: 4 | M12: 4 | N12: =IFERROR(VLOOKUP($A12,'Base Tratada'!$A$2:$AD$577,3,FALSE),"—") | Q12: 4 | R12: 3 | S12: =IFERROR(VLOOKUP($A12,'Base Tratada'!$A$2:$AD$577,10,FALSE),"—") | U12: =IFERROR(VLOOKUP($A12,'Base Tratada'!$A$2:$AD$577,11,FALSE),"—") | V12: =IFERROR(IF(COUNTIF('Fusão Turmas'!$J$2:$J$63,$A12)+COUNTIF('Fusão Turmas'!$N$2:$N$63,$A12)=0,"Sem fusão turma a turma",COUNTIF('Fusão Turmas'!$J$2:$J$63,$A12)&" turma(s) saem · "&COUNTIF('Fusão Turmas'!$N$2:$N$63,$A12)&" turma(s) recebem"),"—") | W12: =IFERROR(VLOOKUP($A12,'Base GDI'!$A$2:$AL$1501,6,FALSE),"") | X12: 11 | Y12: =IF($X12="","",IF($W12>$X12,($W12-$X12)&" SALA(S) OCIOSA(S)",IF($W12<$X12,"CONSTRUIR "&($X12-$W12)&" SALA(S)","QUANTIDADE ADEQUADA"))) | Z12: =IFERROR(VLOOKUP($A12,'Base Tratada'!$A$2:$AD$577,7,FALSE),"—") | AA12: =IFERROR(VLOOKUP($A12,'Base Tratada'!$A$2:$AD$577,16,FALSE),"—") | AD12: =IFERROR(VLOOKUP($A12,'Base Tratada'!$A$2:$AD$577,26,FALSE),"—") | AE12: =IFERROR(VLOOKUP($A12,'Base Tratada'!$A$2:$AD$577,21,FALSE),"—") | AG12: =IF($A12="","",$M12&" de 1ª | "&$Q12&" de 2ª | "&$R12&" de 3ª | Necessidade: "&$X12&" salas | "&$Y12) | AH12: =IFERROR(VLOOKUP($A12,'Base GDI'!$A$2:$AL$1501,18,FALSE),"—")
A13: 22140115 | B13: =IFERROR(VLOOKUP($A13,'Base GDI'!$A$2:$AL$1501,3,FALSE),"") | C13: COCAL | D13: =IFERROR(VLOOKUP($A13,'Base GDI'!$A$2:$AL$1501,5,FALSE),"") | E13: =IFERROR(VLOOKUP($A13,'Base GDI'!$A$2:$AL$1501,14,FALSE),"") | F13: =IFERROR(VLOOKUP($A13,'Base GDI'!$A$2:$AL$1501,15,FALSE),"") | G13: =IFERROR(VLOOKUP($A13,'Base Tratada'!$A$2:$AD$577,9,FALSE),"—") | H13: =IF($C13="","",IFERROR(VLOOKUP($C13,'Panorama Municipal'!$A$2:$N$228,7,FALSE),"—")&" alunos · "&IFERROR(VLOOKUP($C13,'Panorama Municipal'!$A$2:$N$228,8,FALSE),"—")&" turmas (estadual nesta escola: "&IFERROR(VLOOKUP($A13,'Base Tratada'!$A$2:$AD$577,18,FALSE),0)&")") | I13: =IF($C13="","",IF(IFERROR(VLOOKUP($C13,'Panorama Municipal'!$A$2:$N$228,11,FALSE),"")="","—",IF(IFERROR(VLOOKUP($C13,'Panorama Municipal'!$A$2:$N$228,11,FALSE),"")>0,"FALTAM DISTRIBUIR "&IFERROR(VLOOKUP($C13,'Panorama Municipal'!$A$2:$N$228,11,FALSE),"")&" TURMA(S)",IF(IFERROR(VLOOKUP($C13,'Panorama Municipal'!$A$2:$N$228,11,FALSE),"")=0,"DEMANDA MUNICIPAL ATENDIDA","EXCEDE A DEMANDA EM "&ABS(IFERROR(VLOOKUP($C13,'Panorama Municipal'!$A$2:$N$228,11,FALSE),""))&" TURMA(S)")))) | K13: =IFERROR(IF(N(VLOOKUP($C13,'IDEB Municípios'!$A$2:$F$228,2,FALSE))=0,"— sem IDEB cadastrado",VLOOKUP($C13,'IDEB Municípios'!$A$2:$F$228,2,FALSE)),"— sem IDEB cadastrado") | L13: 2 | M13: 2 | N13: =IFERROR(VLOOKUP($A13,'Base Tratada'!$A$2:$AD$577,3,FALSE),"—") | Q13: 2 | R13: 1 | S13: =IFERROR(VLOOKUP($A13,'Base Tratada'!$A$2:$AD$577,10,FALSE),"—") | U13: =IFERROR(VLOOKUP($A13,'Base Tratada'!$A$2:$AD$577,11,FALSE),"—") | V13: =IFERROR(IF(COUNTIF('Fusão Turmas'!$J$2:$J$63,$A13)+COUNTIF('Fusão Turmas'!$N$2:$N$63,$A13)=0,"Sem fusão turma a turma",COUNTIF('Fusão Turmas'!$J$2:$J$63,$A13)&" turma(s) saem · "&COUNTIF('Fusão Turmas'!$N$2:$N$63,$A13)&" turma(s) recebem"),"—") | W13: =IFERROR(VLOOKUP($A13,'Base GDI'!$A$2:$AL$1501,6,FALSE),"") | X13: 5 | Y13: =IF($X13="","",IF($W13>$X13,($W13-$X13)&" SALA(S) OCIOSA(S)",IF($W13<$X13,"CONSTRUIR "&($X13-$W13)&" SALA(S)","QUANTIDADE ADEQUADA"))) | Z13: =IFERROR(VLOOKUP($A13,'Base Tratada'!$A$2:$AD$577,7,FALSE),"—") | AA13: =IFERROR(VLOOKUP($A13,'Base Tratada'!$A$2:$AD$577,16,FALSE),"—") | AD13: =IFERROR(VLOOKUP($A13,'Base Tratada'!$A$2:$AD$577,26,FALSE),"—") | AE13: =IFERROR(VLOOKUP($A13,'Base Tratada'!$A$2:$AD$577,21,FALSE),"—") | AG13: =IF($A13="","",$M13&" de 1ª | "&$Q13&" de 2ª | "&$R13&" de 3ª | Necessidade: "&$X13&" salas | "&$Y13) | AH13: =IFERROR(VLOOKUP($A13,'Base GDI'!$A$2:$AL$1501,18,FALSE),"—")
... A85: 22123458 | B85: =IFERROR(VLOOKUP($A85,'Base GDI'!$A$2:$AL$1501,3,FALSE),"") | C85: PEDRO II | D85: =IFERROR(VLOOKUP($A85,'Base GDI'!$A$2:$AL$1501,5,FALSE),"") | E85: =IFERROR(VLOOKUP($A85,'Base GDI'!$A$2:$AL$1501,14,FALSE),"") | F85: =IFERROR(VLOOKUP($A85,'Base GDI'!$A$2:$AL$1501,15,FALSE),"") | G85: =IFERROR(VLOOKUP($A85,'Base Tratada'!$A$2:$AD$577,9,FALSE),"—") | H85: =IF($C85="","",IFERROR(VLOOKUP($C85,'Panorama Municipal'!$A$2:$N$228,7,FALSE),"—")&" alunos · "&IFERROR(VLOOKUP($C85,'Panorama Municipal'!$A$2:$N$228,8,FALSE),"—")&" turmas (estadual nesta escola: "&IFERROR(VLOOKUP($A85,'Base Tratada'!$A$2:$AD$577,18,FALSE),0)&")") | I85: =IF($C85="","",IF(IFERROR(VLOOKUP($C85,'Panorama Municipal'!$A$2:$N$228,11,FALSE),"")="","—",IF(IFERROR(VLOOKUP($C85,'Panorama Municipal'!$A$2:$N$228,11,FALSE),"")>0,"FALTAM DISTRIBUIR "&IFERROR(VLOOKUP($C85,'Panorama Municipal'!$A$2:$N$228,11,FALSE),"")&" TURMA(S)",IF(IFERROR(VLOOKUP($C85,'Panorama Municipal'!$A$2:$N$228,11,FALSE),"")=0,"DEMANDA MUNICIPAL ATENDIDA","EXCEDE A DEMANDA EM "&ABS(IFERROR(VLOOKUP($C85,'Panorama Municipal'!$A$2:$N$228,11,FALSE),""))&" TURMA(S)")))) | K85: =IFERROR(IF(N(VLOOKUP($C85,'IDEB Municípios'!$A$2:$F$228,2,FALSE))=0,"— sem IDEB cadastrado",VLOOKUP($C85,'IDEB Municípios'!$A$2:$F$228,2,FALSE)),"— sem IDEB cadastrado") | L85: 4 | M85: 4 | N85: =IFERROR(VLOOKUP($A85,'Base Tratada'!$A$2:$AD$577,3,FALSE),"—") | Q85: 4 | R85: 4 | S85: =IFERROR(VLOOKUP($A85,'Base Tratada'!$A$2:$AD$577,10,FALSE),"—") | U85: =IFERROR(VLOOKUP($A85,'Base Tratada'!$A$2:$AD$577,11,FALSE),"—") | V85: =IFERROR(IF(COUNTIF('Fusão Turmas'!$J$2:$J$63,$A85)+COUNTIF('Fusão Turmas'!$N$2:$N$63,$A85)=0,"Sem fusão turma a turma",COUNTIF('Fusão Turmas'!$J$2:$J$63,$A85)&" turma(s) saem · "&COUNTIF('Fusão Turmas'!$N$2:$N$63,$A85)&" turma(s) recebem"),"—") | W85: =IFERROR(VLOOKUP($A85,'Base GDI'!$A$2:$AL$1501,6,FALSE),"") | X85: 19 | Y85: =IF($X85="","",IF($W85>$X85,($W85-$X85)&" SALA(S) OCIOSA(S)",IF($W85<$X85,"CONSTRUIR "&($X85-$W85)&" SALA(S)","QUANTIDADE ADEQUADA"))) | Z85: =IFERROR(VLOOKUP($A85,'Base Tratada'!$A$2:$AD$577,7,FALSE),"—") | AA85: =IFERROR(VLOOKUP($A85,'Base Tratada'!$A$2:$AD$577,16,FALSE),"—") | AD85: =IFERROR(VLOOKUP($A85,'Base Tratada'!$A$2:$AD$577,26,FALSE),"—") | AE85: =IFERROR(VLOOKUP($A85,'Base Tratada'!$A$2:$AD$577,21,FALSE),"—") | AG85: =IF($A85="","",$M85&" de 1ª | "&$Q85&" de 2ª | "&$R85&" de 3ª | Necessidade: "&$X85&" salas | "&$Y85) | AH85: =IFERROR(VLOOKUP($A85,'Base GDI'!$A$2:$AL$1501,18,FALSE),"—")
A86: 22130640 | B86: =IFERROR(VLOOKUP($A86,'Base GDI'!$A$2:$AL$1501,3,FALSE),"") | D86: =IFERROR(VLOOKUP($A86,'Base GDI'!$A$2:$AL$1501,5,FALSE),"") | E86: =IFERROR(VLOOKUP($A86,'Base GDI'!$A$2:$AL$1501,14,FALSE),"") | F86: =IFERROR(VLOOKUP($A86,'Base GDI'!$A$2:$AL$1501,15,FALSE),"") | G86: =IFERROR(VLOOKUP($A86,'Base Tratada'!$A$2:$AD$577,9,FALSE),"—") | H86: =IF($C86="","",IFERROR(VLOOKUP($C86,'Panorama Municipal'!$A$2:$N$228,7,FALSE),"—")&" alunos · "&IFERROR(VLOOKUP($C86,'Panorama Municipal'!$A$2:$N$228,8,FALSE),"—")&" turmas (estadual nesta escola: "&IFERROR(VLOOKUP($A86,'Base Tratada'!$A$2:$AD$577,18,FALSE),0)&")") | I86: =IF($C86="","",IF(IFERROR(VLOOKUP($C86,'Panorama Municipal'!$A$2:$N$228,11,FALSE),"")="","—",IF(IFERROR(VLOOKUP($C86,'Panorama Municipal'!$A$2:$N$228,11,FALSE),"")>0,"FALTAM DISTRIBUIR "&IFERROR(VLOOKUP($C86,'Panorama Municipal'!$A$2:$N$228,11,FALSE),"")&" TURMA(S)",IF(IFERROR(VLOOKUP($C86,'Panorama Municipal'!$A$2:$N$228,11,FALSE),"")=0,"DEMANDA MUNICIPAL ATENDIDA","EXCEDE A DEMANDA EM "&ABS(IFERROR(VLOOKUP($C86,'Panorama Municipal'!$A$2:$N$228,11,FALSE),""))&" TURMA(S)")))) | K86: =IFERROR(IF(N(VLOOKUP($C86,'IDEB Municípios'!$A$2:$F$228,2,FALSE))=0,"— sem IDEB cadastrado",VLOOKUP($C86,'IDEB Municípios'!$A$2:$F$228,2,FALSE)),"— sem IDEB cadastrado") | L86: 1 | M86: 1 | N86: =IFERROR(VLOOKUP($A86,'Base Tratada'!$A$2:$AD$577,3,FALSE),"—") | Q86: 1 | R86: 1 | S86: =IFERROR(VLOOKUP($A86,'Base Tratada'!$A$2:$AD$577,10,FALSE),"—") | U86: =IFERROR(VLOOKUP($A86,'Base Tratada'!$A$2:$AD$577,11,FALSE),"—") | V86: =IFERROR(IF(COUNTIF('Fusão Turmas'!$J$2:$J$63,$A86)+COUNTIF('Fusão Turmas'!$N$2:$N$63,$A86)=0,"Sem fusão turma a turma",COUNTIF('Fusão Turmas'!$J$2:$J$63,$A86)&" turma(s) saem · "&COUNTIF('Fusão Turmas'!$N$2:$N$63,$A86)&" turma(s) recebem"),"—") | W86: =IFERROR(VLOOKUP($A86,'Base GDI'!$A$2:$AL$1501,6,FALSE),"") | X86: 7 | Y86: =IF($X86="","",IF($W86>$X86,($W86-$X86)&" SALA(S) OCIOSA(S)",IF($W86<$X86,"CONSTRUIR "&($X86-$W86)&" SALA(S)","QUANTIDADE ADEQUADA"))) | Z86: =IFERROR(VLOOKUP($A86,'Base Tratada'!$A$2:$AD$577,7,FALSE),"—") | AA86: =IFERROR(VLOOKUP($A86,'Base Tratada'!$A$2:$AD$577,16,FALSE),"—") | AD86: =IFERROR(VLOOKUP($A86,'Base Tratada'!$A$2:$AD$577,26,FALSE),"—") | AE86: =IFERROR(VLOOKUP($A86,'Base Tratada'!$A$2:$AD$577,21,FALSE),"—") | AG86: =IF($A86="","",$M86&" de 1ª | "&$Q86&" de 2ª | "&$R86&" de 3ª | Necessidade: "&$X86&" salas | "&$Y86) | AH86: =IFERROR(VLOOKUP($A86,'Base GDI'!$A$2:$AL$1501,18,FALSE),"—")
A87: 22137211 | B87: =IFERROR(VLOOKUP($A87,'Base GDI'!$A$2:$AL$1501,3,FALSE),"") | C87: PEDRO II | D87: =IFERROR(VLOOKUP($A87,'Base GDI'!$A$2:$AL$1501,5,FALSE),"") | E87: =IFERROR(VLOOKUP($A87,'Base GDI'!$A$2:$AL$1501,14,FALSE),"") | F87: =IFERROR(VLOOKUP($A87,'Base GDI'!$A$2:$AL$1501,15,FALSE),"") | G87: =IFERROR(VLOOKUP($A87,'Base Tratada'!$A$2:$AD$577,9,FALSE),"—") | H87: =IF($C87="","",IFERROR(VLOOKUP($C87,'Panorama Municipal'!$A$2:$N$228,7,FALSE),"—")&" alunos · "&IFERROR(VLOOKUP($C87,'Panorama Municipal'!$A$2:$N$228,8,FALSE),"—")&" turmas (estadual nesta escola: "&IFERROR(VLOOKUP($A87,'Base Tratada'!$A$2:$AD$577,18,FALSE),0)&")") | I87: =IF($C87="","",IF(IFERROR(VLOOKUP($C87,'Panorama Municipal'!$A$2:$N$228,11,FALSE),"")="","—",IF(IFERROR(VLOOKUP($C87,'Panorama Municipal'!$A$2:$N$228,11,FALSE),"")>0,"FALTAM DISTRIBUIR "&IFERROR(VLOOKUP($C87,'Panorama Municipal'!$A$2:$N$228,11,FALSE),"")&" TURMA(S)",IF(IFERROR(VLOOKUP($C87,'Panorama Municipal'!$A$2:$N$228,11,FALSE),"")=0,"DEMANDA MUNICIPAL ATENDIDA","EXCEDE A DEMANDA EM "&ABS(IFERROR(VLOOKUP($C87,'Panorama Municipal'!$A$2:$N$228,11,FALSE),""))&" TURMA(S)")))) | K87: =IFERROR(IF(N(VLOOKUP($C87,'IDEB Municípios'!$A$2:$F$228,2,FALSE))=0,"— sem IDEB cadastrado",VLOOKUP($C87,'IDEB Municípios'!$A$2:$F$228,2,FALSE)),"— sem IDEB cadastrado") | L87: 1 | M87: 1 | N87: =IFERROR(VLOOKUP($A87,'Base Tratada'!$A$2:$AD$577,3,FALSE),"—") | Q87: 1 | R87: 1 | S87: =IFERROR(VLOOKUP($A87,'Base Tratada'!$A$2:$AD$577,10,FALSE),"—") | U87: =IFERROR(VLOOKUP($A87,'Base Tratada'!$A$2:$AD$577,11,FALSE),"—") | V87: =IFERROR(IF(COUNTIF('Fusão Turmas'!$J$2:$J$63,$A87)+COUNTIF('Fusão Turmas'!$N$2:$N$63,$A87)=0,"Sem fusão turma a turma",COUNTIF('Fusão Turmas'!$J$2:$J$63,$A87)&" turma(s) saem · "&COUNTIF('Fusão Turmas'!$N$2:$N$63,$A87)&" turma(s) recebem"),"—") | W87: =IFERROR(VLOOKUP($A87,'Base GDI'!$A$2:$AL$1501,6,FALSE),"") | X87: 3 | Y87: =IF($X87="","",IF($W87>$X87,($W87-$X87)&" SALA(S) OCIOSA(S)",IF($W87<$X87,"CONSTRUIR "&($X87-$W87)&" SALA(S)","QUANTIDADE ADEQUADA"))) | Z87: =IFERROR(VLOOKUP($A87,'Base Tratada'!$A$2:$AD$577,7,FALSE),"—") | AA87: =IFERROR(VLOOKUP($A87,'Base Tratada'!$A$2:$AD$577,16,FALSE),"—") | AD87: =IFERROR(VLOOKUP($A87,'Base Tratada'!$A$2:$AD$577,26,FALSE),"—") | AE87: =IFERROR(VLOOKUP($A87,'Base Tratada'!$A$2:$AD$577,21,FALSE),"—") | AG87: =IF($A87="","",$M87&" de 1ª | "&$Q87&" de 2ª | "&$R87&" de 3ª | Necessidade: "&$X87&" salas | "&$Y87) | AH87: =IFERROR(VLOOKUP($A87,'Base GDI'!$A$2:$AL$1501,18,FALSE),"—")
A88: 22016694 | B88: =IFERROR(VLOOKUP($A88,'Base GDI'!$A$2:$AL$1501,3,FALSE),"") | C88: PIRACURUCA | D88: =IFERROR(VLOOKUP($A88,'Base GDI'!$A$2:$AL$1501,5,FALSE),"") | E88: =IFERROR(VLOOKUP($A88,'Base GDI'!$A$2:$AL$1501,14,FALSE),"") | F88: =IFERROR(VLOOKUP($A88,'Base GDI'!$A$2:$AL$1501,15,FALSE),"") | G88: =IFERROR(VLOOKUP($A88,'Base Tratada'!$A$2:$AD$577,9,FALSE),"—") | H88: =IF($C88="","",IFERROR(VLOOKUP($C88,'Panorama Municipal'!$A$2:$N$228,7,FALSE),"—")&" alunos · "&IFERROR(VLOOKUP($C88,'Panorama Municipal'!$A$2:$N$228,8,FALSE),"—")&" turmas (estadual nesta escola: "&IFERROR(VLOOKUP($A88,'Base Tratada'!$A$2:$AD$577,18,FALSE),0)&")") | I88: =IF($C88="","",IF(IFERROR(VLOOKUP($C88,'Panorama Municipal'!$A$2:$N$228,11,FALSE),"")="","—",IF(IFERROR(VLOOKUP($C88,'Panorama Municipal'!$A$2:$N$228,11,FALSE),"")>0,"FALTAM DISTRIBUIR "&IFERROR(VLOOKUP($C88,'Panorama Municipal'!$A$2:$N$228,11,FALSE),"")&" TURMA(S)",IF(IFERROR(VLOOKUP($C88,'Panorama Municipal'!$A$2:$N$228,11,FALSE),"")=0,"DEMANDA MUNICIPAL ATENDIDA","EXCEDE A DEMANDA EM "&ABS(IFERROR(VLOOKUP($C88,'Panorama Municipal'!$A$2:$N$228,11,FALSE),""))&" TURMA(S)")))) | K88: =IFERROR(IF(N(VLOOKUP($C88,'IDEB Municípios'!$A$2:$F$228,2,FALSE))=0,"— sem IDEB cadastrado",VLOOKUP($C88,'IDEB Municípios'!$A$2:$F$228,2,FALSE)),"— sem IDEB cadastrado") | L88: 3 | M88: 3 | N88: =IFERROR(VLOOKUP($A88,'Base Tratada'!$A$2:$AD$577,3,FALSE),"—") | Q88: 3 | R88: 3 | S88: =IFERROR(VLOOKUP($A88,'Base Tratada'!$A$2:$AD$577,10,FALSE),"—") | U88: =IFERROR(VLOOKUP($A88,'Base Tratada'!$A$2:$AD$577,11,FALSE),"—") | V88: =IFERROR(IF(COUNTIF('Fusão Turmas'!$J$2:$J$63,$A88)+COUNTIF('Fusão Turmas'!$N$2:$N$63,$A88)=0,"Sem fusão turma a turma",COUNTIF('Fusão Turmas'!$J$2:$J$63,$A88)&" turma(s) saem · "&COUNTIF('Fusão Turmas'!$N$2:$N$63,$A88)&" turma(s) recebem"),"—") | W88: =IFERROR(VLOOKUP($A88,'Base GDI'!$A$2:$AL$1501,6,FALSE),"") | X88: 15 | Y88: =IF($X88="","",IF($W88>$X88,($W88-$X88)&" SALA(S) OCIOSA(S)",IF($W88<$X88,"CONSTRUIR "&($X88-$W88)&" SALA(S)","QUANTIDADE ADEQUADA"))) | Z88: =IFERROR(VLOOKUP($A88,'Base Tratada'!$A$2:$AD$577,7,FALSE),"—") | AA88: =IFERROR(VLOOKUP($A88,'Base Tratada'!$A$2:$AD$577,16,FALSE),"—") | AD88: =IFERROR(VLOOKUP($A88,'Base Tratada'!$A$2:$AD$577,26,FALSE),"—") | AE88: =IFERROR(VLOOKUP($A88,'Base Tratada'!$A$2:$AD$577,21,FALSE),"—") | AG88: =IF($A88="","",$M88&" de 1ª | "&$Q88&" de 2ª | "&$R88&" de 3ª | Necessidade: "&$X88&" salas | "&$Y88) | AH88: =IFERROR(VLOOKUP($A88,'Base GDI'!$A$2:$AL$1501,18,FALSE),"—")
A89: 22016724 | B89: =IFERROR(VLOOKUP($A89,'Base GDI'!$A$2:$AL$1501,3,FALSE),"") | C89: PIRACURUCA | D89: =IFERROR(VLOOKUP($A89,'Base GDI'!$A$2:$AL$1501,5,FALSE),"") | E89: =IFERROR(VLOOKUP($A89,'Base GDI'!$A$2:$AL$1501,14,FALSE),"") | F89: =IFERROR(VLOOKUP($A89,'Base GDI'!$A$2:$AL$1501,15,FALSE),"") | G89: =IFERROR(VLOOKUP($A89,'Base Tratada'!$A$2:$AD$577,9,FALSE),"—") | H89: =IF($C89="","",IFERROR(VLOOKUP($C89,'Panorama Municipal'!$A$2:$N$228,7,FALSE),"—")&" alunos · "&IFERROR(VLOOKUP($C89,'Panorama Municipal'!$A$2:$N$228,8,FALSE),"—")&" turmas (estadual nesta escola: "&IFERROR(VLOOKUP($A89,'Base Tratada'!$A$2:$AD$577,18,FALSE),0)&")") | I89: =IF($C89="","",IF(IFERROR(VLOOKUP($C89,'Panorama Municipal'!$A$2:$N$228,11,FALSE),"")="","—",IF(IFERROR(VLOOKUP($C89,'Panorama Municipal'!$A$2:$N$228,11,FALSE),"")>0,"FALTAM DISTRIBUIR "&IFERROR(VLOOKUP($C89,'Panorama Municipal'!$A$2:$N$228,11,FALSE),"")&" TURMA(S)",IF(IFERROR(VLOOKUP($C89,'Panorama Municipal'!$A$2:$N$228,11,FALSE),"")=0,"DEMANDA MUNICIPAL ATENDIDA","EXCEDE A DEMANDA EM "&ABS(IFERROR(VLOOKUP($C89,'Panorama Municipal'!$A$2:$N$228,11,FALSE),""))&" TURMA(S)")))) | K89: =IFERROR(IF(N(VLOOKUP($C89,'IDEB Municípios'!$A$2:$F$228,2,FALSE))=0,"— sem IDEB cadastrado",VLOOKUP($C89,'IDEB Municípios'!$A$2:$F$228,2,FALSE)),"— sem IDEB cadastrado") | L89: 4 | M89: 4 | N89: =IFERROR(VLOOKUP($A89,'Base Tratada'!$A$2:$AD$577,3,FALSE),"—") | Q89: 4 | R89: 4 | S89: =IFERROR(VLOOKUP($A89,'Base Tratada'!$A$2:$AD$577,10,FALSE),"—") | U89: =IFERROR(VLOOKUP($A89,'Base Tratada'!$A$2:$AD$577,11,FALSE),"—") | V89: =IFERROR(IF(COUNTIF('Fusão Turmas'!$J$2:$J$63,$A89)+COUNTIF('Fusão Turmas'!$N$2:$N$63,$A89)=0,"Sem fusão turma a turma",COUNTIF('Fusão Turmas'!$J$2:$J$63,$A89)&" turma(s) saem · "&COUNTIF('Fusão Turmas'!$N$2:$N$63,$A89)&" turma(s) recebem"),"—") | W89: =IFERROR(VLOOKUP($A89,'Base GDI'!$A$2:$AL$1501,6,FALSE),"") | X89: 12 | Y89: =IF($X89="","",IF($W89>$X89,($W89-$X89)&" SALA(S) OCIOSA(S)",IF($W89<$X89,"CONSTRUIR "&($X89-$W89)&" SALA(S)","QUANTIDADE ADEQUADA"))) | Z89: =IFERROR(VLOOKUP($A89,'Base Tratada'!$A$2:$AD$577,7,FALSE),"—") | AA89: =IFERROR(VLOOKUP($A89,'Base Tratada'!$A$2:$AD$577,16,FALSE),"—") | AD89: =IFERROR(VLOOKUP($A89,'Base Tratada'!$A$2:$AD$577,26,FALSE),"—") | AE89: =IFERROR(VLOOKUP($A89,'Base Tratada'!$A$2:$AD$577,21,FALSE),"—") | AG89: =IF($A89="","",$M89&" de 1ª | "&$Q89&" de 2ª | "&$R89&" de 3ª | Necessidade: "&$X89&" salas | "&$Y89) | AH89: =IFERROR(VLOOKUP($A89,'Base GDI'!$A$2:$AL$1501,18,FALSE),"—")
A90: 22016937 | B90: =IFERROR(VLOOKUP($A90,'Base GDI'!$A$2:$AL$1501,3,FALSE),"") | C90: PIRACURUCA | D90: =IFERROR(VLOOKUP($A90,'Base GDI'!$A$2:$AL$1501,5,FALSE),"") | E90: =IFERROR(VLOOKUP($A90,'Base GDI'!$A$2:$AL$1501,14,FALSE),"") | F90: =IFERROR(VLOOKUP($A90,'Base GDI'!$A$2:$AL$1501,15,FALSE),"") | G90: =IFERROR(VLOOKUP($A90,'Base Tratada'!$A$2:$AD$577,9,FALSE),"—") | H90: =IF($C90="","",IFERROR(VLOOKUP($C90,'Panorama Municipal'!$A$2:$N$228,7,FALSE),"—")&" alunos · "&IFERROR(VLOOKUP($C90,'Panorama Municipal'!$A$2:$N$228,8,FALSE),"—")&" turmas (estadual nesta escola: "&IFERROR(VLOOKUP($A90,'Base Tratada'!$A$2:$AD$577,18,FALSE),0)&")") | I90: =IF($C90="","",IF(IFERROR(VLOOKUP($C90,'Panorama Municipal'!$A$2:$N$228,11,FALSE),"")="","—",IF(IFERROR(VLOOKUP($C90,'Panorama Municipal'!$A$2:$N$228,11,FALSE),"")>0,"FALTAM DISTRIBUIR "&IFERROR(VLOOKUP($C90,'Panorama Municipal'!$A$2:$N$228,11,FALSE),"")&" TURMA(S)",IF(IFERROR(VLOOKUP($C90,'Panorama Municipal'!$A$2:$N$228,11,FALSE),"")=0,"DEMANDA MUNICIPAL ATENDIDA","EXCEDE A DEMANDA EM "&ABS(IFERROR(VLOOKUP($C90,'Panorama Municipal'!$A$2:$N$228,11,FALSE),""))&" TURMA(S)")))) | K90: =IFERROR(IF(N(VLOOKUP($C90,'IDEB Municípios'!$A$2:$F$228,2,FALSE))=0,"— sem IDEB cadastrado",VLOOKUP($C90,'IDEB Municípios'!$A$2:$F$228,2,FALSE)),"— sem IDEB cadastrado") | L90: 1 | M90: 1 | N90: =IFERROR(VLOOKUP($A90,'Base Tratada'!$A$2:$AD$577,3,FALSE),"—") | Q90: 1 | R90: 2 | S90: =IFERROR(VLOOKUP($A90,'Base Tratada'!$A$2:$AD$577,10,FALSE),"—") | U90: =IFERROR(VLOOKUP($A90,'Base Tratada'!$A$2:$AD$577,11,FALSE),"—") | V90: =IFERROR(IF(COUNTIF('Fusão Turmas'!$J$2:$J$63,$A90)+COUNTIF('Fusão Turmas'!$N$2:$N$63,$A90)=0,"Sem fusão turma a turma",COUNTIF('Fusão Turmas'!$J$2:$J$63,$A90)&" turma(s) saem · "&COUNTIF('Fusão Turmas'!$N$2:$N$63,$A90)&" turma(s) recebem"),"—") | W90: =IFERROR(VLOOKUP($A90,'Base GDI'!$A$2:$AL$1501,6,FALSE),"") | X90: 8 | Y90: =IF($X90="","",IF($W90>$X90,($W90-$X90)&" SALA(S) OCIOSA(S)",IF($W90<$X90,"CONSTRUIR "&($X90-$W90)&" SALA(S)","QUANTIDADE ADEQUADA"))) | Z90: =IFERROR(VLOOKUP($A90,'Base Tratada'!$A$2:$AD$577,7,FALSE),"—") | AA90: =IFERROR(VLOOKUP($A90,'Base Tratada'!$A$2:$AD$577,16,FALSE),"—") | AD90: =IFERROR(VLOOKUP($A90,'Base Tratada'!$A$2:$AD$577,26,FALSE),"—") | AE90: =IFERROR(VLOOKUP($A90,'Base Tratada'!$A$2:$AD$577,21,FALSE),"—") | AG90: =IF($A90="","",$M90&" de 1ª | "&$Q90&" de 2ª | "&$R90&" de 3ª | Necessidade: "&$X90&" salas | "&$Y90) | AH90: =IFERROR(VLOOKUP($A90,'Base GDI'!$A$2:$AL$1501,18,FALSE),"—")
A91: 22017011 | B91: =IFERROR(VLOOKUP($A91,'Base GDI'!$A$2:$AL$1501,3,FALSE),"") | C91: PIRACURUCA | D91: =IFERROR(VLOOKUP($A91,'Base GDI'!$A$2:$AL$1501,5,FALSE),"") | E91: =IFERROR(VLOOKUP($A91,'Base GDI'!$A$2:$AL$1501,14,FALSE),"") | F91: =IFERROR(VLOOKUP($A91,'Base GDI'!$A$2:$AL$1501,15,FALSE),"") | G91: =IFERROR(VLOOKUP($A91,'Base Tratada'!$A$2:$AD$577,9,FALSE),"—") | H91: =IF($C91="","",IFERROR(VLOOKUP($C91,'Panorama Municipal'!$A$2:$N$228,7,FALSE),"—")&" alunos · "&IFERROR(VLOOKUP($C91,'Panorama Municipal'!$A$2:$N$228,8,FALSE),"—")&" turmas (estadual nesta escola: "&IFERROR(VLOOKUP($A91,'Base Tratada'!$A$2:$AD$577,18,FALSE),0)&")") | I91: =IF($C91="","",IF(IFERROR(VLOOKUP($C91,'Panorama Municipal'!$A$2:$N$228,11,FALSE),"")="","—",IF(IFERROR(VLOOKUP($C91,'Panorama Municipal'!$A$2:$N$228,11,FALSE),"")>0,"FALTAM DISTRIBUIR "&IFERROR(VLOOKUP($C91,'Panorama Municipal'!$A$2:$N$228,11,FALSE),"")&" TURMA(S)",IF(IFERROR(VLOOKUP($C91,'Panorama Municipal'!$A$2:$N$228,11,FALSE),"")=0,"DEMANDA MUNICIPAL ATENDIDA","EXCEDE A DEMANDA EM "&ABS(IFERROR(VLOOKUP($C91,'Panorama Municipal'!$A$2:$N$228,11,FALSE),""))&" TURMA(S)")))) | K91: =IFERROR(IF(N(VLOOKUP($C91,'IDEB Municípios'!$A$2:$F$228,2,FALSE))=0,"— sem IDEB cadastrado",VLOOKUP($C91,'IDEB Municípios'!$A$2:$F$228,2,FALSE)),"— sem IDEB cadastrado") | L91: 4 | M91: 4 | N91: =IFERROR(VLOOKUP($A91,'Base Tratada'!$A$2:$AD$577,3,FALSE),"—") | Q91: 4 | R91: 3 | S91: =IFERROR(VLOOKUP($A91,'Base Tratada'!$A$2:$AD$577,10,FALSE),"—") | U91: =IFERROR(VLOOKUP($A91,'Base Tratada'!$A$2:$AD$577,11,FALSE),"—") | V91: =IFERROR(IF(COUNTIF('Fusão Turmas'!$J$2:$J$63,$A91)+COUNTIF('Fusão Turmas'!$N$2:$N$63,$A91)=0,"Sem fusão turma a turma",COUNTIF('Fusão Turmas'!$J$2:$J$63,$A91)&" turma(s) saem · "&COUNTIF('Fusão Turmas'!$N$2:$N$63,$A91)&" turma(s) recebem"),"—") | W91: =IFERROR(VLOOKUP($A91,'Base GDI'!$A$2:$AL$1501,6,FALSE),"") | X91: 13 | Y91: =IF($X91="","",IF($W91>$X91,($W91-$X91)&" SALA(S) OCIOSA(S)",IF($W91<$X91,"CONSTRUIR "&($X91-$W91)&" SALA(S)","QUANTIDADE ADEQUADA"))) | Z91: =IFERROR(VLOOKUP($A91,'Base Tratada'!$A$2:$AD$577,7,FALSE),"—") | AA91: =IFERROR(VLOOKUP($A91,'Base Tratada'!$A$2:$AD$577,16,FALSE),"—") | AD91: =IFERROR(VLOOKUP($A91,'Base Tratada'!$A$2:$AD$577,26,FALSE),"—") | AE91: =IFERROR(VLOOKUP($A91,'Base Tratada'!$A$2:$AD$577,21,FALSE),"—") | AG91: =IF($A91="","",$M91&" de 1ª | "&$Q91&" de 2ª | "&$R91&" de 3ª | Necessidade: "&$X91&" salas | "&$Y91) | AH91: =IFERROR(VLOOKUP($A91,'Base GDI'!$A$2:$AL$1501,18,FALSE),"—")
A92: 22147403 | B92: =IFERROR(VLOOKUP($A92,'Base GDI'!$A$2:$AL$1501,3,FALSE),"") | C92: PIRACURUCA | D92: =IFERROR(VLOOKUP($A92,'Base GDI'!$A$2:$AL$1501,5,FALSE),"") | E92: =IFERROR(VLOOKUP($A92,'Base GDI'!$A$2:$AL$1501,14,FALSE),"") | F92: =IFERROR(VLOOKUP($A92,'Base GDI'!$A$2:$AL$1501,15,FALSE),"") | G92: =IFERROR(VLOOKUP($A92,'Base Tratada'!$A$2:$AD$577,9,FALSE),"—") | H92: =IF($C92="","",IFERROR(VLOOKUP($C92,'Panorama Municipal'!$A$2:$N$228,7,FALSE),"—")&" alunos · "&IFERROR(VLOOKUP($C92,'Panorama Municipal'!$A$2:$N$228,8,FALSE),"—")&" turmas (estadual nesta escola: "&IFERROR(VLOOKUP($A92,'Base Tratada'!$A$2:$AD$577,18,FALSE),0)&")") | I92: =IF($C92="","",IF(IFERROR(VLOOKUP($C92,'Panorama Municipal'!$A$2:$N$228,11,FALSE),"")="","—",IF(IFERROR(VLOOKUP($C92,'Panorama Municipal'!$A$2:$N$228,11,FALSE),"")>0,"FALTAM DISTRIBUIR "&IFERROR(VLOOKUP($C92,'Panorama Municipal'!$A$2:$N$228,11,FALSE),"")&" TURMA(S)",IF(IFERROR(VLOOKUP($C92,'Panorama Municipal'!$A$2:$N$228,11,FALSE),"")=0,"DEMANDA MUNICIPAL ATENDIDA","EXCEDE A DEMANDA EM "&ABS(IFERROR(VLOOKUP($C92,'Panorama Municipal'!$A$2:$N$228,11,FALSE),""))&" TURMA(S)")))) | K92: =IFERROR(IF(N(VLOOKUP($C92,'IDEB Municípios'!$A$2:$F$228,2,FALSE))=0,"— sem IDEB cadastrado",VLOOKUP($C92,'IDEB Municípios'!$A$2:$F$228,2,FALSE)),"— sem IDEB cadastrado") | L92: 1 | M92: 1 | N92: =IFERROR(VLOOKUP($A92,'Base Tratada'!$A$2:$AD$577,3,FALSE),"—") | Q92: 1 | R92: 1 | S92: =IFERROR(VLOOKUP($A92,'Base Tratada'!$A$2:$AD$577,10,FALSE),"—") | U92: =IFERROR(VLOOKUP($A92,'Base Tratada'!$A$2:$AD$577,11,FALSE),"—") | V92: =IFERROR(IF(COUNTIF('Fusão Turmas'!$J$2:$J$63,$A92)+COUNTIF('Fusão Turmas'!$N$2:$N$63,$A92)=0,"Sem fusão turma a turma",COUNTIF('Fusão Turmas'!$J$2:$J$63,$A92)&" turma(s) saem · "&COUNTIF('Fusão Turmas'!$N$2:$N$63,$A92)&" turma(s) recebem"),"—") | W92: =IFERROR(VLOOKUP($A92,'Base GDI'!$A$2:$AL$1501,6,FALSE),"") | X92: 3 | Y92: =IF($X92="","",IF($W92>$X92,($W92-$X92)&" SALA(S) OCIOSA(S)",IF($W92<$X92,"CONSTRUIR "&($X92-$W92)&" SALA(S)","QUANTIDADE ADEQUADA"))) | Z92: =IFERROR(VLOOKUP($A92,'Base Tratada'!$A$2:$AD$577,7,FALSE),"—") | AA92: =IFERROR(VLOOKUP($A92,'Base Tratada'!$A$2:$AD$577,16,FALSE),"—") | AD92: =IFERROR(VLOOKUP($A92,'Base Tratada'!$A$2:$AD$577,26,FALSE),"—") | AE92: =IFERROR(VLOOKUP($A92,'Base Tratada'!$A$2:$AD$577,21,FALSE),"—") | AG92: =IF($A92="","",$M92&" de 1ª | "&$Q92&" de 2ª | "&$R92&" de 3ª | Necessidade: "&$X92&" salas | "&$Y92) | AH92: =IFERROR(VLOOKUP($A92,'Base GDI'!$A$2:$AL$1501,18,FALSE),"—")
A93: 22010254 | B93: =IFERROR(VLOOKUP($A93,'Base GDI'!$A$2:$AL$1501,3,FALSE),"") | C93: PIRIPIRI | D93: =IFERROR(VLOOKUP($A93,'Base GDI'!$A$2:$AL$1501,5,FALSE),"") | E93: =IFERROR(VLOOKUP($A93,'Base GDI'!$A$2:$AL$1501,14,FALSE),"") | F93: =IFERROR(VLOOKUP($A93,'Base GDI'!$A$2:$AL$1501,15,FALSE),"") | G93: =IFERROR(VLOOKUP($A93,'Base Tratada'!$A$2:$AD$577,9,FALSE),"—") | H93: =IF($C93="","",IFERROR(VLOOKUP($C93,'Panorama Municipal'!$A$2:$N$228,7,FALSE),"—")&" alunos · "&IFERROR(VLOOKUP($C93,'Panorama Municipal'!$A$2:$N$228,8,FALSE),"—")&" turmas (estadual nesta escola: "&IFERROR(VLOOKUP($A93,'Base Tratada'!$A$2:$AD$577,18,FALSE),0)&")") | I93: =IF($C93="","",IF(IFERROR(VLOOKUP($C93,'Panorama Municipal'!$A$2:$N$228,11,FALSE),"")="","—",IF(IFERROR(VLOOKUP($C93,'Panorama Municipal'!$A$2:$N$228,11,FALSE),"")>0,"FALTAM DISTRIBUIR "&IFERROR(VLOOKUP($C93,'Panorama Municipal'!$A$2:$N$228,11,FALSE),"")&" TURMA(S)",IF(IFERROR(VLOOKUP($C93,'Panorama Municipal'!$A$2:$N$228,11,FALSE),"")=0,"DEMANDA MUNICIPAL ATENDIDA","EXCEDE A DEMANDA EM "&ABS(IFERROR(VLOOKUP($C93,'Panorama Municipal'!$A$2:$N$228,11,FALSE),""))&" TURMA(S)")))) | K93: =IFERROR(IF(N(VLOOKUP($C93,'IDEB Municípios'!$A$2:$F$228,2,FALSE))=0,"— sem IDEB cadastrado",VLOOKUP($C93,'IDEB Municípios'!$A$2:$F$228,2,FALSE)),"— sem IDEB cadastrado") | L93: 3 | M93: 3 | N93: =IFERROR(VLOOKUP($A93,'Base Tratada'!$A$2:$AD$577,3,FALSE),"—") | Q93: 3 | R93: 3 | S93: =IFERROR(VLOOKUP($A93,'Base Tratada'!$A$2:$AD$577,10,FALSE),"—") | U93: =IFERROR(VLOOKUP($A93,'Base Tratada'!$A$2:$AD$577,11,FALSE),"—") | V93: =IFERROR(IF(COUNTIF('Fusão Turmas'!$J$2:$J$63,$A93)+COUNTIF('Fusão Turmas'!$N$2:$N$63,$A93)=0,"Sem fusão turma a turma",COUNTIF('Fusão Turmas'!$J$2:$J$63,$A93)&" turma(s) saem · "&COUNTIF('Fusão Turmas'!$N$2:$N$63,$A93)&" turma(s) recebem"),"—") | W93: =IFERROR(VLOOKUP($A93,'Base GDI'!$A$2:$AL$1501,6,FALSE),"") | X93: 9 | Y93: =IF($X93="","",IF($W93>$X93,($W93-$X93)&" SALA(S) OCIOSA(S)",IF($W93<$X93,"CONSTRUIR "&($X93-$W93)&" SALA(S)","QUANTIDADE ADEQUADA"))) | Z93: =IFERROR(VLOOKUP($A93,'Base Tratada'!$A$2:$AD$577,7,FALSE),"—") | AA93: =IFERROR(VLOOKUP($A93,'Base Tratada'!$A$2:$AD$577,16,FALSE),"—") | AD93: =IFERROR(VLOOKUP($A93,'Base Tratada'!$A$2:$AD$577,26,FALSE),"—") | AE93: =IFERROR(VLOOKUP($A93,'Base Tratada'!$A$2:$AD$577,21,FALSE),"—") | AG93: =IF($A93="","",$M93&" de 1ª | "&$Q93&" de 2ª | "&$R93&" de 3ª | Necessidade: "&$X93&" salas | "&$Y93) | AH93: =IFERROR(VLOOKUP($A93,'Base GDI'!$A$2:$AL$1501,18,FALSE),"—")
A94: 22010467 | B94: =IFERROR(VLOOKUP($A94,'Base GDI'!$A$2:$AL$1501,3,FALSE),"") | C94: PIRIPIRI | D94: =IFERROR(VLOOKUP($A94,'Base GDI'!$A$2:$AL$1501,5,FALSE),"") | E94: =IFERROR(VLOOKUP($A94,'Base GDI'!$A$2:$AL$1501,14,FALSE),"") | F94: =IFERROR(VLOOKUP($A94,'Base GDI'!$A$2:$AL$1501,15,FALSE),"") | G94: =IFERROR(VLOOKUP($A94,'Base Tratada'!$A$2:$AD$577,9,FALSE),"—") | H94: =IF($C94="","",IFERROR(VLOOKUP($C94,'Panorama Municipal'!$A$2:$N$228,7,FALSE),"—")&" alunos · "&IFERROR(VLOOKUP($C94,'Panorama Municipal'!$A$2:$N$228,8,FALSE),"—")&" turmas (estadual nesta escola: "&IFERROR(VLOOKUP($A94,'Base Tratada'!$A$2:$AD$577,18,FALSE),0)&")") | I94: =IF($C94="","",IF(IFERROR(VLOOKUP($C94,'Panorama Municipal'!$A$2:$N$228,11,FALSE),"")="","—",IF(IFERROR(VLOOKUP($C94,'Panorama Municipal'!$A$2:$N$228,11,FALSE),"")>0,"FALTAM DISTRIBUIR "&IFERROR(VLOOKUP($C94,'Panorama Municipal'!$A$2:$N$228,11,FALSE),"")&" TURMA(S)",IF(IFERROR(VLOOKUP($C94,'Panorama Municipal'!$A$2:$N$228,11,FALSE),"")=0,"DEMANDA MUNICIPAL ATENDIDA","EXCEDE A DEMANDA EM "&ABS(IFERROR(VLOOKUP($C94,'Panorama Municipal'!$A$2:$N$228,11,FALSE),""))&" TURMA(S)")))) | K94: =IFERROR(IF(N(VLOOKUP($C94,'IDEB Municípios'!$A$2:$F$228,2,FALSE))=0,"— sem IDEB cadastrado",VLOOKUP($C94,'IDEB Municípios'!$A$2:$F$228,2,FALSE)),"— sem IDEB cadastrado") | L94: 2 | M94: 2 | N94: =IFERROR(VLOOKUP($A94,'Base Tratada'!$A$2:$AD$577,3,FALSE),"—") | Q94: 2 | R94: 3 | S94: =IFERROR(VLOOKUP($A94,'Base Tratada'!$A$2:$AD$577,10,FALSE),"—") | U94: =IFERROR(VLOOKUP($A94,'Base Tratada'!$A$2:$AD$577,11,FALSE),"—") | V94: =IFERROR(IF(COUNTIF('Fusão Turmas'!$J$2:$J$63,$A94)+COUNTIF('Fusão Turmas'!$N$2:$N$63,$A94)=0,"Sem fusão turma a turma",COUNTIF('Fusão Turmas'!$J$2:$J$63,$A94)&" turma(s) saem · "&COUNTIF('Fusão Turmas'!$N$2:$N$63,$A94)&" turma(s) recebem"),"—") | W94: =IFERROR(VLOOKUP($A94,'Base GDI'!$A$2:$AL$1501,6,FALSE),"") | X94: 7 | Y94: =IF($X94="","",IF($W94>$X94,($W94-$X94)&" SALA(S) OCIOSA(S)",IF($W94<$X94,"CONSTRUIR "&($X94-$W94)&" SALA(S)","QUANTIDADE ADEQUADA"))) | Z94: =IFERROR(VLOOKUP($A94,'Base Tratada'!$A$2:$AD$577,7,FALSE),"—") | AA94: =IFERROR(VLOOKUP($A94,'Base Tratada'!$A$2:$AD$577,16,FALSE),"—") | AD94: =IFERROR(VLOOKUP($A94,'Base Tratada'!$A$2:$AD$577,26,FALSE),"—") | AE94: =IFERROR(VLOOKUP($A94,'Base Tratada'!$A$2:$AD$577,21,FALSE),"—") | AG94: =IF($A94="","",$M94&" de 1ª | "&$Q94&" de 2ª | "&$R94&" de 3ª | Necessidade: "&$X94&" salas | "&$Y94) | AH94: =IFERROR(VLOOKUP($A94,'Base GDI'!$A$2:$AL$1501,18,FALSE),"—")
A95: 22010483 | B95: =IFERROR(VLOOKUP($A95,'Base GDI'!$A$2:$AL$1501,3,FALSE),"") | C95: PIRIPIRI | D95: =IFERROR(VLOOKUP($A95,'Base GDI'!$A$2:$AL$1501,5,FALSE),"") | E95: =IFERROR(VLOOKUP($A95,'Base GDI'!$A$2:$AL$1501,14,FALSE),"") | F95: =IFERROR(VLOOKUP($A95,'Base GDI'!$A$2:$AL$1501,15,FALSE),"") | G95: =IFERROR(VLOOKUP($A95,'Base Tratada'!$A$2:$AD$577,9,FALSE),"—") | H95: =IF($C95="","",IFERROR(VLOOKUP($C95,'Panorama Municipal'!$A$2:$N$228,7,FALSE),"—")&" alunos · "&IFERROR(VLOOKUP($C95,'Panorama Municipal'!$A$2:$N$228,8,FALSE),"—")&" turmas (estadual nesta escola: "&IFERROR(VLOOKUP($A95,'Base Tratada'!$A$2:$AD$577,18,FALSE),0)&")") | I95: =IF($C95="","",IF(IFERROR(VLOOKUP($C95,'Panorama Municipal'!$A$2:$N$228,11,FALSE),"")="","—",IF(IFERROR(VLOOKUP($C95,'Panorama Municipal'!$A$2:$N$228,11,FALSE),"")>0,"FALTAM DISTRIBUIR "&IFERROR(VLOOKUP($C95,'Panorama Municipal'!$A$2:$N$228,11,FALSE),"")&" TURMA(S)",IF(IFERROR(VLOOKUP($C95,'Panorama Municipal'!$A$2:$N$228,11,FALSE),"")=0,"DEMANDA MUNICIPAL ATENDIDA","EXCEDE A DEMANDA EM "&ABS(IFERROR(VLOOKUP($C95,'Panorama Municipal'!$A$2:$N$228,11,FALSE),""))&" TURMA(S)")))) | K95: =IFERROR(IF(N(VLOOKUP($C95,'IDEB Municípios'!$A$2:$F$228,2,FALSE))=0,"— sem IDEB cadastrado",VLOOKUP($C95,'IDEB Municípios'!$A$2:$F$228,2,FALSE)),"— sem IDEB cadastrado") | L95: 3 | M95: 3 | N95: =IFERROR(VLOOKUP($A95,'Base Tratada'!$A$2:$AD$577,3,FALSE),"—") | Q95: 3 | R95: 3 | S95: =IFERROR(VLOOKUP($A95,'Base Tratada'!$A$2:$AD$577,10,FALSE),"—") | U95: =IFERROR(VLOOKUP($A95,'Base Tratada'!$A$2:$AD$577,11,FALSE),"—") | V95: =IFERROR(IF(COUNTIF('Fusão Turmas'!$J$2:$J$63,$A95)+COUNTIF('Fusão Turmas'!$N$2:$N$63,$A95)=0,"Sem fusão turma a turma",COUNTIF('Fusão Turmas'!$J$2:$J$63,$A95)&" turma(s) saem · "&COUNTIF('Fusão Turmas'!$N$2:$N$63,$A95)&" turma(s) recebem"),"—") | W95: =IFERROR(VLOOKUP($A95,'Base GDI'!$A$2:$AL$1501,6,FALSE),"") | X95: 9 | Y95: =IF($X95="","",IF($W95>$X95,($W95-$X95)&" SALA(S) OCIOSA(S)",IF($W95<$X95,"CONSTRUIR "&($X95-$W95)&" SALA(S)","QUANTIDADE ADEQUADA"))) | Z95: =IFERROR(VLOOKUP($A95,'Base Tratada'!$A$2:$AD$577,7,FALSE),"—") | AA95: =IFERROR(VLOOKUP($A95,'Base Tratada'!$A$2:$AD$577,16,FALSE),"—") | AD95: =IFERROR(VLOOKUP($A95,'Base Tratada'!$A$2:$AD$577,26,FALSE),"—") | AE95: =IFERROR(VLOOKUP($A95,'Base Tratada'!$A$2:$AD$577,21,FALSE),"—") | AG95: =IF($A95="","",$M95&" de 1ª | "&$Q95&" de 2ª | "&$R95&" de 3ª | Necessidade: "&$X95&" salas | "&$Y95) | AH95: =IFERROR(VLOOKUP($A95,'Base GDI'!$A$2:$AL$1501,18,FALSE),"—")
A96: 22010505 | B96: =IFERROR(VLOOKUP($A96,'Base GDI'!$A$2:$AL$1501,3,FALSE),"") | C96: PIRIPIRI | D96: =IFERROR(VLOOKUP($A96,'Base GDI'!$A$2:$AL$1501,5,FALSE),"") | E96: =IFERROR(VLOOKUP($A96,'Base GDI'!$A$2:$AL$1501,14,FALSE),"") | F96: =IFERROR(VLOOKUP($A96,'Base GDI'!$A$2:$AL$1501,15,FALSE),"") | G96: =IFERROR(VLOOKUP($A96,'Base Tratada'!$A$2:$AD$577,9,FALSE),"—") | H96: =IF($C96="","",IFERROR(VLOOKUP($C96,'Panorama Municipal'!$A$2:$N$228,7,FALSE),"—")&" alunos · "&IFERROR(VLOOKUP($C96,'Panorama Municipal'!$A$2:$N$228,8,FALSE),"—")&" turmas (estadual nesta escola: "&IFERROR(VLOOKUP($A96,'Base Tratada'!$A$2:$AD$577,18,FALSE),0)&")") | I96: =IF($C96="","",IF(IFERROR(VLOOKUP($C96,'Panorama Municipal'!$A$2:$N$228,11,FALSE),"")="","—",IF(IFERROR(VLOOKUP($C96,'Panorama Municipal'!$A$2:$N$228,11,FALSE),"")>0,"FALTAM DISTRIBUIR "&IFERROR(VLOOKUP($C96,'Panorama Municipal'!$A$2:$N$228,11,FALSE),"")&" TURMA(S)",IF(IFERROR(VLOOKUP($C96,'Panorama Municipal'!$A$2:$N$228,11,FALSE),"")=0,"DEMANDA MUNICIPAL ATENDIDA","EXCEDE A DEMANDA EM "&ABS(IFERROR(VLOOKUP($C96,'Panorama Municipal'!$A$2:$N$228,11,FALSE),""))&" TURMA(S)")))) | K96: =IFERROR(IF(N(VLOOKUP($C96,'IDEB Municípios'!$A$2:$F$228,2,FALSE))=0,"— sem IDEB cadastrado",VLOOKUP($C96,'IDEB Municípios'!$A$2:$F$228,2,FALSE)),"— sem IDEB cadastrado") | L96: 2 | M96: 2 | N96: =IFERROR(VLOOKUP($A96,'Base Tratada'!$A$2:$AD$577,3,FALSE),"—") | Q96: 2 | R96: 2 | S96: =IFERROR(VLOOKUP($A96,'Base Tratada'!$A$2:$AD$577,10,FALSE),"—") | U96: =IFERROR(VLOOKUP($A96,'Base Tratada'!$A$2:$AD$577,11,FALSE),"—") | V96: =IFERROR(IF(COUNTIF('Fusão Turmas'!$J$2:$J$63,$A96)+COUNTIF('Fusão Turmas'!$N$2:$N$63,$A96)=0,"Sem fusão turma a turma",COUNTIF('Fusão Turmas'!$J$2:$J$63,$A96)&" turma(s) saem · "&COUNTIF('Fusão Turmas'!$N$2:$N$63,$A96)&" turma(s) recebem"),"—") | W96: =IFERROR(VLOOKUP($A96,'Base GDI'!$A$2:$AL$1501,6,FALSE),"") | X96: 8 | Y96: =IF($X96="","",IF($W96>$X96,($W96-$X96)&" SALA(S) OCIOSA(S)",IF($W96<$X96,"CONSTRUIR "&($X96-$W96)&" SALA(S)","QUANTIDADE ADEQUADA"))) | Z96: =IFERROR(VLOOKUP($A96,'Base Tratada'!$A$2:$AD$577,7,FALSE),"—") | AA96: =IFERROR(VLOOKUP($A96,'Base Tratada'!$A$2:$AD$577,16,FALSE),"—") | AD96: =IFERROR(VLOOKUP($A96,'Base Tratada'!$A$2:$AD$577,26,FALSE),"—") | AE96: =IFERROR(VLOOKUP($A96,'Base Tratada'!$A$2:$AD$577,21,FALSE),"—") | AG96: =IF($A96="","",$M96&" de 1ª | "&$Q96&" de 2ª | "&$R96&" de 3ª | Necessidade: "&$X96&" salas | "&$Y96) | AH96: =IFERROR(VLOOKUP($A96,'Base GDI'!$A$2:$AL$1501,18,FALSE),"—")
A97: 22010513 | B97: =IFERROR(VLOOKUP($A97,'Base GDI'!$A$2:$AL$1501,3,FALSE),"") | C97: PIRIPIRI | D97: =IFERROR(VLOOKUP($A97,'Base GDI'!$A$2:$AL$1501,5,FALSE),"") | E97: =IFERROR(VLOOKUP($A97,'Base GDI'!$A$2:$AL$1501,14,FALSE),"") | F97: =IFERROR(VLOOKUP($A97,'Base GDI'!$A$2:$AL$1501,15,FALSE),"") | G97: =IFERROR(VLOOKUP($A97,'Base Tratada'!$A$2:$AD$577,9,FALSE),"—") | H97: =IF($C97="","",IFERROR(VLOOKUP($C97,'Panorama Municipal'!$A$2:$N$228,7,FALSE),"—")&" alunos · "&IFERROR(VLOOKUP($C97,'Panorama Municipal'!$A$2:$N$228,8,FALSE),"—")&" turmas (estadual nesta escola: "&IFERROR(VLOOKUP($A97,'Base Tratada'!$A$2:$AD$577,18,FALSE),0)&")") | I97: =IF($C97="","",IF(IFERROR(VLOOKUP($C97,'Panorama Municipal'!$A$2:$N$228,11,FALSE),"")="","—",IF(IFERROR(VLOOKUP($C97,'Panorama Municipal'!$A$2:$N$228,11,FALSE),"")>0,"FALTAM DISTRIBUIR "&IFERROR(VLOOKUP($C97,'Panorama Municipal'!$A$2:$N$228,11,FALSE),"")&" TURMA(S)",IF(IFERROR(VLOOKUP($C97,'Panorama Municipal'!$A$2:$N$228,11,FALSE),"")=0,"DEMANDA MUNICIPAL ATENDIDA","EXCEDE A DEMANDA EM "&ABS(IFERROR(VLOOKUP($C97,'Panorama Municipal'!$A$2:$N$228,11,FALSE),""))&" TURMA(S)")))) | K97: =IFERROR(IF(N(VLOOKUP($C97,'IDEB Municípios'!$A$2:$F$228,2,FALSE))=0,"— sem IDEB cadastrado",VLOOKUP($C97,'IDEB Municípios'!$A$2:$F$228,2,FALSE)),"— sem IDEB cadastrado") | L97: 0 | M97: 0 | N97: =IFERROR(VLOOKUP($A97,'Base Tratada'!$A$2:$AD$577,3,FALSE),"—") | Q97: 0 | R97: 0 | S97: =IFERROR(VLOOKUP($A97,'Base Tratada'!$A$2:$AD$577,10,FALSE),"—") | U97: =IFERROR(VLOOKUP($A97,'Base Tratada'!$A$2:$AD$577,11,FALSE),"—") | V97: =IFERROR(IF(COUNTIF('Fusão Turmas'!$J$2:$J$63,$A97)+COUNTIF('Fusão Turmas'!$N$2:$N$63,$A97)=0,"Sem fusão turma a turma",COUNTIF('Fusão Turmas'!$J$2:$J$63,$A97)&" turma(s) saem · "&COUNTIF('Fusão Turmas'!$N$2:$N$63,$A97)&" turma(s) recebem"),"—") | W97: =IFERROR(VLOOKUP($A97,'Base GDI'!$A$2:$AL$1501,6,FALSE),"") | X97: 1 | Y97: =IF($X97="","",IF($W97>$X97,($W97-$X97)&" SALA(S) OCIOSA(S)",IF($W97<$X97,"CONSTRUIR "&($X97-$W97)&" SALA(S)","QUANTIDADE ADEQUADA"))) | Z97: =IFERROR(VLOOKUP($A97,'Base Tratada'!$A$2:$AD$577,7,FALSE),"—") | AA97: =IFERROR(VLOOKUP($A97,'Base Tratada'!$A$2:$AD$577,16,FALSE),"—") | AD97: =IFERROR(VLOOKUP($A97,'Base Tratada'!$A$2:$AD$577,26,FALSE),"—") | AE97: =IFERROR(VLOOKUP($A97,'Base Tratada'!$A$2:$AD$577,21,FALSE),"—") | AG97: =IF($A97="","",$M97&" de 1ª | "&$Q97&" de 2ª | "&$R97&" de 3ª | Necessidade: "&$X97&" salas | "&$Y97) | AH97: =IFERROR(VLOOKUP($A97,'Base GDI'!$A$2:$AL$1501,18,FALSE),"—")
A98: 22010521 | B98: =IFERROR(VLOOKUP($A98,'Base GDI'!$A$2:$AL$1501,3,FALSE),"") | C98: PIRIPIRI | D98: =IFERROR(VLOOKUP($A98,'Base GDI'!$A$2:$AL$1501,5,FALSE),"") | E98: =IFERROR(VLOOKUP($A98,'Base GDI'!$A$2:$AL$1501,14,FALSE),"") | F98: =IFERROR(VLOOKUP($A98,'Base GDI'!$A$2:$AL$1501,15,FALSE),"") | G98: =IFERROR(VLOOKUP($A98,'Base Tratada'!$A$2:$AD$577,9,FALSE),"—") | H98: =IF($C98="","",IFERROR(VLOOKUP($C98,'Panorama Municipal'!$A$2:$N$228,7,FALSE),"—")&" alunos · "&IFERROR(VLOOKUP($C98,'Panorama Municipal'!$A$2:$N$228,8,FALSE),"—")&" turmas (estadual nesta escola: "&IFERROR(VLOOKUP($A98,'Base Tratada'!$A$2:$AD$577,18,FALSE),0)&")") | I98: =IF($C98="","",IF(IFERROR(VLOOKUP($C98,'Panorama Municipal'!$A$2:$N$228,11,FALSE),"")="","—",IF(IFERROR(VLOOKUP($C98,'Panorama Municipal'!$A$2:$N$228,11,FALSE),"")>0,"FALTAM DISTRIBUIR "&IFERROR(VLOOKUP($C98,'Panorama Municipal'!$A$2:$N$228,11,FALSE),"")&" TURMA(S)",IF(IFERROR(VLOOKUP($C98,'Panorama Municipal'!$A$2:$N$228,11,FALSE),"")=0,"DEMANDA MUNICIPAL ATENDIDA","EXCEDE A DEMANDA EM "&ABS(IFERROR(VLOOKUP($C98,'Panorama Municipal'!$A$2:$N$228,11,FALSE),""))&" TURMA(S)")))) | K98: =IFERROR(IF(N(VLOOKUP($C98,'IDEB Municípios'!$A$2:$F$228,2,FALSE))=0,"— sem IDEB cadastrado",VLOOKUP($C98,'IDEB Municípios'!$A$2:$F$228,2,FALSE)),"— sem IDEB cadastrado") | L98: 2 | M98: 2 | N98: =IFERROR(VLOOKUP($A98,'Base Tratada'!$A$2:$AD$577,3,FALSE),"—") | Q98: 2 | R98: 2 | S98: =IFERROR(VLOOKUP($A98,'Base Tratada'!$A$2:$AD$577,10,FALSE),"—") | U98: =IFERROR(VLOOKUP($A98,'Base Tratada'!$A$2:$AD$577,11,FALSE),"—") | V98: =IFERROR(IF(COUNTIF('Fusão Turmas'!$J$2:$J$63,$A98)+COUNTIF('Fusão Turmas'!$N$2:$N$63,$A98)=0,"Sem fusão turma a turma",COUNTIF('Fusão Turmas'!$J$2:$J$63,$A98)&" turma(s) saem · "&COUNTIF('Fusão Turmas'!$N$2:$N$63,$A98)&" turma(s) recebem"),"—") | W98: =IFERROR(VLOOKUP($A98,'Base GDI'!$A$2:$AL$1501,6,FALSE),"") | X98: 7 | Y98: =IF($X98="","",IF($W98>$X98,($W98-$X98)&" SALA(S) OCIOSA(S)",IF($W98<$X98,"CONSTRUIR "&($X98-$W98)&" SALA(S)","QUANTIDADE ADEQUADA"))) | Z98: =IFERROR(VLOOKUP($A98,'Base Tratada'!$A$2:$AD$577,7,FALSE),"—") | AA98: =IFERROR(VLOOKUP($A98,'Base Tratada'!$A$2:$AD$577,16,FALSE),"—") | AD98: =IFERROR(VLOOKUP($A98,'Base Tratada'!$A$2:$AD$577,26,FALSE),"—") | AE98: =IFERROR(VLOOKUP($A98,'Base Tratada'!$A$2:$AD$577,21,FALSE),"—") | AG98: =IF($A98="","",$M98&" de 1ª | "&$Q98&" de 2ª | "&$R98&" de 3ª | Necessidade: "&$X98&" salas | "&$Y98) | AH98: =IFERROR(VLOOKUP($A98,'Base GDI'!$A$2:$AL$1501,18,FALSE),"—")
... A577: 22143017 | B577: =IFERROR(VLOOKUP($A577,'Base GDI'!$A$2:$AL$1501,3,FALSE),"") | C577: TERESINA | D577: =IFERROR(VLOOKUP($A577,'Base GDI'!$A$2:$AL$1501,5,FALSE),"") | E577: =IFERROR(VLOOKUP($A577,'Base GDI'!$A$2:$AL$1501,14,FALSE),"") | F577: =IFERROR(VLOOKUP($A577,'Base GDI'!$A$2:$AL$1501,15,FALSE),"") | G577: =IFERROR(VLOOKUP($A577,'Base Tratada'!$A$2:$AD$577,9,FALSE),"—") | H577: =IF($C577="","",IFERROR(VLOOKUP($C577,'Panorama Municipal'!$A$2:$N$228,7,FALSE),"—")&" alunos · "&IFERROR(VLOOKUP($C577,'Panorama Municipal'!$A$2:$N$228,8,FALSE),"—")&" turmas (estadual nesta escola: "&IFERROR(VLOOKUP($A577,'Base Tratada'!$A$2:$AD$577,18,FALSE),0)&")") | I577: =IF($C577="","",IF(IFERROR(VLOOKUP($C577,'Panorama Municipal'!$A$2:$N$228,11,FALSE),"")="","—",IF(IFERROR(VLOOKUP($C577,'Panorama Municipal'!$A$2:$N$228,11,FALSE),"")>0,"FALTAM DISTRIBUIR "&IFERROR(VLOOKUP($C577,'Panorama Municipal'!$A$2:$N$228,11,FALSE),"")&" TURMA(S)",IF(IFERROR(VLOOKUP($C577,'Panorama Municipal'!$A$2:$N$228,11,FALSE),"")=0,"DEMANDA MUNICIPAL ATENDIDA","EXCEDE A DEMANDA EM "&ABS(IFERROR(VLOOKUP($C577,'Panorama Municipal'!$A$2:$N$228,11,FALSE),""))&" TURMA(S)")))) | K577: =IFERROR(IF(N(VLOOKUP($C577,'IDEB Municípios'!$A$2:$F$228,2,FALSE))=0,"— sem IDEB cadastrado",VLOOKUP($C577,'IDEB Municípios'!$A$2:$F$228,2,FALSE)),"— sem IDEB cadastrado") | L577: 6 | M577: 6 | N577: =IFERROR(VLOOKUP($A577,'Base Tratada'!$A$2:$AD$577,3,FALSE),"—") | Q577: 6 | R577: 3 | S577: =IFERROR(VLOOKUP($A577,'Base Tratada'!$A$2:$AD$577,10,FALSE),"—") | U577: =IFERROR(VLOOKUP($A577,'Base Tratada'!$A$2:$AD$577,11,FALSE),"—") | V577: =IFERROR(IF(COUNTIF('Fusão Turmas'!$J$2:$J$63,$A577)+COUNTIF('Fusão Turmas'!$N$2:$N$63,$A577)=0,"Sem fusão turma a turma",COUNTIF('Fusão Turmas'!$J$2:$J$63,$A577)&" turma(s) saem · "&COUNTIF('Fusão Turmas'!$N$2:$N$63,$A577)&" turma(s) recebem"),"—") | W577: =IFERROR(VLOOKUP($A577,'Base GDI'!$A$2:$AL$1501,6,FALSE),"") | X577: 17 | Y577: =IF($X577="","",IF($W577>$X577,($W577-$X577)&" SALA(S) OCIOSA(S)",IF($W577<$X577,"CONSTRUIR "&($X577-$W577)&" SALA(S)","QUANTIDADE ADEQUADA"))) | Z577: =IFERROR(VLOOKUP($A577,'Base Tratada'!$A$2:$AD$577,7,FALSE),"—") | AA577: =IFERROR(VLOOKUP($A577,'Base Tratada'!$A$2:$AD$577,16,FALSE),"—") | AD577: =IFERROR(VLOOKUP($A577,'Base Tratada'!$A$2:$AD$577,26,FALSE),"—") | AE577: =IFERROR(VLOOKUP($A577,'Base Tratada'!$A$2:$AD$577,21,FALSE),"—") | AG577: =IF($A577="","",$M577&" de 1ª | "&$Q577&" de 2ª | "&$R577&" de 3ª | Necessidade: "&$X577&" salas | "&$Y577) | AH577: =IFERROR(VLOOKUP($A577,'Base GDI'!$A$2:$AL$1501,18,FALSE),"—")

Sheet Reordenamento 2027 V3
A1: INEP | B1: GRE | C1: Município | D1: Escola | E1: Turmas hoje (2026) | F1: Turmas 2027 (projeção) | G1: Oferta Fundamental | H1: 9º Ano NESTA escola (rede estadual) | I1: 9º Ano do município (todas as redes) | J1: Demanda total de 1ª série 2027 | K1: Ainda faltam no município | L1: ★ FUNDAMENTAL 2027 DECIDA AQUI | M1: IDEB do município | N1: 1ª Série 2026 | O1: ★ 1ª SÉRIE 2027 DECIDA AQUI | P1: Cursos EM 2026 (sem EJA) | Q1: ★ CURSOS 1ª SÉRIE 2027 DECIDA AQUI | R1: ★ ALTERAÇÃO DE CURSOS EMI | S1: ★ 2ª SÉRIE 2027 DECIDA AQUI | T1: ★ 3ª SÉRIE 2027 DECIDA AQUI | U1: UETEP · novas matrículas 2027 | V1: UETEP · detalhe por curso | W1: UETEP · turmas previstas | X1: Parciais 2026 | Y1: ★ Parciais 2026 justificativa | Z1: Possíveis fusões NA PRÓPRIA ESCOLA | AA1: Fusão ENTRE ESCOLAS (mesmo município) | AB1: ★ Validação da fusão | AC1: Salas existentes | AD1: Salas necessárias 2027 (calculado) | AE1: ★ SALAS NECESSÁRIAS 2027 — DECIDA AQUI | AF1: Situação da sala | AG1: Oferta EJA 2026 | AH1: Matrículas / Turmas EJA | AI1: EJA fora do prédio matriz (UEJA) | AJ1: ★ EJA Turmas 2027 | AK1: ★ EJA Cursos 2027 | AL1: Anexos desta escola | AM1: Qtd. de anexos | AN1: ★ MANTER O ANEXO? | AO1: ★ ENCERRAR O ANEXO? | AP1: ★ REMANEJAR A OFERTA DO ANEXO? | AQ1: Resumo 2027 | AR1: Escola Próxima | AS1: ★ Reordenamento 2027 | AT1: ★ Justificativa | AU1: ★ Observação | AV1: ✓ Pronto
A2: 22129723 | B2: =IFERROR(VLOOKUP($A2,'Base GDI'!$A$2:$AL$1501,3,FALSE),"") | C2: BOM PRINCIPIO DO PIAUI | D2: =IFERROR(VLOOKUP($A2,'Base GDI'!$A$2:$AL$1501,5,FALSE),"") | E2: =IFERROR(VLOOKUP($A2,'Base GDI'!$A$2:$AL$1501,14,FALSE),"") | F2: =IFERROR(VLOOKUP($A2,'Base GDI'!$A$2:$AL$1501,15,FALSE),"") | G2: =IFERROR(VLOOKUP($A2,'Base Tratada'!$A$2:$AD$577,9,FALSE),"—") | H2: =IF($A2="","",IFERROR(VLOOKUP($A2,'Base Tratada'!$A$2:$AD$577,18,FALSE),0)&" matrícula(s) · "&IFERROR(VLOOKUP($A2,'Base Tratada'!$A$2:$AD$577,17,FALSE),0)&" turma(s)") | I2: =IF($C2="","",IFERROR(VLOOKUP($C2,'Panorama Municipal'!$A$2:$N$228,2,FALSE),0)&" alunos (estadual "&IFERROR(VLOOKUP($C2,'Panorama Municipal'!$A$2:$N$228,4,FALSE),0)&" + outras redes "&IFERROR(VLOOKUP($C2,'Panorama Municipal'!$A$2:$N$228,6,FALSE),0)&")") | J2: =IF($C2="","",IFERROR(VLOOKUP($C2,'Panorama Municipal'!$A$2:$N$228,7,FALSE),0)&" alunos → "&IFERROR(VLOOKUP($C2,'Panorama Municipal'!$A$2:$N$228,8,FALSE),0)&" turma(s) necessária(s)") | K2: =IF($C2="","",IF(IFERROR(VLOOKUP($C2,'Panorama Municipal'!$A$2:$N$228,13,FALSE),"")="","—",IF(IFERROR(VLOOKUP($C2,'Panorama Municipal'!$A$2:$N$228,13,FALSE),"")>0,"FALTAM DISTRIBUIR "&IFERROR(VLOOKUP($C2,'Panorama Municipal'!$A$2:$N$228,13,FALSE),"")&" TURMA(S)",IF(IFERROR(VLOOKUP($C2,'Panorama Municipal'!$A$2:$N$228,13,FALSE),"")=0,"DEMANDA MUNICIPAL ATENDIDA","EXCEDE A DEMANDA EM "&ABS(IFERROR(VLOOKUP($C2,'Panorama Municipal'!$A$2:$N$228,13,FALSE),""))&" TURMA(S)")))) | M2: =IFERROR(IF(N(VLOOKUP($C2,'IDEB Municípios'!$A$2:$F$228,2,FALSE))=0,"— sem IDEB cadastrado",VLOOKUP($C2,'IDEB Municípios'!$A$2:$F$228,2,FALSE)),"— sem IDEB cadastrado") | N2: 3 | O2: 3 | P2: =IFERROR(VLOOKUP($A2,'Base Tratada'!$A$2:$AD$577,3,FALSE),"—") | S2: 3 | T2: 3 | U2: =IFERROR(VLOOKUP($A2,'Base Tratada'!$A$2:$AD$577,19,FALSE),0) | V2: =IFERROR(VLOOKUP($A2,'Base Tratada'!$A$2:$AD$577,21,FALSE),"—") | W2: =IFERROR(VLOOKUP($A2,'Base Tratada'!$A$2:$AD$577,20,FALSE),0) | X2: =IFERROR(VLOOKUP($A2,'Base Tratada'!$A$2:$AD$577,10,FALSE),"—") | Z2: =IFERROR(VLOOKUP($A2,'Base Tratada'!$A$2:$AD$577,11,FALSE),"—") | AA2: =IFERROR(IF(COUNTIF('Fusão Entre Escolas'!$F$2:$F$139,$A2)+COUNTIF('Fusão Entre Escolas'!$N$2:$N$139,$A2)=0,"Nenhuma fusão sugerida",IFERROR(VLOOKUP($A2,'Base Tratada'!$A$2:$AD$577,25,FALSE),"—")),"—") | AC2: =IFERROR(VLOOKUP($A2,'Base GDI'!$A$2:$AL$1501,6,FALSE),"") | AD2: =IF($A2="","",MAX(0,IFERROR(VLOOKUP($A2,'Base Tratada'!$A$2:$AD$577,28,FALSE),0)+($O2-IFERROR(VLOOKUP($A2,'Base Tratada'!$A$2:$AD$577,4,FALSE),0))+($S2-IFERROR(VLOOKUP($A2,'Base Tratada'!$A$2:$AD$577,5,FALSE),0))+($T2-IFERROR(VLOOKUP($A2,'Base Tratada'!$A$2:$AD$577,6,FALSE),0)))) | AE2: 12 | AF2: =IF($AE2="","",IF($AC2>$AE2,($AC2-$AE2)&" SALA(S) OCIOSA(S)",IF($AC2<$AE2,"CONSTRUIR "&($AE2-$AC2)&" SALA(S)","QUANTIDADE ADEQUADA"))) | AG2: =IFERROR(VLOOKUP($A2,'Base Tratada'!$A$2:$AD$577,7,FALSE),"—") | AH2: =IFERROR(VLOOKUP($A2,'Base Tratada'!$A$2:$AD$577,16,FALSE),"—") | AI2: =IFERROR(VLOOKUP($A2,'Base Tratada'!$A$2:$AD$577,22,FALSE),"—") | AL2: =IFERROR(VLOOKUP($A2,'Base Tratada'!$A$2:$AD$577,26,FALSE),"—") | AM2: =IFERROR(VLOOKUP($A2,'Base Tratada'!$A$2:$AD$577,27,FALSE),0) | AQ2: =IF($A2="","",$O2&" de 1ª | "&$S2&" de 2ª | "&$T2&" de 3ª | UETEP "&$W2&" | Necessidade: "&$AE2&" salas | "&$AF2) | AR2: =IFERROR(VLOOKUP($A2,'Base GDI'!$A$2:$AL$1501,18,FALSE),"—")
A3: 22012419 | B3: =IFERROR(VLOOKUP($A3,'Base GDI'!$A$2:$AL$1501,3,FALSE),"") | C3: BURITI DOS LOPES | D3: =IFERROR(VLOOKUP($A3,'Base GDI'!$A$2:$AL$1501,5,FALSE),"") | E3: =IFERROR(VLOOKUP($A3,'Base GDI'!$A$2:$AL$1501,14,FALSE),"") | F3: =IFERROR(VLOOKUP($A3,'Base GDI'!$A$2:$AL$1501,15,FALSE),"") | G3: =IFERROR(VLOOKUP($A3,'Base Tratada'!$A$2:$AD$577,9,FALSE),"—") | H3: =IF($A3="","",IFERROR(VLOOKUP($A3,'Base Tratada'!$A$2:$AD$577,18,FALSE),0)&" matrícula(s) · "&IFERROR(VLOOKUP($A3,'Base Tratada'!$A$2:$AD$577,17,FALSE),0)&" turma(s)") | I3: =IF($C3="","",IFERROR(VLOOKUP($C3,'Panorama Municipal'!$A$2:$N$228,2,FALSE),0)&" alunos (estadual "&IFERROR(VLOOKUP($C3,'Panorama Municipal'!$A$2:$N$228,4,FALSE),0)&" + outras redes "&IFERROR(VLOOKUP($C3,'Panorama Municipal'!$A$2:$N$228,6,FALSE),0)&")") | J3: =IF($C3="","",IFERROR(VLOOKUP($C3,'Panorama Municipal'!$A$2:$N$228,7,FALSE),0)&" alunos → "&IFERROR(VLOOKUP($C3,'Panorama Municipal'!$A$2:$N$228,8,FALSE),0)&" turma(s) necessária(s)") | K3: =IF($C3="","",IF(IFERROR(VLOOKUP($C3,'Panorama Municipal'!$A$2:$N$228,13,FALSE),"")="","—",IF(IFERROR(VLOOKUP($C3,'Panorama Municipal'!$A$2:$N$228,13,FALSE),"")>0,"FALTAM DISTRIBUIR "&IFERROR(VLOOKUP($C3,'Panorama Municipal'!$A$2:$N$228,13,FALSE),"")&" TURMA(S)",IF(IFERROR(VLOOKUP($C3,'Panorama Municipal'!$A$2:$N$228,13,FALSE),"")=0,"DEMANDA MUNICIPAL ATENDIDA","EXCEDE A DEMANDA EM "&ABS(IFERROR(VLOOKUP($C3,'Panorama Municipal'!$A$2:$N$228,13,FALSE),""))&" TURMA(S)")))) | M3: =IFERROR(IF(N(VLOOKUP($C3,'IDEB Municípios'!$A$2:$F$228,2,FALSE))=0,"— sem IDEB cadastrado",VLOOKUP($C3,'IDEB Municípios'!$A$2:$F$228,2,FALSE)),"— sem IDEB cadastrado") | N3: 2 | O3: 2 | P3: =IFERROR(VLOOKUP($A3,'Base Tratada'!$A$2:$AD$577,3,FALSE),"—") | S3: 2 | T3: 2 | U3: =IFERROR(VLOOKUP($A3,'Base Tratada'!$A$2:$AD$577,19,FALSE),0) | V3: =IFERROR(VLOOKUP($A3,'Base Tratada'!$A$2:$AD$577,21,FALSE),"—") | W3: =IFERROR(VLOOKUP($A3,'Base Tratada'!$A$2:$AD$577,20,FALSE),0) | X3: =IFERROR(VLOOKUP($A3,'Base Tratada'!$A$2:$AD$577,10,FALSE),"—") | Z3: =IFERROR(VLOOKUP($A3,'Base Tratada'!$A$2:$AD$577,11,FALSE),"—") | AA3: =IFERROR(IF(COUNTIF('Fusão Entre Escolas'!$F$2:$F$139,$A3)+COUNTIF('Fusão Entre Escolas'!$N$2:$N$139,$A3)=0,"Nenhuma fusão sugerida",IFERROR(VLOOKUP($A3,'Base Tratada'!$A$2:$AD$577,25,FALSE),"—")),"—") | AC3: =IFERROR(VLOOKUP($A3,'Base GDI'!$A$2:$AL$1501,6,FALSE),"") | AD3: =IF($A3="","",MAX(0,IFERROR(VLOOKUP($A3,'Base Tratada'!$A$2:$AD$577,28,FALSE),0)+($O3-IFERROR(VLOOKUP($A3,'Base Tratada'!$A$2:$AD$577,4,FALSE),0))+($S3-IFERROR(VLOOKUP($A3,'Base Tratada'!$A$2:$AD$577,5,FALSE),0))+($T3-IFERROR(VLOOKUP($A3,'Base Tratada'!$A$2:$AD$577,6,FALSE),0)))) | AE3: 8 | AF3: =IF($AE3="","",IF($AC3>$AE3,($AC3-$AE3)&" SALA(S) OCIOSA(S)",IF($AC3<$AE3,"CONSTRUIR "&($AE3-$AC3)&" SALA(S)","QUANTIDADE ADEQUADA"))) | AG3: =IFERROR(VLOOKUP($A3,'Base Tratada'!$A$2:$AD$577,7,FALSE),"—") | AH3: =IFERROR(VLOOKUP($A3,'Base Tratada'!$A$2:$AD$577,16,FALSE),"—") | AI3: =IFERROR(VLOOKUP($A3,'Base Tratada'!$A$2:$AD$577,22,FALSE),"—") | AL3: =IFERROR(VLOOKUP($A3,'Base Tratada'!$A$2:$AD$577,26,FALSE),"—") | AM3: =IFERROR(VLOOKUP($A3,'Base Tratada'!$A$2:$AD$577,27,FALSE),0) | AQ3: =IF($A3="","",$O3&" de 1ª | "&$S3&" de 2ª | "&$T3&" de 3ª | UETEP "&$W3&" | Necessidade: "&$AE3&" salas | "&$AF3) | AR3: =IFERROR(VLOOKUP($A3,'Base GDI'!$A$2:$AL$1501,18,FALSE),"—")
A4: 22012508 | B4: =IFERROR(VLOOKUP($A4,'Base GDI'!$A$2:$AL$1501,3,FALSE),"") | C4: BURITI DOS LOPES | D4: =IFERROR(VLOOKUP($A4,'Base GDI'!$A$2:$AL$1501,5,FALSE),"") | E4: =IFERROR(VLOOKUP($A4,'Base GDI'!$A$2:$AL$1501,14,FALSE),"") | F4: =IFERROR(VLOOKUP($A4,'Base GDI'!$A$2:$AL$1501,15,FALSE),"") | G4: =IFERROR(VLOOKUP($A4,'Base Tratada'!$A$2:$AD$577,9,FALSE),"—") | H4: =IF($A4="","",IFERROR(VLOOKUP($A4,'Base Tratada'!$A$2:$AD$577,18,FALSE),0)&" matrícula(s) · "&IFERROR(VLOOKUP($A4,'Base Tratada'!$A$2:$AD$577,17,FALSE),0)&" turma(s)") | I4: =IF($C4="","",IFERROR(VLOOKUP($C4,'Panorama Municipal'!$A$2:$N$228,2,FALSE),0)&" alunos (estadual "&IFERROR(VLOOKUP($C4,'Panorama Municipal'!$A$2:$N$228,4,FALSE),0)&" + outras redes "&IFERROR(VLOOKUP($C4,'Panorama Municipal'!$A$2:$N$228,6,FALSE),0)&")") | J4: =IF($C4="","",IFERROR(VLOOKUP($C4,'Panorama Municipal'!$A$2:$N$228,7,FALSE),0)&" alunos → "&IFERROR(VLOOKUP($C4,'Panorama Municipal'!$A$2:$N$228,8,FALSE),0)&" turma(s) necessária(s)") | K4: =IF($C4="","",IF(IFERROR(VLOOKUP($C4,'Panorama Municipal'!$A$2:$N$228,13,FALSE),"")="","—",IF(IFERROR(VLOOKUP($C4,'Panorama Municipal'!$A$2:$N$228,13,FALSE),"")>0,"FALTAM DISTRIBUIR "&IFERROR(VLOOKUP($C4,'Panorama Municipal'!$A$2:$N$228,13,FALSE),"")&" TURMA(S)",IF(IFERROR(VLOOKUP($C4,'Panorama Municipal'!$A$2:$N$228,13,FALSE),"")=0,"DEMANDA MUNICIPAL ATENDIDA","EXCEDE A DEMANDA EM "&ABS(IFERROR(VLOOKUP($C4,'Panorama Municipal'!$A$2:$N$228,13,FALSE),""))&" TURMA(S)")))) | M4: =IFERROR(IF(N(VLOOKUP($C4,'IDEB Municípios'!$A$2:$F$228,2,FALSE))=0,"— sem IDEB cadastrado",VLOOKUP($C4,'IDEB Municípios'!$A$2:$F$228,2,FALSE)),"— sem IDEB cadastrado") | N4: 0 | O4: 0 | P4: =IFERROR(VLOOKUP($A4,'Base Tratada'!$A$2:$AD$577,3,FALSE),"—") | S4: 0 | T4: 0 | U4: =IFERROR(VLOOKUP($A4,'Base Tratada'!$A$2:$AD$577,19,FALSE),0) | V4: =IFERROR(VLOOKUP($A4,'Base Tratada'!$A$2:$AD$577,21,FALSE),"—") | W4: =IFERROR(VLOOKUP($A4,'Base Tratada'!$A$2:$AD$577,20,FALSE),0) | X4: =IFERROR(VLOOKUP($A4,'Base Tratada'!$A$2:$AD$577,10,FALSE),"—") | Z4: =IFERROR(VLOOKUP($A4,'Base Tratada'!$A$2:$AD$577,11,FALSE),"—") | AA4: =IFERROR(IF(COUNTIF('Fusão Entre Escolas'!$F$2:$F$139,$A4)+COUNTIF('Fusão Entre Escolas'!$N$2:$N$139,$A4)=0,"Nenhuma fusão sugerida",IFERROR(VLOOKUP($A4,'Base Tratada'!$A$2:$AD$577,25,FALSE),"—")),"—") | AC4: =IFERROR(VLOOKUP($A4,'Base GDI'!$A$2:$AL$1501,6,FALSE),"") | AD4: =IF($A4="","",MAX(0,IFERROR(VLOOKUP($A4,'Base Tratada'!$A$2:$AD$577,28,FALSE),0)+($O4-IFERROR(VLOOKUP($A4,'Base Tratada'!$A$2:$AD$577,4,FALSE),0))+($S4-IFERROR(VLOOKUP($A4,'Base Tratada'!$A$2:$AD$577,5,FALSE),0))+($T4-IFERROR(VLOOKUP($A4,'Base Tratada'!$A$2:$AD$577,6,FALSE),0)))) | AE4: 0 | AF4: =IF($AE4="","",IF($AC4>$AE4,($AC4-$AE4)&" SALA(S) OCIOSA(S)",IF($AC4<$AE4,"CONSTRUIR "&($AE4-$AC4)&" SALA(S)","QUANTIDADE ADEQUADA"))) | AG4: =IFERROR(VLOOKUP($A4,'Base Tratada'!$A$2:$AD$577,7,FALSE),"—") | AH4: =IFERROR(VLOOKUP($A4,'Base Tratada'!$A$2:$AD$577,16,FALSE),"—") | AI4: =IFERROR(VLOOKUP($A4,'Base Tratada'!$A$2:$AD$577,22,FALSE),"—") | AL4: =IFERROR(VLOOKUP($A4,'Base Tratada'!$A$2:$AD$577,26,FALSE),"—") | AM4: =IFERROR(VLOOKUP($A4,'Base Tratada'!$A$2:$AD$577,27,FALSE),0) | AQ4: =IF($A4="","",$O4&" de 1ª | "&$S4&" de 2ª | "&$T4&" de 3ª | UETEP "&$W4&" | Necessidade: "&$AE4&" salas | "&$AF4) | AR4: =IFERROR(VLOOKUP($A4,'Base GDI'!$A$2:$AL$1501,18,FALSE),"—")
A5: 22137947 | B5: =IFERROR(VLOOKUP($A5,'Base GDI'!$A$2:$AL$1501,3,FALSE),"") | C5: BURITI DOS LOPES | D5: =IFERROR(VLOOKUP($A5,'Base GDI'!$A$2:$AL$1501,5,FALSE),"") | E5: =IFERROR(VLOOKUP($A5,'Base GDI'!$A$2:$AL$1501,14,FALSE),"") | F5: =IFERROR(VLOOKUP($A5,'Base GDI'!$A$2:$AL$1501,15,FALSE),"") | G5: =IFERROR(VLOOKUP($A5,'Base Tratada'!$A$2:$AD$577,9,FALSE),"—") | H5: =IF($A5="","",IFERROR(VLOOKUP($A5,'Base Tratada'!$A$2:$AD$577,18,FALSE),0)&" matrícula(s) · "&IFERROR(VLOOKUP($A5,'Base Tratada'!$A$2:$AD$577,17,FALSE),0)&" turma(s)") | I5: =IF($C5="","",IFERROR(VLOOKUP($C5,'Panorama Municipal'!$A$2:$N$228,2,FALSE),0)&" alunos (estadual "&IFERROR(VLOOKUP($C5,'Panorama Municipal'!$A$2:$N$228,4,FALSE),0)&" + outras redes "&IFERROR(VLOOKUP($C5,'Panorama Municipal'!$A$2:$N$228,6,FALSE),0)&")") | J5: =IF($C5="","",IFERROR(VLOOKUP($C5,'Panorama Municipal'!$A$2:$N$228,7,FALSE),0)&" alunos → "&IFERROR(VLOOKUP($C5,'Panorama Municipal'!$A$2:$N$228,8,FALSE),0)&" turma(s) necessária(s)") | K5: =IF($C5="","",IF(IFERROR(VLOOKUP($C5,'Panorama Municipal'!$A$2:$N$228,13,FALSE),"")="","—",IF(IFERROR(VLOOKUP($C5,'Panorama Municipal'!$A$2:$N$228,13,FALSE),"")>0,"FALTAM DISTRIBUIR "&IFERROR(VLOOKUP($C5,'Panorama Municipal'!$A$2:$N$228,13,FALSE),"")&" TURMA(S)",IF(IFERROR(VLOOKUP($C5,'Panorama Municipal'!$A$2:$N$228,13,FALSE),"")=0,"DEMANDA MUNICIPAL ATENDIDA","EXCEDE A DEMANDA EM "&ABS(IFERROR(VLOOKUP($C5,'Panorama Municipal'!$A$2:$N$228,13,FALSE),""))&" TURMA(S)")))) | M5: =IFERROR(IF(N(VLOOKUP($C5,'IDEB Municípios'!$A$2:$F$228,2,FALSE))=0,"— sem IDEB cadastrado",VLOOKUP($C5,'IDEB Municípios'!$A$2:$F$228,2,FALSE)),"— sem IDEB cadastrado") | N5: 5 | O5: 5 | P5: =IFERROR(VLOOKUP($A5,'Base Tratada'!$A$2:$AD$577,3,FALSE),"—") | S5: 5 | T5: 4 | U5: =IFERROR(VLOOKUP($A5,'Base Tratada'!$A$2:$AD$577,19,FALSE),0) | V5: =IFERROR(VLOOKUP($A5,'Base Tratada'!$A$2:$AD$577,21,FALSE),"—") | W5: =IFERROR(VLOOKUP($A5,'Base Tratada'!$A$2:$AD$577,20,FALSE),0) | X5: =IFERROR(VLOOKUP($A5,'Base Tratada'!$A$2:$AD$577,10,FALSE),"—") | Z5: =IFERROR(VLOOKUP($A5,'Base Tratada'!$A$2:$AD$577,11,FALSE),"—") | AA5: =IFERROR(IF(COUNTIF('Fusão Entre Escolas'!$F$2:$F$139,$A5)+COUNTIF('Fusão Entre Escolas'!$N$2:$N$139,$A5)=0,"Nenhuma fusão sugerida",IFERROR(VLOOKUP($A5,'Base Tratada'!$A$2:$AD$577,25,FALSE),"—")),"—") | AC5: =IFERROR(VLOOKUP($A5,'Base GDI'!$A$2:$AL$1501,6,FALSE),"") | AD5: =IF($A5="","",MAX(0,IFERROR(VLOOKUP($A5,'Base Tratada'!$A$2:$AD$577,28,FALSE),0)+($O5-IFERROR(VLOOKUP($A5,'Base Tratada'!$A$2:$AD$577,4,FALSE),0))+($S5-IFERROR(VLOOKUP($A5,'Base Tratada'!$A$2:$AD$577,5,FALSE),0))+($T5-IFERROR(VLOOKUP($A5,'Base Tratada'!$A$2:$AD$577,6,FALSE),0)))) | AE5: 14 | AF5: =IF($AE5="","",IF($AC5>$AE5,($AC5-$AE5)&" SALA(S) OCIOSA(S)",IF($AC5<$AE5,"CONSTRUIR "&($AE5-$AC5)&" SALA(S)","QUANTIDADE ADEQUADA"))) | AG5: =IFERROR(VLOOKUP($A5,'Base Tratada'!$A$2:$AD$577,7,FALSE),"—") | AH5: =IFERROR(VLOOKUP($A5,'Base Tratada'!$A$2:$AD$577,16,FALSE),"—") | AI5: =IFERROR(VLOOKUP($A5,'Base Tratada'!$A$2:$AD$577,22,FALSE),"—") | AL5: =IFERROR(VLOOKUP($A5,'Base Tratada'!$A$2:$AD$577,26,FALSE),"—") | AM5: =IFERROR(VLOOKUP($A5,'Base Tratada'!$A$2:$AD$577,27,FALSE),0) | AQ5: =IF($A5="","",$O5&" de 1ª | "&$S5&" de 2ª | "&$T5&" de 3ª | UETEP "&$W5&" | Necessidade: "&$AE5&" salas | "&$AF5) | AR5: =IFERROR(VLOOKUP($A5,'Base GDI'!$A$2:$AL$1501,18,FALSE),"—")
A6: 22162607 | B6: =IFERROR(VLOOKUP($A6,'Base GDI'!$A$2:$AL$1501,3,FALSE),"") | C6: BURITI DOS LOPES | D6: =IFERROR(VLOOKUP($A6,'Base GDI'!$A$2:$AL$1501,5,FALSE),"") | E6: =IFERROR(VLOOKUP($A6,'Base GDI'!$A$2:$AL$1501,14,FALSE),"") | F6: =IFERROR(VLOOKUP($A6,'Base GDI'!$A$2:$AL$1501,15,FALSE),"") | G6: =IFERROR(VLOOKUP($A6,'Base Tratada'!$A$2:$AD$577,9,FALSE),"—") | H6: =IF($A6="","",IFERROR(VLOOKUP($A6,'Base Tratada'!$A$2:$AD$577,18,FALSE),0)&" matrícula(s) · "&IFERROR(VLOOKUP($A6,'Base Tratada'!$A$2:$AD$577,17,FALSE),0)&" turma(s)") | I6: =IF($C6="","",IFERROR(VLOOKUP($C6,'Panorama Municipal'!$A$2:$N$228,2,FALSE),0)&" alunos (estadual "&IFERROR(VLOOKUP($C6,'Panorama Municipal'!$A$2:$N$228,4,FALSE),0)&" + outras redes "&IFERROR(VLOOKUP($C6,'Panorama Municipal'!$A$2:$N$228,6,FALSE),0)&")") | J6: =IF($C6="","",IFERROR(VLOOKUP($C6,'Panorama Municipal'!$A$2:$N$228,7,FALSE),0)&" alunos → "&IFERROR(VLOOKUP($C6,'Panorama Municipal'!$A$2:$N$228,8,FALSE),0)&" turma(s) necessária(s)") | K6: =IF($C6="","",IF(IFERROR(VLOOKUP($C6,'Panorama Municipal'!$A$2:$N$228,13,FALSE),"")="","—",IF(IFERROR(VLOOKUP($C6,'Panorama Municipal'!$A$2:$N$228,13,FALSE),"")>0,"FALTAM DISTRIBUIR "&IFERROR(VLOOKUP($C6,'Panorama Municipal'!$A$2:$N$228,13,FALSE),"")&" TURMA(S)",IF(IFERROR(VLOOKUP($C6,'Panorama Municipal'!$A$2:$N$228,13,FALSE),"")=0,"DEMANDA MUNICIPAL ATENDIDA","EXCEDE A DEMANDA EM "&ABS(IFERROR(VLOOKUP($C6,'Panorama Municipal'!$A$2:$N$228,13,FALSE),""))&" TURMA(S)")))) | M6: =IFERROR(IF(N(VLOOKUP($C6,'IDEB Municípios'!$A$2:$F$228,2,FALSE))=0,"— sem IDEB cadastrado",VLOOKUP($C6,'IDEB Municípios'!$A$2:$F$228,2,FALSE)),"— sem IDEB cadastrado") | N6: 2 | O6: 2 | P6: =IFERROR(VLOOKUP($A6,'Base Tratada'!$A$2:$AD$577,3,FALSE),"—") | S6: 2 | T6: 2 | U6: =IFERROR(VLOOKUP($A6,'Base Tratada'!$A$2:$AD$577,19,FALSE),0) | V6: =IFERROR(VLOOKUP($A6,'Base Tratada'!$A$2:$AD$577,21,FALSE),"—") | W6: =IFERROR(VLOOKUP($A6,'Base Tratada'!$A$2:$AD$577,20,FALSE),0) | X6: =IFERROR(VLOOKUP($A6,'Base Tratada'!$A$2:$AD$577,10,FALSE),"—") | Z6: =IFERROR(VLOOKUP($A6,'Base Tratada'!$A$2:$AD$577,11,FALSE),"—") | AA6: =IFERROR(IF(COUNTIF('Fusão Entre Escolas'!$F$2:$F$139,$A6)+COUNTIF('Fusão Entre Escolas'!$N$2:$N$139,$A6)=0,"Nenhuma fusão sugerida",IFERROR(VLOOKUP($A6,'Base Tratada'!$A$2:$AD$577,25,FALSE),"—")),"—") | AC6: =IFERROR(VLOOKUP($A6,'Base GDI'!$A$2:$AL$1501,6,FALSE),"") | AD6: =IF($A6="","",MAX(0,IFERROR(VLOOKUP($A6,'Base Tratada'!$A$2:$AD$577,28,FALSE),0)+($O6-IFERROR(VLOOKUP($A6,'Base Tratada'!$A$2:$AD$577,4,FALSE),0))+($S6-IFERROR(VLOOKUP($A6,'Base Tratada'!$A$2:$AD$577,5,FALSE),0))+($T6-IFERROR(VLOOKUP($A6,'Base Tratada'!$A$2:$AD$577,6,FALSE),0)))) | AE6: 8 | AF6: =IF($AE6="","",IF($AC6>$AE6,($AC6-$AE6)&" SALA(S) OCIOSA(S)",IF($AC6<$AE6,"CONSTRUIR "&($AE6-$AC6)&" SALA(S)","QUANTIDADE ADEQUADA"))) | AG6: =IFERROR(VLOOKUP($A6,'Base Tratada'!$A$2:$AD$577,7,FALSE),"—") | AH6: =IFERROR(VLOOKUP($A6,'Base Tratada'!$A$2:$AD$577,16,FALSE),"—") | AI6: =IFERROR(VLOOKUP($A6,'Base Tratada'!$A$2:$AD$577,22,FALSE),"—") | AL6: =IFERROR(VLOOKUP($A6,'Base Tratada'!$A$2:$AD$577,26,FALSE),"—") | AM6: =IFERROR(VLOOKUP($A6,'Base Tratada'!$A$2:$AD$577,27,FALSE),0) | AQ6: =IF($A6="","",$O6&" de 1ª | "&$S6&" de 2ª | "&$T6&" de 3ª | UETEP "&$W6&" | Necessidade: "&$AE6&" salas | "&$AF6) | AR6: =IFERROR(VLOOKUP($A6,'Base GDI'!$A$2:$AL$1501,18,FALSE),"—")
A7: 22014306 | B7: =IFERROR(VLOOKUP($A7,'Base GDI'!$A$2:$AL$1501,3,FALSE),"") | C7: CAJUEIRO DA PRAIA | D7: =IFERROR(VLOOKUP($A7,'Base GDI'!$A$2:$AL$1501,5,FALSE),"") | E7: =IFERROR(VLOOKUP($A7,'Base GDI'!$A$2:$AL$1501,14,FALSE),"") | F7: =IFERROR(VLOOKUP($A7,'Base GDI'!$A$2:$AL$1501,15,FALSE),"") | G7: =IFERROR(VLOOKUP($A7,'Base Tratada'!$A$2:$AD$577,9,FALSE),"—") | H7: =IF($A7="","",IFERROR(VLOOKUP($A7,'Base Tratada'!$A$2:$AD$577,18,FALSE),0)&" matrícula(s) · "&IFERROR(VLOOKUP($A7,'Base Tratada'!$A$2:$AD$577,17,FALSE),0)&" turma(s)") | I7: =IF($C7="","",IFERROR(VLOOKUP($C7,'Panorama Municipal'!$A$2:$N$228,2,FALSE),0)&" alunos (estadual "&IFERROR(VLOOKUP($C7,'Panorama Municipal'!$A$2:$N$228,4,FALSE),0)&" + outras redes "&IFERROR(VLOOKUP($C7,'Panorama Municipal'!$A$2:$N$228,6,FALSE),0)&")") | J7: =IF($C7="","",IFERROR(VLOOKUP($C7,'Panorama Municipal'!$A$2:$N$228,7,FALSE),0)&" alunos → "&IFERROR(VLOOKUP($C7,'Panorama Municipal'!$A$2:$N$228,8,FALSE),0)&" turma(s) necessária(s)") | K7: =IF($C7="","",IF(IFERROR(VLOOKUP($C7,'Panorama Municipal'!$A$2:$N$228,13,FALSE),"")="","—",IF(IFERROR(VLOOKUP($C7,'Panorama Municipal'!$A$2:$N$228,13,FALSE),"")>0,"FALTAM DISTRIBUIR "&IFERROR(VLOOKUP($C7,'Panorama Municipal'!$A$2:$N$228,13,FALSE),"")&" TURMA(S)",IF(IFERROR(VLOOKUP($C7,'Panorama Municipal'!$A$2:$N$228,13,FALSE),"")=0,"DEMANDA MUNICIPAL ATENDIDA","EXCEDE A DEMANDA EM "&ABS(IFERROR(VLOOKUP($C7,'Panorama Municipal'!$A$2:$N$228,13,FALSE),""))&" TURMA(S)")))) | M7: =IFERROR(IF(N(VLOOKUP($C7,'IDEB Municípios'!$A$2:$F$228,2,FALSE))=0,"— sem IDEB cadastrado",VLOOKUP($C7,'IDEB Municípios'!$A$2:$F$228,2,FALSE)),"— sem IDEB cadastrado") | N7: 3 | O7: 3 | P7: =IFERROR(VLOOKUP($A7,'Base Tratada'!$A$2:$AD$577,3,FALSE),"—") | S7: 3 | T7: 3 | U7: =IFERROR(VLOOKUP($A7,'Base Tratada'!$A$2:$AD$577,19,FALSE),0) | V7: =IFERROR(VLOOKUP($A7,'Base Tratada'!$A$2:$AD$577,21,FALSE),"—") | W7: =IFERROR(VLOOKUP($A7,'Base Tratada'!$A$2:$AD$577,20,FALSE),0) | X7: =IFERROR(VLOOKUP($A7,'Base Tratada'!$A$2:$AD$577,10,FALSE),"—") | Z7: =IFERROR(VLOOKUP($A7,'Base Tratada'!$A$2:$AD$577,11,FALSE),"—") | AA7: =IFERROR(IF(COUNTIF('Fusão Entre Escolas'!$F$2:$F$139,$A7)+COUNTIF('Fusão Entre Escolas'!$N$2:$N$139,$A7)=0,"Nenhuma fusão sugerida",IFERROR(VLOOKUP($A7,'Base Tratada'!$A$2:$AD$577,25,FALSE),"—")),"—") | AC7: =IFERROR(VLOOKUP($A7,'Base GDI'!$A$2:$AL$1501,6,FALSE),"") | AD7: =IF($A7="","",MAX(0,IFERROR(VLOOKUP($A7,'Base Tratada'!$A$2:$AD$577,28,FALSE),0)+($O7-IFERROR(VLOOKUP($A7,'Base Tratada'!$A$2:$AD$577,4,FALSE),0))+($S7-IFERROR(VLOOKUP($A7,'Base Tratada'!$A$2:$AD$577,5,FALSE),0))+($T7-IFERROR(VLOOKUP($A7,'Base Tratada'!$A$2:$AD$577,6,FALSE),0)))) | AE7: 11 | AF7: =IF($AE7="","",IF($AC7>$AE7,($AC7-$AE7)&" SALA(S) OCIOSA(S)",IF($AC7<$AE7,"CONSTRUIR "&($AE7-$AC7)&" SALA(S)","QUANTIDADE ADEQUADA"))) | AG7: =IFERROR(VLOOKUP($A7,'Base Tratada'!$A$2:$AD$577,7,FALSE),"—") | AH7: =IFERROR(VLOOKUP($A7,'Base Tratada'!$A$2:$AD$577,16,FALSE),"—") | AI7: =IFERROR(VLOOKUP($A7,'Base Tratada'!$A$2:$AD$577,22,FALSE),"—") | AL7: =IFERROR(VLOOKUP($A7,'Base Tratada'!$A$2:$AD$577,26,FALSE),"—") | AM7: =IFERROR(VLOOKUP($A7,'Base Tratada'!$A$2:$AD$577,27,FALSE),0) | AQ7: =IF($A7="","",$O7&" de 1ª | "&$S7&" de 2ª | "&$T7&" de 3ª | UETEP "&$W7&" | Necessidade: "&$AE7&" salas | "&$AF7) | AR7: =IFERROR(VLOOKUP($A7,'Base GDI'!$A$2:$AL$1501,18,FALSE),"—")
A8: 22135863 | B8: =IFERROR(VLOOKUP($A8,'Base GDI'!$A$2:$AL$1501,3,FALSE),"") | C8: CARAUBAS DO PIAUI | D8: =IFERROR(VLOOKUP($A8,'Base GDI'!$A$2:$AL$1501,5,FALSE),"") | E8: =IFERROR(VLOOKUP($A8,'Base GDI'!$A$2:$AL$1501,14,FALSE),"") | F8: =IFERROR(VLOOKUP($A8,'Base GDI'!$A$2:$AL$1501,15,FALSE),"") | G8: =IFERROR(VLOOKUP($A8,'Base Tratada'!$A$2:$AD$577,9,FALSE),"—") | H8: =IF($A8="","",IFERROR(VLOOKUP($A8,'Base Tratada'!$A$2:$AD$577,18,FALSE),0)&" matrícula(s) · "&IFERROR(VLOOKUP($A8,'Base Tratada'!$A$2:$AD$577,17,FALSE),0)&" turma(s)") | I8: =IF($C8="","",IFERROR(VLOOKUP($C8,'Panorama Municipal'!$A$2:$N$228,2,FALSE),0)&" alunos (estadual "&IFERROR(VLOOKUP($C8,'Panorama Municipal'!$A$2:$N$228,4,FALSE),0)&" + outras redes "&IFERROR(VLOOKUP($C8,'Panorama Municipal'!$A$2:$N$228,6,FALSE),0)&")") | J8: =IF($C8="","",IFERROR(VLOOKUP($C8,'Panorama Municipal'!$A$2:$N$228,7,FALSE),0)&" alunos → "&IFERROR(VLOOKUP($C8,'Panorama Municipal'!$A$2:$N$228,8,FALSE),0)&" turma(s) necessária(s)") | K8: =IF($C8="","",IF(IFERROR(VLOOKUP($C8,'Panorama Municipal'!$A$2:$N$228,13,FALSE),"")="","—",IF(IFERROR(VLOOKUP($C8,'Panorama Municipal'!$A$2:$N$228,13,FALSE),"")>0,"FALTAM DISTRIBUIR "&IFERROR(VLOOKUP($C8,'Panorama Municipal'!$A$2:$N$228,13,FALSE),"")&" TURMA(S)",IF(IFERROR(VLOOKUP($C8,'Panorama Municipal'!$A$2:$N$228,13,FALSE),"")=0,"DEMANDA MUNICIPAL ATENDIDA","EXCEDE A DEMANDA EM "&ABS(IFERROR(VLOOKUP($C8,'Panorama Municipal'!$A$2:$N$228,13,FALSE),""))&" TURMA(S)")))) | M8: =IFERROR(IF(N(VLOOKUP($C8,'IDEB Municípios'!$A$2:$F$228,2,FALSE))=0,"— sem IDEB cadastrado",VLOOKUP($C8,'IDEB Municípios'!$A$2:$F$228,2,FALSE)),"— sem IDEB cadastrado") | N8: 2 | O8: 2 | P8: =IFERROR(VLOOKUP($A8,'Base Tratada'!$A$2:$AD$577,3,FALSE),"—") | S8: 2 | T8: 2 | U8: =IFERROR(VLOOKUP($A8,'Base Tratada'!$A$2:$AD$577,19,FALSE),0) | V8: =IFERROR(VLOOKUP($A8,'Base Tratada'!$A$2:$AD$577,21,FALSE),"—") | W8: =IFERROR(VLOOKUP($A8,'Base Tratada'!$A$2:$AD$577,20,FALSE),0) | X8: =IFERROR(VLOOKUP($A8,'Base Tratada'!$A$2:$AD$577,10,FALSE),"—") | Z8: =IFERROR(VLOOKUP($A8,'Base Tratada'!$A$2:$AD$577,11,FALSE),"—") | AA8: =IFERROR(IF(COUNTIF('Fusão Entre Escolas'!$F$2:$F$139,$A8)+COUNTIF('Fusão Entre Escolas'!$N$2:$N$139,$A8)=0,"Nenhuma fusão sugerida",IFERROR(VLOOKUP($A8,'Base Tratada'!$A$2:$AD$577,25,FALSE),"—")),"—") | AC8: =IFERROR(VLOOKUP($A8,'Base GDI'!$A$2:$AL$1501,6,FALSE),"") | AD8: =IF($A8="","",MAX(0,IFERROR(VLOOKUP($A8,'Base Tratada'!$A$2:$AD$577,28,FALSE),0)+($O8-IFERROR(VLOOKUP($A8,'Base Tratada'!$A$2:$AD$577,4,FALSE),0))+($S8-IFERROR(VLOOKUP($A8,'Base Tratada'!$A$2:$AD$577,5,FALSE),0))+($T8-IFERROR(VLOOKUP($A8,'Base Tratada'!$A$2:$AD$577,6,FALSE),0)))) | AE8: 7 | AF8: =IF($AE8="","",IF($AC8>$AE8,($AC8-$AE8)&" SALA(S) OCIOSA(S)",IF($AC8<$AE8,"CONSTRUIR "&($AE8-$AC8)&" SALA(S)","QUANTIDADE ADEQUADA"))) | AG8: =IFERROR(VLOOKUP($A8,'Base Tratada'!$A$2:$AD$577,7,FALSE),"—") | AH8: =IFERROR(VLOOKUP($A8,'Base Tratada'!$A$2:$AD$577,16,FALSE),"—") | AI8: =IFERROR(VLOOKUP($A8,'Base Tratada'!$A$2:$AD$577,22,FALSE),"—") | AL8: =IFERROR(VLOOKUP($A8,'Base Tratada'!$A$2:$AD$577,26,FALSE),"—") | AM8: =IFERROR(VLOOKUP($A8,'Base Tratada'!$A$2:$AD$577,27,FALSE),0) | AQ8: =IF($A8="","",$O8&" de 1ª | "&$S8&" de 2ª | "&$T8&" de 3ª | UETEP "&$W8&" | Necessidade: "&$AE8&" salas | "&$AF8) | AR8: =IFERROR(VLOOKUP($A8,'Base GDI'!$A$2:$AL$1501,18,FALSE),"—")
A9: 22135782 | B9: =IFERROR(VLOOKUP($A9,'Base GDI'!$A$2:$AL$1501,3,FALSE),"") | C9: CAXINGO | D9: =IFERROR(VLOOKUP($A9,'Base GDI'!$A$2:$AL$1501,5,FALSE),"") | E9: =IFERROR(VLOOKUP($A9,'Base GDI'!$A$2:$AL$1501,14,FALSE),"") | F9: =IFERROR(VLOOKUP($A9,'Base GDI'!$A$2:$AL$1501,15,FALSE),"") | G9: =IFERROR(VLOOKUP($A9,'Base Tratada'!$A$2:$AD$577,9,FALSE),"—") | H9: =IF($A9="","",IFERROR(VLOOKUP($A9,'Base Tratada'!$A$2:$AD$577,18,FALSE),0)&" matrícula(s) · "&IFERROR(VLOOKUP($A9,'Base Tratada'!$A$2:$AD$577,17,FALSE),0)&" turma(s)") | I9: =IF($C9="","",IFERROR(VLOOKUP($C9,'Panorama Municipal'!$A$2:$N$228,2,FALSE),0)&" alunos (estadual "&IFERROR(VLOOKUP($C9,'Panorama Municipal'!$A$2:$N$228,4,FALSE),0)&" + outras redes "&IFERROR(VLOOKUP($C9,'Panorama Municipal'!$A$2:$N$228,6,FALSE),0)&")") | J9: =IF($C9="","",IFERROR(VLOOKUP($C9,'Panorama Municipal'!$A$2:$N$228,7,FALSE),0)&" alunos → "&IFERROR(VLOOKUP($C9,'Panorama Municipal'!$A$2:$N$228,8,FALSE),0)&" turma(s) necessária(s)") | K9: =IF($C9="","",IF(IFERROR(VLOOKUP($C9,'Panorama Municipal'!$A$2:$N$228,13,FALSE),"")="","—",IF(IFERROR(VLOOKUP($C9,'Panorama Municipal'!$A$2:$N$228,13,FALSE),"")>0,"FALTAM DISTRIBUIR "&IFERROR(VLOOKUP($C9,'Panorama Municipal'!$A$2:$N$228,13,FALSE),"")&" TURMA(S)",IF(IFERROR(VLOOKUP($C9,'Panorama Municipal'!$A$2:$N$228,13,FALSE),"")=0,"DEMANDA MUNICIPAL ATENDIDA","EXCEDE A DEMANDA EM "&ABS(IFERROR(VLOOKUP($C9,'Panorama Municipal'!$A$2:$N$228,13,FALSE),""))&" TURMA(S)")))) | M9: =IFERROR(IF(N(VLOOKUP($C9,'IDEB Municípios'!$A$2:$F$228,2,FALSE))=0,"— sem IDEB cadastrado",VLOOKUP($C9,'IDEB Municípios'!$A$2:$F$228,2,FALSE)),"— sem IDEB cadastrado") | N9: 2 | O9: 2 | P9: =IFERROR(VLOOKUP($A9,'Base Tratada'!$A$2:$AD$577,3,FALSE),"—") | S9: 2 | T9: 2 | U9: =IFERROR(VLOOKUP($A9,'Base Tratada'!$A$2:$AD$577,19,FALSE),0) | V9: =IFERROR(VLOOKUP($A9,'Base Tratada'!$A$2:$AD$577,21,FALSE),"—") | W9: =IFERROR(VLOOKUP($A9,'Base Tratada'!$A$2:$AD$577,20,FALSE),0) | X9: =IFERROR(VLOOKUP($A9,'Base Tratada'!$A$2:$AD$577,10,FALSE),"—") | Z9: =IFERROR(VLOOKUP($A9,'Base Tratada'!$A$2:$AD$577,11,FALSE),"—") | AA9: =IFERROR(IF(COUNTIF('Fusão Entre Escolas'!$F$2:$F$139,$A9)+COUNTIF('Fusão Entre Escolas'!$N$2:$N$139,$A9)=0,"Nenhuma fusão sugerida",IFERROR(VLOOKUP($A9,'Base Tratada'!$A$2:$AD$577,25,FALSE),"—")),"—") | AC9: =IFERROR(VLOOKUP($A9,'Base GDI'!$A$2:$AL$1501,6,FALSE),"") | AD9: =IF($A9="","",MAX(0,IFERROR(VLOOKUP($A9,'Base Tratada'!$A$2:$AD$577,28,FALSE),0)+($O9-IFERROR(VLOOKUP($A9,'Base Tratada'!$A$2:$AD$577,4,FALSE),0))+($S9-IFERROR(VLOOKUP($A9,'Base Tratada'!$A$2:$AD$577,5,FALSE),0))+($T9-IFERROR(VLOOKUP($A9,'Base Tratada'!$A$2:$AD$577,6,FALSE),0)))) | AE9: 7 | AF9: =IF($AE9="","",IF($AC9>$AE9,($AC9-$AE9)&" SALA(S) OCIOSA(S)",IF($AC9<$AE9,"CONSTRUIR "&($AE9-$AC9)&" SALA(S)","QUANTIDADE ADEQUADA"))) | AG9: =IFERROR(VLOOKUP($A9,'Base Tratada'!$A$2:$AD$577,7,FALSE),"—") | AH9: =IFERROR(VLOOKUP($A9,'Base Tratada'!$A$2:$AD$577,16,FALSE),"—") | AI9: =IFERROR(VLOOKUP($A9,'Base Tratada'!$A$2:$AD$577,22,FALSE),"—") | AL9: =IFERROR(VLOOKUP($A9,'Base Tratada'!$A$2:$AD$577,26,FALSE),"—") | AM9: =IFERROR(VLOOKUP($A9,'Base Tratada'!$A$2:$AD$577,27,FALSE),0) | AQ9: =IF($A9="","",$O9&" de 1ª | "&$S9&" de 2ª | "&$T9&" de 3ª | UETEP "&$W9&" | Necessidade: "&$AE9&" salas | "&$AF9) | AR9: =IFERROR(VLOOKUP($A9,'Base GDI'!$A$2:$AL$1501,18,FALSE),"—")
A10: 22013555 | B10: =IFERROR(VLOOKUP($A10,'Base GDI'!$A$2:$AL$1501,3,FALSE),"") | C10: COCAL | D10: =IFERROR(VLOOKUP($A10,'Base GDI'!$A$2:$AL$1501,5,FALSE),"") | E10: =IFERROR(VLOOKUP($A10,'Base GDI'!$A$2:$AL$1501,14,FALSE),"") | F10: =IFERROR(VLOOKUP($A10,'Base GDI'!$A$2:$AL$1501,15,FALSE),"") | G10: =IFERROR(VLOOKUP($A10,'Base Tratada'!$A$2:$AD$577,9,FALSE),"—") | H10: =IF($A10="","",IFERROR(VLOOKUP($A10,'Base Tratada'!$A$2:$AD$577,18,FALSE),0)&" matrícula(s) · "&IFERROR(VLOOKUP($A10,'Base Tratada'!$A$2:$AD$577,17,FALSE),0)&" turma(s)") | I10: =IF($C10="","",IFERROR(VLOOKUP($C10,'Panorama Municipal'!$A$2:$N$228,2,FALSE),0)&" alunos (estadual "&IFERROR(VLOOKUP($C10,'Panorama Municipal'!$A$2:$N$228,4,FALSE),0)&" + outras redes "&IFERROR(VLOOKUP($C10,'Panorama Municipal'!$A$2:$N$228,6,FALSE),0)&")") | J10: =IF($C10="","",IFERROR(VLOOKUP($C10,'Panorama Municipal'!$A$2:$N$228,7,FALSE),0)&" alunos → "&IFERROR(VLOOKUP($C10,'Panorama Municipal'!$A$2:$N$228,8,FALSE),0)&" turma(s) necessária(s)") | K10: =IF($C10="","",IF(IFERROR(VLOOKUP($C10,'Panorama Municipal'!$A$2:$N$228,13,FALSE),"")="","—",IF(IFERROR(VLOOKUP($C10,'Panorama Municipal'!$A$2:$N$228,13,FALSE),"")>0,"FALTAM DISTRIBUIR "&IFERROR(VLOOKUP($C10,'Panorama Municipal'!$A$2:$N$228,13,FALSE),"")&" TURMA(S)",IF(IFERROR(VLOOKUP($C10,'Panorama Municipal'!$A$2:$N$228,13,FALSE),"")=0,"DEMANDA MUNICIPAL ATENDIDA","EXCEDE A DEMANDA EM "&ABS(IFERROR(VLOOKUP($C10,'Panorama Municipal'!$A$2:$N$228,13,FALSE),""))&" TURMA(S)")))) | M10: =IFERROR(IF(N(VLOOKUP($C10,'IDEB Municípios'!$A$2:$F$228,2,FALSE))=0,"— sem IDEB cadastrado",VLOOKUP($C10,'IDEB Municípios'!$A$2:$F$228,2,FALSE)),"— sem IDEB cadastrado") | N10: 1 | O10: 1 | P10: =IFERROR(VLOOKUP($A10,'Base Tratada'!$A$2:$AD$577,3,FALSE),"—") | S10: 1 | T10: 3 | U10: =IFERROR(VLOOKUP($A10,'Base Tratada'!$A$2:$AD$577,19,FALSE),0) | V10: =IFERROR(VLOOKUP($A10,'Base Tratada'!$A$2:$AD$577,21,FALSE),"—") | W10: =IFERROR(VLOOKUP($A10,'Base Tratada'!$A$2:$AD$577,20,FALSE),0) | X10: =IFERROR(VLOOKUP($A10,'Base Tratada'!$A$2:$AD$577,10,FALSE),"—") | Z10: =IFERROR(VLOOKUP($A10,'Base Tratada'!$A$2:$AD$577,11,FALSE),"—") | AA10: =IFERROR(IF(COUNTIF('Fusão Entre Escolas'!$F$2:$F$139,$A10)+COUNTIF('Fusão Entre Escolas'!$N$2:$N$139,$A10)=0,"Nenhuma fusão sugerida",IFERROR(VLOOKUP($A10,'Base Tratada'!$A$2:$AD$577,25,FALSE),"—")),"—") | AC10: =IFERROR(VLOOKUP($A10,'Base GDI'!$A$2:$AL$1501,6,FALSE),"") | AD10: =IF($A10="","",MAX(0,IFERROR(VLOOKUP($A10,'Base Tratada'!$A$2:$AD$577,28,FALSE),0)+($O10-IFERROR(VLOOKUP($A10,'Base Tratada'!$A$2:$AD$577,4,FALSE),0))+($S10-IFERROR(VLOOKUP($A10,'Base Tratada'!$A$2:$AD$577,5,FALSE),0))+($T10-IFERROR(VLOOKUP($A10,'Base Tratada'!$A$2:$AD$577,6,FALSE),0)))) | AE10: 6 | AF10: =IF($AE10="","",IF($AC10>$AE10,($AC10-$AE10)&" SALA(S) OCIOSA(S)",IF($AC10<$AE10,"CONSTRUIR "&($AE10-$AC10)&" SALA(S)","QUANTIDADE ADEQUADA"))) | AG10: =IFERROR(VLOOKUP($A10,'Base Tratada'!$A$2:$AD$577,7,FALSE),"—") | AH10: =IFERROR(VLOOKUP($A10,'Base Tratada'!$A$2:$AD$577,16,FALSE),"—") | AI10: =IFERROR(VLOOKUP($A10,'Base Tratada'!$A$2:$AD$577,22,FALSE),"—") | AL10: =IFERROR(VLOOKUP($A10,'Base Tratada'!$A$2:$AD$577,26,FALSE),"—") | AM10: =IFERROR(VLOOKUP($A10,'Base Tratada'!$A$2:$AD$577,27,FALSE),0) | AQ10: =IF($A10="","",$O10&" de 1ª | "&$S10&" de 2ª | "&$T10&" de 3ª | UETEP "&$W10&" | Necessidade: "&$AE10&" salas | "&$AF10) | AR10: =IFERROR(VLOOKUP($A10,'Base GDI'!$A$2:$AL$1501,18,FALSE),"—")
A11: 22013601 | B11: =IFERROR(VLOOKUP($A11,'Base GDI'!$A$2:$AL$1501,3,FALSE),"") | C11: COCAL | D11: =IFERROR(VLOOKUP($A11,'Base GDI'!$A$2:$AL$1501,5,FALSE),"") | E11: =IFERROR(VLOOKUP($A11,'Base GDI'!$A$2:$AL$1501,14,FALSE),"") | F11: =IFERROR(VLOOKUP($A11,'Base GDI'!$A$2:$AL$1501,15,FALSE),"") | G11: =IFERROR(VLOOKUP($A11,'Base Tratada'!$A$2:$AD$577,9,FALSE),"—") | H11: =IF($A11="","",IFERROR(VLOOKUP($A11,'Base Tratada'!$A$2:$AD$577,18,FALSE),0)&" matrícula(s) · "&IFERROR(VLOOKUP($A11,'Base Tratada'!$A$2:$AD$577,17,FALSE),0)&" turma(s)") | I11: =IF($C11="","",IFERROR(VLOOKUP($C11,'Panorama Municipal'!$A$2:$N$228,2,FALSE),0)&" alunos (estadual "&IFERROR(VLOOKUP($C11,'Panorama Municipal'!$A$2:$N$228,4,FALSE),0)&" + outras redes "&IFERROR(VLOOKUP($C11,'Panorama Municipal'!$A$2:$N$228,6,FALSE),0)&")") | J11: =IF($C11="","",IFERROR(VLOOKUP($C11,'Panorama Municipal'!$A$2:$N$228,7,FALSE),0)&" alunos → "&IFERROR(VLOOKUP($C11,'Panorama Municipal'!$A$2:$N$228,8,FALSE),0)&" turma(s) necessária(s)") | K11: =IF($C11="","",IF(IFERROR(VLOOKUP($C11,'Panorama Municipal'!$A$2:$N$228,13,FALSE),"")="","—",IF(IFERROR(VLOOKUP($C11,'Panorama Municipal'!$A$2:$N$228,13,FALSE),"")>0,"FALTAM DISTRIBUIR "&IFERROR(VLOOKUP($C11,'Panorama Municipal'!$A$2:$N$228,13,FALSE),"")&" TURMA(S)",IF(IFERROR(VLOOKUP($C11,'Panorama Municipal'!$A$2:$N$228,13,FALSE),"")=0,"DEMANDA MUNICIPAL ATENDIDA","EXCEDE A DEMANDA EM "&ABS(IFERROR(VLOOKUP($C11,'Panorama Municipal'!$A$2:$N$228,13,FALSE),""))&" TURMA(S)")))) | M11: =IFERROR(IF(N(VLOOKUP($C11,'IDEB Municípios'!$A$2:$F$228,2,FALSE))=0,"— sem IDEB cadastrado",VLOOKUP($C11,'IDEB Municípios'!$A$2:$F$228,2,FALSE)),"— sem IDEB cadastrado") | N11: 0 | O11: 0 | P11: =IFERROR(VLOOKUP($A11,'Base Tratada'!$A$2:$AD$577,3,FALSE),"—") | S11: 0 | T11: 0 | U11: =IFERROR(VLOOKUP($A11,'Base Tratada'!$A$2:$AD$577,19,FALSE),0) | V11: =IFERROR(VLOOKUP($A11,'Base Tratada'!$A$2:$AD$577,21,FALSE),"—") | W11: =IFERROR(VLOOKUP($A11,'Base Tratada'!$A$2:$AD$577,20,FALSE),0) | X11: =IFERROR(VLOOKUP($A11,'Base Tratada'!$A$2:$AD$577,10,FALSE),"—") | Z11: =IFERROR(VLOOKUP($A11,'Base Tratada'!$A$2:$AD$577,11,FALSE),"—") | AA11: =IFERROR(IF(COUNTIF('Fusão Entre Escolas'!$F$2:$F$139,$A11)+COUNTIF('Fusão Entre Escolas'!$N$2:$N$139,$A11)=0,"Nenhuma fusão sugerida",IFERROR(VLOOKUP($A11,'Base Tratada'!$A$2:$AD$577,25,FALSE),"—")),"—") | AC11: =IFERROR(VLOOKUP($A11,'Base GDI'!$A$2:$AL$1501,6,FALSE),"") | AD11: =IF($A11="","",MAX(0,IFERROR(VLOOKUP($A11,'Base Tratada'!$A$2:$AD$577,28,FALSE),0)+($O11-IFERROR(VLOOKUP($A11,'Base Tratada'!$A$2:$AD$577,4,FALSE),0))+($S11-IFERROR(VLOOKUP($A11,'Base Tratada'!$A$2:$AD$577,5,FALSE),0))+($T11-IFERROR(VLOOKUP($A11,'Base Tratada'!$A$2:$AD$577,6,FALSE),0)))) | AE11: 1 | AF11: =IF($AE11="","",IF($AC11>$AE11,($AC11-$AE11)&" SALA(S) OCIOSA(S)",IF($AC11<$AE11,"CONSTRUIR "&($AE11-$AC11)&" SALA(S)","QUANTIDADE ADEQUADA"))) | AG11: =IFERROR(VLOOKUP($A11,'Base Tratada'!$A$2:$AD$577,7,FALSE),"—") | AH11: =IFERROR(VLOOKUP($A11,'Base Tratada'!$A$2:$AD$577,16,FALSE),"—") | AI11: =IFERROR(VLOOKUP($A11,'Base Tratada'!$A$2:$AD$577,22,FALSE),"—") | AL11: =IFERROR(VLOOKUP($A11,'Base Tratada'!$A$2:$AD$577,26,FALSE),"—") | AM11: =IFERROR(VLOOKUP($A11,'Base Tratada'!$A$2:$AD$577,27,FALSE),0) | AQ11: =IF($A11="","",$O11&" de 1ª | "&$S11&" de 2ª | "&$T11&" de 3ª | UETEP "&$W11&" | Necessidade: "&$AE11&" salas | "&$AF11) | AR11: =IFERROR(VLOOKUP($A11,'Base GDI'!$A$2:$AL$1501,18,FALSE),"—")
A12: 22136037 | B12: =IFERROR(VLOOKUP($A12,'Base GDI'!$A$2:$AL$1501,3,FALSE),"") | C12: COCAL | D12: =IFERROR(VLOOKUP($A12,'Base GDI'!$A$2:$AL$1501,5,FALSE),"") | E12: =IFERROR(VLOOKUP($A12,'Base GDI'!$A$2:$AL$1501,14,FALSE),"") | F12: =IFERROR(VLOOKUP($A12,'Base GDI'!$A$2:$AL$1501,15,FALSE),"") | G12: =IFERROR(VLOOKUP($A12,'Base Tratada'!$A$2:$AD$577,9,FALSE),"—") | H12: =IF($A12="","",IFERROR(VLOOKUP($A12,'Base Tratada'!$A$2:$AD$577,18,FALSE),0)&" matrícula(s) · "&IFERROR(VLOOKUP($A12,'Base Tratada'!$A$2:$AD$577,17,FALSE),0)&" turma(s)") | I12: =IF($C12="","",IFERROR(VLOOKUP($C12,'Panorama Municipal'!$A$2:$N$228,2,FALSE),0)&" alunos (estadual "&IFERROR(VLOOKUP($C12,'Panorama Municipal'!$A$2:$N$228,4,FALSE),0)&" + outras redes "&IFERROR(VLOOKUP($C12,'Panorama Municipal'!$A$2:$N$228,6,FALSE),0)&")") | J12: =IF($C12="","",IFERROR(VLOOKUP($C12,'Panorama Municipal'!$A$2:$N$228,7,FALSE),0)&" alunos → "&IFERROR(VLOOKUP($C12,'Panorama Municipal'!$A$2:$N$228,8,FALSE),0)&" turma(s) necessária(s)") | K12: =IF($C12="","",IF(IFERROR(VLOOKUP($C12,'Panorama Municipal'!$A$2:$N$228,13,FALSE),"")="","—",IF(IFERROR(VLOOKUP($C12,'Panorama Municipal'!$A$2:$N$228,13,FALSE),"")>0,"FALTAM DISTRIBUIR "&IFERROR(VLOOKUP($C12,'Panorama Municipal'!$A$2:$N$228,13,FALSE),"")&" TURMA(S)",IF(IFERROR(VLOOKUP($C12,'Panorama Municipal'!$A$2:$N$228,13,FALSE),"")=0,"DEMANDA MUNICIPAL ATENDIDA","EXCEDE A DEMANDA EM "&ABS(IFERROR(VLOOKUP($C12,'Panorama Municipal'!$A$2:$N$228,13,FALSE),""))&" TURMA(S)")))) | M12: =IFERROR(IF(N(VLOOKUP($C12,'IDEB Municípios'!$A$2:$F$228,2,FALSE))=0,"— sem IDEB cadastrado",VLOOKUP($C12,'IDEB Municípios'!$A$2:$F$228,2,FALSE)),"— sem IDEB cadastrado") | N12: 4 | O12: 4 | P12: =IFERROR(VLOOKUP($A12,'Base Tratada'!$A$2:$AD$577,3,FALSE),"—") | S12: 4 | T12: 3 | U12: =IFERROR(VLOOKUP($A12,'Base Tratada'!$A$2:$AD$577,19,FALSE),0) | V12: =IFERROR(VLOOKUP($A12,'Base Tratada'!$A$2:$AD$577,21,FALSE),"—") | W12: =IFERROR(VLOOKUP($A12,'Base Tratada'!$A$2:$AD$577,20,FALSE),0) | X12: =IFERROR(VLOOKUP($A12,'Base Tratada'!$A$2:$AD$577,10,FALSE),"—") | Z12: =IFERROR(VLOOKUP($A12,'Base Tratada'!$A$2:$AD$577,11,FALSE),"—") | AA12: =IFERROR(IF(COUNTIF('Fusão Entre Escolas'!$F$2:$F$139,$A12)+COUNTIF('Fusão Entre Escolas'!$N$2:$N$139,$A12)=0,"Nenhuma fusão sugerida",IFERROR(VLOOKUP($A12,'Base Tratada'!$A$2:$AD$577,25,FALSE),"—")),"—") | AC12: =IFERROR(VLOOKUP($A12,'Base GDI'!$A$2:$AL$1501,6,FALSE),"") | AD12: =IF($A12="","",MAX(0,IFERROR(VLOOKUP($A12,'Base Tratada'!$A$2:$AD$577,28,FALSE),0)+($O12-IFERROR(VLOOKUP($A12,'Base Tratada'!$A$2:$AD$577,4,FALSE),0))+($S12-IFERROR(VLOOKUP($A12,'Base Tratada'!$A$2:$AD$577,5,FALSE),0))+($T12-IFERROR(VLOOKUP($A12,'Base Tratada'!$A$2:$AD$577,6,FALSE),0)))) | AE12: 12 | AF12: =IF($AE12="","",IF($AC12>$AE12,($AC12-$AE12)&" SALA(S) OCIOSA(S)",IF($AC12<$AE12,"CONSTRUIR "&($AE12-$AC12)&" SALA(S)","QUANTIDADE ADEQUADA"))) | AG12: =IFERROR(VLOOKUP($A12,'Base Tratada'!$A$2:$AD$577,7,FALSE),"—") | AH12: =IFERROR(VLOOKUP($A12,'Base Tratada'!$A$2:$AD$577,16,FALSE),"—") | AI12: =IFERROR(VLOOKUP($A12,'Base Tratada'!$A$2:$AD$577,22,FALSE),"—") | AL12: =IFERROR(VLOOKUP($A12,'Base Tratada'!$A$2:$AD$577,26,FALSE),"—") | AM12: =IFERROR(VLOOKUP($A12,'Base Tratada'!$A$2:$AD$577,27,FALSE),0) | AQ12: =IF($A12="","",$O12&" de 1ª | "&$S12&" de 2ª | "&$T12&" de 3ª | UETEP "&$W12&" | Necessidade: "&$AE12&" salas | "&$AF12) | AR12: =IFERROR(VLOOKUP($A12,'Base GDI'!$A$2:$AL$1501,18,FALSE),"—")
A13: 22140115 | B13: =IFERROR(VLOOKUP($A13,'Base GDI'!$A$2:$AL$1501,3,FALSE),"") | C13: COCAL | D13: =IFERROR(VLOOKUP($A13,'Base GDI'!$A$2:$AL$1501,5,FALSE),"") | E13: =IFERROR(VLOOKUP($A13,'Base GDI'!$A$2:$AL$1501,14,FALSE),"") | F13: =IFERROR(VLOOKUP($A13,'Base GDI'!$A$2:$AL$1501,15,FALSE),"") | G13: =IFERROR(VLOOKUP($A13,'Base Tratada'!$A$2:$AD$577,9,FALSE),"—") | H13: =IF($A13="","",IFERROR(VLOOKUP($A13,'Base Tratada'!$A$2:$AD$577,18,FALSE),0)&" matrícula(s) · "&IFERROR(VLOOKUP($A13,'Base Tratada'!$A$2:$AD$577,17,FALSE),0)&" turma(s)") | I13: =IF($C13="","",IFERROR(VLOOKUP($C13,'Panorama Municipal'!$A$2:$N$228,2,FALSE),0)&" alunos (estadual "&IFERROR(VLOOKUP($C13,'Panorama Municipal'!$A$2:$N$228,4,FALSE),0)&" + outras redes "&IFERROR(VLOOKUP($C13,'Panorama Municipal'!$A$2:$N$228,6,FALSE),0)&")") | J13: =IF($C13="","",IFERROR(VLOOKUP($C13,'Panorama Municipal'!$A$2:$N$228,7,FALSE),0)&" alunos → "&IFERROR(VLOOKUP($C13,'Panorama Municipal'!$A$2:$N$228,8,FALSE),0)&" turma(s) necessária(s)") | K13: =IF($C13="","",IF(IFERROR(VLOOKUP($C13,'Panorama Municipal'!$A$2:$N$228,13,FALSE),"")="","—",IF(IFERROR(VLOOKUP($C13,'Panorama Municipal'!$A$2:$N$228,13,FALSE),"")>0,"FALTAM DISTRIBUIR "&IFERROR(VLOOKUP($C13,'Panorama Municipal'!$A$2:$N$228,13,FALSE),"")&" TURMA(S)",IF(IFERROR(VLOOKUP($C13,'Panorama Municipal'!$A$2:$N$228,13,FALSE),"")=0,"DEMANDA MUNICIPAL ATENDIDA","EXCEDE A DEMANDA EM "&ABS(IFERROR(VLOOKUP($C13,'Panorama Municipal'!$A$2:$N$228,13,FALSE),""))&" TURMA(S)")))) | M13: =IFERROR(IF(N(VLOOKUP($C13,'IDEB Municípios'!$A$2:$F$228,2,FALSE))=0,"— sem IDEB cadastrado",VLOOKUP($C13,'IDEB Municípios'!$A$2:$F$228,2,FALSE)),"— sem IDEB cadastrado") | N13: 2 | O13: 2 | P13: =IFERROR(VLOOKUP($A13,'Base Tratada'!$A$2:$AD$577,3,FALSE),"—") | S13: 2 | T13: 1 | U13: =IFERROR(VLOOKUP($A13,'Base Tratada'!$A$2:$AD$577,19,FALSE),0) | V13: =IFERROR(VLOOKUP($A13,'Base Tratada'!$A$2:$AD$577,21,FALSE),"—") | W13: =IFERROR(VLOOKUP($A13,'Base Tratada'!$A$2:$AD$577,20,FALSE),0) | X13: =IFERROR(VLOOKUP($A13,'Base Tratada'!$A$2:$AD$577,10,FALSE),"—") | Z13: =IFERROR(VLOOKUP($A13,'Base Tratada'!$A$2:$AD$577,11,FALSE),"—") | AA13: =IFERROR(IF(COUNTIF('Fusão Entre Escolas'!$F$2:$F$139,$A13)+COUNTIF('Fusão Entre Escolas'!$N$2:$N$139,$A13)=0,"Nenhuma fusão sugerida",IFERROR(VLOOKUP($A13,'Base Tratada'!$A$2:$AD$577,25,FALSE),"—")),"—") | AC13: =IFERROR(VLOOKUP($A13,'Base GDI'!$A$2:$AL$1501,6,FALSE),"") | AD13: =IF($A13="","",MAX(0,IFERROR(VLOOKUP($A13,'Base Tratada'!$A$2:$AD$577,28,FALSE),0)+($O13-IFERROR(VLOOKUP($A13,'Base Tratada'!$A$2:$AD$577,4,FALSE),0))+($S13-IFERROR(VLOOKUP($A13,'Base Tratada'!$A$2:$AD$577,5,FALSE),0))+($T13-IFERROR(VLOOKUP($A13,'Base Tratada'!$A$2:$AD$577,6,FALSE),0)))) | AE13: 5 | AF13: =IF($AE13="","",IF($AC13>$AE13,($AC13-$AE13)&" SALA(S) OCIOSA(S)",IF($AC13<$AE13,"CONSTRUIR "&($AE13-$AC13)&" SALA(S)","QUANTIDADE ADEQUADA"))) | AG13: =IFERROR(VLOOKUP($A13,'Base Tratada'!$A$2:$AD$577,7,FALSE),"—") | AH13: =IFERROR(VLOOKUP($A13,'Base Tratada'!$A$2:$AD$577,16,FALSE),"—") | AI13: =IFERROR(VLOOKUP($A13,'Base Tratada'!$A$2:$AD$577,22,FALSE),"—") | AL13: =IFERROR(VLOOKUP($A13,'Base Tratada'!$A$2:$AD$577,26,FALSE),"—") | AM13: =IFERROR(VLOOKUP($A13,'Base Tratada'!$A$2:$AD$577,27,FALSE),0) | AQ13: =IF($A13="","",$O13&" de 1ª | "&$S13&" de 2ª | "&$T13&" de 3ª | UETEP "&$W13&" | Necessidade: "&$AE13&" salas | "&$AF13) | AR13: =IFERROR(VLOOKUP($A13,'Base GDI'!$A$2:$AL$1501,18,FALSE),"—")
... A85: 22123458 | B85: =IFERROR(VLOOKUP($A85,'Base GDI'!$A$2:$AL$1501,3,FALSE),"") | C85: PEDRO II | D85: =IFERROR(VLOOKUP($A85,'Base GDI'!$A$2:$AL$1501,5,FALSE),"") | E85: =IFERROR(VLOOKUP($A85,'Base GDI'!$A$2:$AL$1501,14,FALSE),"") | F85: =IFERROR(VLOOKUP($A85,'Base GDI'!$A$2:$AL$1501,15,FALSE),"") | G85: =IFERROR(VLOOKUP($A85,'Base Tratada'!$A$2:$AD$577,9,FALSE),"—") | H85: =IF($A85="","",IFERROR(VLOOKUP($A85,'Base Tratada'!$A$2:$AD$577,18,FALSE),0)&" matrícula(s) · "&IFERROR(VLOOKUP($A85,'Base Tratada'!$A$2:$AD$577,17,FALSE),0)&" turma(s)") | I85: =IF($C85="","",IFERROR(VLOOKUP($C85,'Panorama Municipal'!$A$2:$N$228,2,FALSE),0)&" alunos (estadual "&IFERROR(VLOOKUP($C85,'Panorama Municipal'!$A$2:$N$228,4,FALSE),0)&" + outras redes "&IFERROR(VLOOKUP($C85,'Panorama Municipal'!$A$2:$N$228,6,FALSE),0)&")") | J85: =IF($C85="","",IFERROR(VLOOKUP($C85,'Panorama Municipal'!$A$2:$N$228,7,FALSE),0)&" alunos → "&IFERROR(VLOOKUP($C85,'Panorama Municipal'!$A$2:$N$228,8,FALSE),0)&" turma(s) necessária(s)") | K85: =IF($C85="","",IF(IFERROR(VLOOKUP($C85,'Panorama Municipal'!$A$2:$N$228,13,FALSE),"")="","—",IF(IFERROR(VLOOKUP($C85,'Panorama Municipal'!$A$2:$N$228,13,FALSE),"")>0,"FALTAM DISTRIBUIR "&IFERROR(VLOOKUP($C85,'Panorama Municipal'!$A$2:$N$228,13,FALSE),"")&" TURMA(S)",IF(IFERROR(VLOOKUP($C85,'Panorama Municipal'!$A$2:$N$228,13,FALSE),"")=0,"DEMANDA MUNICIPAL ATENDIDA","EXCEDE A DEMANDA EM "&ABS(IFERROR(VLOOKUP($C85,'Panorama Municipal'!$A$2:$N$228,13,FALSE),""))&" TURMA(S)")))) | M85: =IFERROR(IF(N(VLOOKUP($C85,'IDEB Municípios'!$A$2:$F$228,2,FALSE))=0,"— sem IDEB cadastrado",VLOOKUP($C85,'IDEB Municípios'!$A$2:$F$228,2,FALSE)),"— sem IDEB cadastrado") | N85: 4 | O85: 4 | P85: =IFERROR(VLOOKUP($A85,'Base Tratada'!$A$2:$AD$577,3,FALSE),"—") | S85: 4 | T85: 4 | U85: =IFERROR(VLOOKUP($A85,'Base Tratada'!$A$2:$AD$577,19,FALSE),0) | V85: =IFERROR(VLOOKUP($A85,'Base Tratada'!$A$2:$AD$577,21,FALSE),"—") | W85: =IFERROR(VLOOKUP($A85,'Base Tratada'!$A$2:$AD$577,20,FALSE),0) | X85: =IFERROR(VLOOKUP($A85,'Base Tratada'!$A$2:$AD$577,10,FALSE),"—") | Z85: =IFERROR(VLOOKUP($A85,'Base Tratada'!$A$2:$AD$577,11,FALSE),"—") | AA85: =IFERROR(IF(COUNTIF('Fusão Entre Escolas'!$F$2:$F$139,$A85)+COUNTIF('Fusão Entre Escolas'!$N$2:$N$139,$A85)=0,"Nenhuma fusão sugerida",IFERROR(VLOOKUP($A85,'Base Tratada'!$A$2:$AD$577,25,FALSE),"—")),"—") | AC85: =IFERROR(VLOOKUP($A85,'Base GDI'!$A$2:$AL$1501,6,FALSE),"") | AD85: =IF($A85="","",MAX(0,IFERROR(VLOOKUP($A85,'Base Tratada'!$A$2:$AD$577,28,FALSE),0)+($O85-IFERROR(VLOOKUP($A85,'Base Tratada'!$A$2:$AD$577,4,FALSE),0))+($S85-IFERROR(VLOOKUP($A85,'Base Tratada'!$A$2:$AD$577,5,FALSE),0))+($T85-IFERROR(VLOOKUP($A85,'Base Tratada'!$A$2:$AD$577,6,FALSE),0)))) | AE85: 22 | AF85: =IF($AE85="","",IF($AC85>$AE85,($AC85-$AE85)&" SALA(S) OCIOSA(S)",IF($AC85<$AE85,"CONSTRUIR "&($AE85-$AC85)&" SALA(S)","QUANTIDADE ADEQUADA"))) | AG85: =IFERROR(VLOOKUP($A85,'Base Tratada'!$A$2:$AD$577,7,FALSE),"—") | AH85: =IFERROR(VLOOKUP($A85,'Base Tratada'!$A$2:$AD$577,16,FALSE),"—") | AI85: =IFERROR(VLOOKUP($A85,'Base Tratada'!$A$2:$AD$577,22,FALSE),"—") | AL85: =IFERROR(VLOOKUP($A85,'Base Tratada'!$A$2:$AD$577,26,FALSE),"—") | AM85: =IFERROR(VLOOKUP($A85,'Base Tratada'!$A$2:$AD$577,27,FALSE),0) | AQ85: =IF($A85="","",$O85&" de 1ª | "&$S85&" de 2ª | "&$T85&" de 3ª | UETEP "&$W85&" | Necessidade: "&$AE85&" salas | "&$AF85) | AR85: =IFERROR(VLOOKUP($A85,'Base GDI'!$A$2:$AL$1501,18,FALSE),"—")
